Workbook

Sheet AMC Matrix
B3: Weightage for AMC Ranking
B4: Category | C4: Weightage
B5: Market Position & Scale | C5: =SUM(C6:C7)
B6: AUM | C6: 0.15
B7: No. of Schemes | C7: 0.1
B8: Performance Metrics | C8: =SUM(C9:C11)
B9: 3-Year Return | C9: 0.15
B10: 5-Year Return | C10: 0.1
B11: 10 Year Return | C11: 0.075
B12: Risk-Adjusted Returns | C12: =SUM(C13:C15)
B13: Sharpe | C13: 0.05
B14: Sortino | C14: 0.075
B15: Alpha | C15: 0.1
B16: Fund Management & Expense Efficiency | C16: =C17
B17: Expense Ratio | C17: 0.2
B18: Total Weightage | C18: =SUM(C5,C8,C12,C16)

Sheet Consol_Thematic (2)
A1: Funds | B1: 1 Yr Ret (%) | C1: Expense Ratio (%) | D1: 3 Yr Ret (%) | E1: 5 Yr Ret (%) | F1: Expense Ratio (%) | G1: Standard Deviation | H1: Sharpe Ratio | I1: Sortino Ratio | J1: Beta | K1: Alpha | L1: Category
A2: 360 ONE FlexiCap Fund - Regular Plan | B2: 4.23 | C2: 2.03 | D2: -- | E2: -- | F2: 2.03 | G2: -- | H2: -- | I2: -- | J2: -- | K2: -- | L2: EQ-FLX
A3: 360 ONE Focused Equity Fund - Regular Plan | B3: 1.94 | C3: 1.8 | D3: 20.36 | E3: 24.2 | F3: 1.8 | G3: 13.28 | H3: 0.94 | I3: 1.58 | J3: 0.88 | K3: 2.4 | L3: EQ-FLX
A4: 360 ONE Quant Fund - Regular Plan | B4: 6.46 | C4: 1.95 | D4: 28.72 | E4: -- | F4: 1.95 | G4: 18.03 | H4: 1.07 | I4: 1.6 | J4: 1.19 | K4: 5.59 | L4: EQ-THEMATIC
A5: Aditya Birla Sun Life Asset Allocator FoF - Regular Plan | B5: 9.61 | C5: 1.27 | D5: 17.35 | E5: 18.19 | F5: 1.27 | G5: 8.45 | H5: 1.12 | I5: 1.9 | J5: 0.84 | K5: 1.96 | L5: HY-MAA
A6: Aditya Birla Sun Life Balanced Advantage Fund - Regular Plan | B6: 9.56 | C6: 1.79 | D6: 14.63 | E6: 15.62 | F6: 1.79 | G6: 7.75 | H6: 0.91 | I6: 1.39 | J6: 0.74 | K6: 1.17 | L6: HY-DAA
A7: Aditya Birla Sun Life Bal Bhavishya Yojna - Regular Plan | B7: 4.02 | C7: 2.16 | D7: 16.53 | E7: 15.7 | F7: 2.16 | G7: 13.97 | H7: 0.65 | I7: 0.98 | J7: 0.94 | K7: -1.75 | L7: EQ-FLX
A8: Aditya Birla Sun Life BSE Sensex ETF | B8: 7.71 | C8: 0.04 | D8: 15.85 | E8: 20.64 | F8: 0.04 | G8: 12.69 | H8: 0.66 | I8: 1.1 | J8: 0.91 | K8: -0.96 | L8: EQ-LC
A9: Aditya Birla Sun Life Business Cycle Fund - Regular Plan | B9: 6.65 | C9: 2.14 | D9: 17.85 | E9: -- | F9: 2.14 | G9: 14.21 | H9: 0.68 | I9: 1.09 | J9: 0.96 | K9: -1.45 | L9: EQ-THEMATIC
A10: Aditya Birla Sun Life Conglomerate - Regular Plan | B10: -- | C10: 2.07 | D10: -- | E10: -- | F10: 2.07 | G10: -- | H10: -- | I10: -- | J10: -- | K10: -- | L10: EQ-THEMATIC
A11: Aditya Birla Sun Life Dividend Yield Fund - Regular Plan | B11: 1.84 | C11: 2.22 | D11: 23.93 | E11: 26.23 | F11: 2.22 | G11: 15.2 | H11: 1 | I11: 1.56 | J11: 0.97 | K11: 4.06 | L11: EQ-DIV Y
A12: Aditya Birla Sun Life Equity Advantage Fund - Regular Plan | B12: 4.58 | C12: 1.9 | D12: 17.54 | E12: 20.91 | F12: 1.9 | G12: 15.21 | H12: 0.62 | I12: 0.86 | J12: 1.01 | K12: -1.71 | L12: EQ-L&MC
A13: Aditya Birla Sun Life ESG Integration Strategy Fund - Regular Plan | B13: 9.7 | C13: 2.44 | D13: 17.21 | E13: -- | F13: 2.44 | G13: 14.57 | H13: 0.62 | I13: 0.98 | J13: 0.98 | K13: -1 | L13: EQ-T-ESG
A14: Aditya Birla Sun Life Financial Planning FoF - Aggressive Plan - Regular Plan | B14: 7.96 | C14: 1.13 | D14: 18.57 | E14: 19.56 | F14: 1.13 | G14: 10.49 | H14: 1 | I14: 1.44 | J14: 1.07 | K14: 1.02 | L14: HY-MAA
A15: Aditya Birla Sun Life Financial Planning FoF - Conservative Plan - Regular Plan | B15: 8.83 | C15: 0.94 | D15: 12.79 | E15: 12.42 | F15: 0.94 | G15: 4.72 | H15: 1.21 | I15: 1.84 | J15: 0.47 | K15: 1.49 | L15: HY-MAA
A16: Aditya Birla Sun Life Financial Planning FoF - Moderate Plan - Regular Plan | B16: 8.83 | C16: 1.09 | D16: 15.69 | E16: 16.02 | F16: 1.09 | G16: 7.64 | H16: 1.06 | I16: 1.54 | J16: 0.77 | K16: 1.24 | L16: HY-MAA
A17: Aditya Birla Sun Life Flexi Cap Fund - Regular Plan | B17: 9.73 | C17: 1.67 | D17: 20.22 | E17: 23.12 | F17: 1.67 | G17: 13.82 | H17: 0.87 | I17: 1.43 | J17: 0.94 | K17: 1.15 | L17: EQ-FLX
A18: Aditya Birla Sun Life Focused Fund - Regular Plan | B18: 9.28 | C18: 1.81 | D18: 18.92 | E18: 21.84 | F18: 1.81 | G18: 13.24 | H18: 0.8 | I18: 1.57 | J18: 0.9 | K18: 0.3 | L18: EQ-FLX
A19: Aditya Birla Sun Life Frontline Equity Fund - Regular Plan | B19: 7.48 | C19: 1.64 | D19: 18.54 | E19: 22.33 | F19: 1.64 | G19: 13.13 | H19: 0.81 | I19: 1.3 | J19: 0.95 | K19: 0.83 | L19: EQ-LC
A20: Aditya Birla Sun Life India GenNext Fund - Regular Plan | B20: 4.63 | C20: 1.85 | D20: 18.95 | E20: 22.13 | F20: 1.85 | G20: 14.6 | H20: 0.75 | I20: 1.16 | J20: 0.79 | K20: -0.37 | L20: EQ-Consumption
A21: Aditya Birla Sun Life Manufacturing Equity Fund - Regular Plan | B21: 2.01 | C21: 2.29 | D21: 20.58 | E21: 21.32 | F21: 2.29 | G21: 16.43 | H21: 0.8 | I21: 1.25 | J21: 1.07 | K21: 0.88 | L21: EQ-THEMATIC
A22: Aditya Birla Sun Life Mid Cap Fund - Regular Plan | B22: 6.66 | C22: 1.89 | D22: 22.4 | E22: 28.63 | F22: 1.89 | G22: 16.24 | H22: 0.85 | I22: 1.39 | J22: 0.92 | K22: -2.87 | L22: EQ-MC
A23: Aditya Birla Sun Life MNC Fund - Regular Plan | B23: -0.79 | C23: 2.01 | D23: 14.75 | E23: 13.98 | F23: 2.01 | G23: 14.9 | H23: 0.52 | I23: 0.89 | J23: 0.9 | K23: -2.66 | L23: EQ-MNC
A24: Aditya Birla Sun Life Multi Asset Allocation Fund - Regular Plan | B24: 10.57 | C24: 1.83 | D24: -- | E24: -- | F24: 1.83 | G24: -- | H24: -- | I24: -- | J24: -- | K24: -- | L24: HY-MAA
A25: Aditya Birla Sun Life Multi-Cap Fund - Regular Plan | B25: 4.72 | C25: 1.84 | D25: 19.48 | E25: -- | F25: 1.84 | G25: 14.3 | H25: 0.8 | I25: 1.06 | J25: 0.88 | K25: -1.43 | L25: EQ-MLC
A26: Aditya Birla Sun Life Multi - Index FoF - Regular Plan | B26: 6.41 | C26: 0.61 | D26: -- | E26: -- | F26: 0.61 | G26: -- | H26: -- | I26: -- | J26: -- | K26: -- | L26: HY-MAA
A27: Aditya Birla Sun Life Nifty 200 Momentum 30 ETF | B27: -11.83 | C27: 0.29 | D27: -- | E27: -- | F27: 0.29 | G27: -- | H27: -- | I27: -- | J27: -- | K27: -- | L27: EQ-L&MC
A28: Aditya Birla Sun Life Nifty 200 Quality 30 ETF | B28: 2.39 | C28: 0.29 | D28: -- | E28: -- | F28: 0.29 | G28: -- | H28: -- | I28: -- | J28: -- | K28: -- | L28: EQ-L&MC
A29: Aditya Birla Sun Life Nifty 50 Equal Weight Index Fund - Regular Plan | B29: 4.87 | C29: 1.02 | D29: 19.35 | E29: -- | F29: 1.02 | G29: 14.76 | H29: 0.77 | I29: 1.17 | J29: 1.04 | K29: 0.57 | L29: EQ-LC
A30: Aditya Birla Sun Life Nifty 50 ETF | B30: 7.81 | C30: 0.04 | D30: 16.6 | E30: 21.4 | F30: 0.04 | G30: 13.14 | H30: 0.69 | I30: 1.18 | J30: 0.95 | K30: -0.72 | L30: EQ-LC
A31: Aditya Birla Sun Life Nifty 50 Index Fund - Regular Plan | B31: 7.33 | C31: 0.47 | D31: 15.98 | E31: 20.62 | F31: 0.47 | G31: 13.12 | H31: 0.65 | I31: 1.11 | J31: 0.95 | K31: -1.25 | L31: EQ-LC
A32: Aditya Birla Sun Life Nifty India Defence Index Fund - Regular Plan | B32: -- | C32: 1.06 | D32: -- | E32: -- | F32: 1.06 | G32: -- | H32: -- | I32: -- | J32: -- | K32: -- | L32: EQ-THEMATIC
A33: Aditya Birla Sun Life Nifty Midcap 150 Index Fund - Regular Plan | B33: 5.32 | C33: 1.01 | D33: 27.02 | E33: -- | F33: 1.01 | G33: 17.01 | H33: 1.06 | I33: 1.53 | J33: 1 | K33: -0.09 | L33: EQ-MC
A34: Aditya Birla Sun Life Nifty Next 50 ETF | B34: -3.18 | C34: 0.09 | D34: 22.13 | E34: 22.68 | F34: 0.09 | G34: 19.54 | H34: 0.73 | I34: 1.09 | J34: 1.3 | K34: 0.85 | L34: EQ-LC
A35: Aditya Birla Sun Life Nifty Next 50 Index Fund - Regular Plan | B35: -4.32 | C35: 0.88 | D35: 20.8 | E35: -- | F35: 0.88 | G35: 19.52 | H35: 0.67 | I35: 1 | J35: 1.3 | K35: -0.25 | L35: EQ-LC
A36: Aditya Birla Sun Life Nifty PSE ETF | B36: -4.83 | C36: 0.2 | D36: -- | E36: -- | F36: 0.2 | G36: -- | H36: -- | I36: -- | J36: -- | K36: -- | L36: EQ-PSU
A37: Aditya Birla Sun Life Nifty Smallcap 50 Index Fund - Regular Plan | B37: 6.38 | C37: 1.01 | D37: 28.75 | E37: -- | F37: 1.01 | G37: 20.71 | H37: 0.92 | I37: 1.48 | J37: 1.03 | K37: 0.22 | L37: EQ-SC
A38: Aditya Birla Sun Life PSU Equity Fund - Regular Plan | B38: -5.53 | C38: 1.79 | D38: 32.4 | E38: 32.39 | F38: 1.79 | G38: 22.36 | H38: 1.07 | I38: 1.95 | J38: 0.97 | K38: -2.99 | L38: EQ-PSU
A39: Aditya Birla Sun Life Quant Fund - Regular Plan | B39: -- | C39: 1.97 | D39: -- | E39: -- | F39: 1.97 | G39: -- | H39: -- | I39: -- | J39: -- | K39: -- | L39: EQ-THEMATIC
A40: Aditya Birla Sun Life Retirement Fund - The 30s Plan - Regular Plan | B40: 8.28 | C40: 2.41 | D40: 17.78 | E40: 16.73 | F40: 2.41 | G40: 14.35 | H40: 0.69 | I40: 1.1 | J40: 0.94 | K40: -0.98 | L40: EQ-FLX
A41: Aditya Birla Sun Life Small Cap Fund - Regular Plan | B41: 2.38 | C41: 1.92 | D41: 21.9 | E41: 29.2 | F41: 1.92 | G41: 17.91 | H41: 0.78 | I41: 1.18 | J41: 0.89 | K41: -2.19 | L41: EQ-SC
A42: Aditya Birla Sun Life Special Opportunities Fund - Regular Plan | B42: 8.14 | C42: 2.39 | D42: 20.35 | E42: -- | F42: 2.39 | G42: 14.79 | H42: 0.79 | I42: 1.39 | J42: 0.99 | K42: 0.3 | L42: EQ-THEMATIC
A43: Aditya Birla Sun Life Transportation and Logistics Fund - Regular Plan | B43: -4.45 | C43: 2.11 | D43: -- | E43: -- | F43: 2.11 | G43: -- | H43: -- | I43: -- | J43: -- | K43: -- | L43: EQ-THEMATIC
A44: Angel One Nifty 50 ETF | B44: -- | C44: 0.09 | D44: -- | E44: -- | F44: 0.09 | G44: -- | H44: -- | I44: -- | J44: -- | K44: -- | L44: EQ-LC
A45: Angel One Nifty 50 Index Fund - Regular Plan | B45: -- | C45: 0.7 | D45: -- | E45: -- | F45: 0.7 | G45: -- | H45: -- | I45: -- | J45: -- | K45: -- | L45: EQ-LC
A46: Angel One Nifty Total Market ETF | B46: -- | C46: 0.28 | D46: -- | E46: -- | F46: 0.28 | G46: -- | H46: -- | I46: -- | J46: -- | K46: -- | L46: EQ-FLX
A47: Angel One Nifty Total Market Index Fund - Regular Plan | B47: -- | C47: 1.03 | D47: -- | E47: -- | F47: 1.03 | G47: -- | H47: -- | I47: -- | J47: -- | K47: -- | L47: EQ-FLX
A48: Axis Balanced Advantage Fund - Regular Plan | B48: 9.34 | C48: 1.94 | D48: 15.53 | E48: 14.3 | F48: 1.94 | G48: 8.06 | H48: 1.01 | I48: 1.7 | J48: 0.75 | K48: 2.22 | L48: HY-DAA
A49: Axis BSE Sensex ETF | B49: 7.73 | C49: 0.04 | D49: -- | E49: -- | F49: 0.04 | G49: -- | H49: -- | I49: -- | J49: -- | K49: -- | L49: EQ-LC
A50: Axis BSE Sensex Index Fund - Regular Plan | B50: 7 | C50: 0.7 | D50: -- | E50: -- | F50: 0.7 | G50: -- | H50: -- | I50: -- | J50: -- | K50: -- | L50: EQ-LC
A51: Axis Business Cycles Fund - Regular Plan | B51: 5.03 | C51: 1.99 | D51: -- | E51: -- | F51: 1.99 | G51: -- | H51: -- | I51: -- | J51: -- | K51: -- | L51: EQ-THEMATIC
A52: Axis Consumption Fund - Regular Plan | B52: -- | C52: 1.86 | D52: -- | E52: -- | F52: 1.86 | G52: -- | H52: -- | I52: -- | J52: -- | K52: -- | L52: EQ-Consumption
A53: Axis Equity ETFs FoF - Regular Plan | B53: -2.44 | C53: 0.7 | D53: 16.12 | E53: -- | F53: 0.7 | G53: 14.4 | H53: 0.6 | I53: 0.89 | J53: 0.98 | K53: -2.69 | L53: EQ-FLX
A54: Axis ESG Integration Strategy Fund - Regular Plan | B54: 4.24 | C54: 2.22 | D54: 15.27 | E54: 16.68 | F54: 2.22 | G54: 14.28 | H54: 0.52 | I54: 0.79 | J54: 0.94 | K54: -2.24 | L54: EQ-T-ESG
A55: Axis Flexi Cap Fund - Regular Plan | B55: 7.13 | C55: 1.71 | D55: 17.07 | E55: 18.82 | F55: 1.71 | G55: 14.62 | H55: 0.64 | I55: 0.9 | J55: 0.96 | K55: -1.74 | L55: EQ-FLX
A56: Axis Focused Fund | B56: 6.48 | C56: 1.74 | D56: 13.14 | E56: 15.91 | F56: 1.74 | G56: 15.7 | H56: 0.36 | I56: 0.61 | J56: 0.99 | K56: -5.72 | L56: EQ-FLX
A57: Axis India Manufacturing Fund - Regular Plan | B57: -0.07 | C57: 1.81 | D57: -- | E57: -- | F57: 1.81 | G57: -- | H57: -- | I57: -- | J57: -- | K57: -- | L57: EQ-THEMATIC
A58: Axis Innovation Fund - Regular Plan | B58: 7.03 | C58: 2.25 | D58: 17.48 | E58: -- | F58: 2.25 | G58: 14.04 | H58: 0.68 | I58: 0.93 | J58: 0.86 | K58: -0.41 | L58: EQ-THEMATIC
A59: Axis Large Cap Fund - Regular Plan | B59: 4.99 | C59: 1.57 | D59: 14.29 | E59: 16.47 | F59: 1.57 | G59: 13.3 | H59: 0.51 | I59: 0.85 | J59: 0.93 | K59: -2.78 | L59: EQ-LC
A60: Axis Large & Mid Cap Fund - Regular Plan | B60: 5.78 | C60: 1.68 | D60: 20.83 | E60: 24.15 | F60: 1.68 | G60: 14.14 | H60: 0.88 | I60: 1.32 | J60: 0.88 | K60: 2.71 | L60: EQ-L&MC
A61: Axis Midcap Fund - Regular Plan | B61: 6.2 | C61: 1.57 | D61: 22.4 | E61: 24.84 | F61: 1.57 | G61: 15.55 | H61: 0.88 | I61: 1.23 | J61: 0.85 | K61: -1.78 | L61: EQ-MC
A62: Axis Momentum Fund - Regular Plan | B62: -- | C62: 2.11 | D62: -- | E62: -- | F62: 2.11 | G62: -- | H62: -- | I62: -- | J62: -- | K62: -- | L62: EQ-THEMATIC
A63: Axis Multi Asset Allocation Fund - Regular Plan | B63: 9.03 | C63: 2.08 | D63: 12.84 | E63: 15.25 | F63: 2.08 | G63: 10 | H63: 0.52 | I63: 0.99 | J63: 0.98 | K63: -3.51 | L63: HY-MAA
A64: Axis Multicap Fund - Regular Plan | B64: 9.49 | C64: 1.79 | D64: 25.63 | E64: -- | F64: 1.79 | G64: 14.9 | H64: 1.12 | I64: 1.49 | J64: 0.91 | K64: 3.3 | L64: EQ-MLC
A65: Axis Nifty 100 Index Fund - Regular Plan | B65: 4.89 | C65: 0.92 | D65: 16.04 | E65: 20.19 | F65: 0.92 | G65: 13.94 | H65: 0.61 | I65: 1 | J65: 1.01 | K65: -1.81 | L65: EQ-LC
A66: Axis Nifty 500 Index Fund - Regular Plan | B66: -- | C66: 1 | D66: -- | E66: -- | F66: 1 | G66: -- | H66: -- | I66: -- | J66: -- | K66: -- | L66: EQ-FLX
A67: Axis Nifty500 Momentum 50 Index Fund - Regular Plan | B67: -- | C67: 1.06 | D67: -- | E67: -- | F67: 1.06 | G67: -- | H67: -- | I67: -- | J67: -- | K67: -- | L67: EQ-FLX
A68: Axis Nifty 50 ETF | B68: 7.81 | C68: 0.04 | D68: 16.59 | E68: 21.37 | F68: 0.04 | G68: 13.12 | H68: 0.69 | I68: 1.18 | J68: 0.95 | K68: -0.72 | L68: EQ-LC
A69: Axis Nifty 50 Index Fund - Regular Plan | B69: 7.42 | C69: 0.42 | D69: 16.06 | E69: -- | F69: 0.42 | G69: 13.08 | H69: 0.65 | I69: 1.12 | J69: 0.94 | K69: -1.15 | L69: EQ-LC
A70: Axis NIFTY India Consumption ETF | B70: 3.75 | C70: 0.38 | D70: 20.38 | E70: -- | F70: 0.38 | G70: 15.94 | H70: 0.77 | I70: 1.12 | J70: 0.85 | K70: 0.05 | L70: EQ-Consumption
A71: Axis Nifty Midcap 50 Index Fund - Regular Plan | B71: 7.29 | C71: 1.03 | D71: 28.42 | E71: -- | F71: 1.03 | G71: 17.57 | H71: 1.07 | I71: 1.52 | J71: 1.01 | K71: 0.41 | L71: EQ-MC
A72: Axis Nifty Next 50 Index Fund - Regular Plan | B72: -4.11 | C72: 1.01 | D72: 21.1 | E72: -- | F72: 1.01 | G72: 19.43 | H72: 0.69 | I72: 1.03 | J72: 1.29 | K72: 0.08 | L72: EQ-LC
A73: Axis Nifty Smallcap 50 Index Fund - Regular Plan | B73: 5.82 | C73: 1.02 | D73: 28.38 | E73: -- | F73: 1.02 | G73: 20.53 | H73: 0.91 | I73: 1.48 | J73: 1.02 | K73: 0.09 | L73: EQ-SC
A74: Axis Quant Fund - Regular Plan | B74: -3.4 | C74: 2.22 | D74: 16.25 | E74: -- | F74: 2.22 | G74: 14.8 | H74: 0.61 | I74: 0.86 | J74: 0.97 | K74: -2.21 | L74: EQ-THEMATIC
A75: Axis Retirement Fund - Dynamic Plan - Regular Plan | B75: 8.17 | C75: 2.43 | D75: 17.04 | E75: 15.72 | F75: 2.43 | G75: 12.64 | H75: 0.75 | I75: 1.08 | J75: 1.15 | K75: 0.41 | L75: HY-DAA
A76: Axis Small Cap Fund - Regular Plan | B76: 8.75 | C76: 1.6 | D76: 22.99 | E76: 31.14 | F76: 1.6 | G76: 14.41 | H76: 1.01 | I76: 1.36 | J76: 0.71 | K76: 1.64 | L76: EQ-SC
A77: Bajaj Finserv Balanced Advantage Fund - Regular Plan | B77: 3.66 | C77: 2.05 | D77: -- | E77: -- | F77: 2.05 | G77: -- | H77: -- | I77: -- | J77: -- | K77: -- | L77: HY-DAA
A78: Bajaj Finserv Consumption Fund - Regular Plan | B78: -- | C78: 2.33 | D78: -- | E78: -- | F78: 2.33 | G78: -- | H78: -- | I78: -- | J78: -- | K78: -- | L78: EQ-Consumption
A79: Bajaj Finserv Flexi Cap Fund - Regular Plan | B79: 9.02 | C79: 1.83 | D79: -- | E79: -- | F79: 1.83 | G79: -- | H79: -- | I79: -- | J79: -- | K79: -- | L79: EQ-FLX
A80: Bajaj Finserv Large and Mid Cap Fund - Regular Plan | B80: 7.02 | C80: 2.02 | D80: -- | E80: -- | F80: 2.02 | G80: -- | H80: -- | I80: -- | J80: -- | K80: -- | L80: EQ-L&MC
A81: Bajaj Finserv Large Cap Fund - Regular Plan | B81: -- | C81: 2.07 | D81: -- | E81: -- | F81: 2.07 | G81: -- | H81: -- | I81: -- | J81: -- | K81: -- | L81: EQ-LC
A82: Bajaj Finserv Multi Asset Allocation Fund - Regular Plan | B82: 7.06 | C82: 2.03 | D82: -- | E82: -- | F82: 2.03 | G82: -- | H82: -- | I82: -- | J82: -- | K82: -- | L82: HY-MAA
A83: Bajaj Finserv Multi Cap Fund - Regular Plan | B83: -- | C83: 2.3 | D83: -- | E83: -- | F83: 2.3 | G83: -- | H83: -- | I83: -- | J83: -- | K83: -- | L83: EQ-MLC
A84: Bajaj Finserv Nifty 50 ETF | B84: 7.79 | C84: 0.07 | D84: -- | E84: -- | F84: 0.07 | G84: -- | H84: -- | I84: -- | J84: -- | K84: -- | L84: EQ-LC
A85: Bajaj Finserv Nifty 50 Index Fund - Regular Plan | B85: -- | C85: 0.9 | D85: -- | E85: -- | F85: 0.9 | G85: -- | H85: -- | I85: -- | J85: -- | K85: -- | L85: EQ-LC
A86: Bajaj Finserv Nifty Next 50 Index Fund - Regular Plan | B86: -- | C86: 0.95 | D86: -- | E86: -- | F86: 0.95 | G86: -- | H86: -- | I86: -- | J86: -- | K86: -- | L86: EQ-LC
A87: Bandhan Balanced Advantage Fund - Regular Plan | B87: 7.09 | C87: 2.02 | D87: 12.7 | E87: 12.28 | F87: 2.02 | G87: 7.5 | H87: 0.69 | I87: 0.99 | J87: 0.69 | K87: -0.25 | L87: HY-DAA
A88: Bandhan BSE Sensex ETF | B88: 7.39 | C88: 0.38 | D88: 15.48 | E88: 20.13 | F88: 0.38 | G88: 12.69 | H88: 0.64 | I88: 1.06 | J88: 0.91 | K88: -1.29 | L88: EQ-LC
A89: Bandhan Business Cycle Fund - Regular Plan | B89: -- | C89: 2.05 | D89: -- | E89: -- | F89: 2.05 | G89: -- | H89: -- | I89: -- | J89: -- | K89: -- | L89: EQ-THEMATIC
A90: Bandhan Flexi Cap Fund - Regular Plan | B90: 7.21 | C90: 1.86 | D90: 19.28 | E90: 21.3 | F90: 1.86 | G90: 13.24 | H90: 0.82 | I90: 1.33 | J90: 0.88 | K90: 0.73 | L90: EQ-FLX
A91: Bandhan Focused Fund - Regular Plan | B91: 13.29 | C91: 2.09 | D91: 21.38 | E91: 21.44 | F91: 2.09 | G91: 14.89 | H91: 0.87 | I91: 1.27 | J91: 0.9 | K91: 2.48 | L91: EQ-FLX
A92: Bandhan Innovation Fund - Regular Plan | B92: 17.96 | C92: 2.08 | D92: -- | E92: -- | F92: 2.08 | G92: -- | H92: -- | I92: -- | J92: -- | K92: -- | L92: EQ-THEMATIC
A93: Bandhan Large Cap Fund - Regular Plan | B93: 6.92 | C93: 2.04 | D93: 19.15 | E93: 20.77 | F93: 2.04 | G93: 14.13 | H93: 0.79 | I93: 1.32 | J93: 1 | K93: 0.94 | L93: EQ-LC
A94: Bandhan Large & Mid Cap Fund - Regular Plan | B94: 9.01 | C94: 1.74 | D94: 27.88 | E94: 28.9 | F94: 1.74 | G94: 14.42 | H94: 1.26 | I94: 1.82 | J94: 0.95 | K94: 7.63 | L94: EQ-L&MC
A95: Bandhan Midcap Fund - Regular Plan | B95: 5.35 | C95: 2.07 | D95: -- | E95: -- | F95: 2.07 | G95: -- | H95: -- | I95: -- | J95: -- | K95: -- | L95: EQ-MC
A96: Bandhan Multi Asset Allocation Fund - Regular Plan | B96: 9.76 | C96: 1.98 | D96: -- | E96: -- | F96: 1.98 | G96: -- | H96: -- | I96: -- | J96: -- | K96: -- | L96: HY-MAA
A97: Bandhan Multi Cap Fund - Regular Plan | B97: 5.03 | C97: 1.95 | D97: 22.08 | E97: -- | F97: 1.95 | G97: 13.66 | H97: 0.99 | I97: 1.49 | J97: 0.86 | K97: 1.05 | L97: EQ-MLC
A98: Bandhan Nifty 100 Index Fund - Regular Plan | B98: 5.12 | C98: 0.61 | D98: 16.35 | E98: -- | F98: 0.61 | G98: 13.96 | H98: 0.63 | I98: 1.03 | J98: 1.01 | K98: -1.55 | L98: EQ-LC
A99: Bandhan Nifty100 Low Volatility 30 Index Fund - Regular Plan | B99: 4.78 | C99: 1.04 | D99: -- | E99: -- | F99: 1.04 | G99: -- | H99: -- | I99: -- | J99: -- | K99: -- | L99: EQ-LC
A100: Bandhan Nifty200 Momentum 30 Index Fund - Regular Plan | B100: -12.71 | C100: 1.07 | D100: -- | E100: -- | F100: 1.07 | G100: -- | H100: -- | I100: -- | J100: -- | K100: -- | L100: EQ-L&MC
...

Sheet Table 1
B2: Financial Product Catalog: A Ready Reckoner , As on 29th Apr 2026
B4: Whats new? (July 2026) | F4: Debt
B5: Fund Name | C5: End Date
B6: ICICI Prudential Active Momentum Fund | C6: July 22, 2025 | F6: Debt Mutual Funds (Ultra Short Duration) | G6: 3-Year Return | H6: 1-Year Return
B7: Bandhan Multi-Factor Fund | C7: July 24, 2025 | F7: NIFTY Ultra Short Duration Debt Index | G7: =VLOOKUP(F7,'[3]Page001 (2)'!$A:$K,10,0)&"%" | H7: =VLOOKUP(F7,'[3]Page001 (2)'!$A:$K,11,0)&"%"
F8: Ultra Short - Fund Name ( Return CAGR ) | G8: 3-Year Return | H8: 1-Year Return
B9: Equity | F9: ='Summary '!J4 | G9: ='Summary '!K4 | H9: ='Summary '!L4
F10: ='Summary '!J5 | G10: ='Summary '!K5 | H10: ='Summary '!L5
B11: Large Cap - Funds | C11: 3-Year Return | D11: 1-Year Return | F11: ='Summary '!J6 | G11: ='Summary '!K6 | H11: ='Summary '!L6
B12: NIFTY 50 | C12: =VLOOKUP(B12,'[3]Table001 (Page 1-2)'!$A:$E,5,0)&"%" | D12: =VLOOKUP(B12,'[3]Table001 (Page 1-2)'!$A:$E,4,0)&"%"
B13: Large Cap - Funds (Return CAGR) | C13: 3-Year Return | D13: 1-Year Return | F13: Debt Mutual Funds (Low Duration) | G13: 3-Year Return | H13: 1-Year Return
B14: ='Summary '!D4 | C14: ='Summary '!E4 | D14: ='Summary '!F4 | F14: NIFTY Low Duration Debt Index | G14: =VLOOKUP(F14,'[3]Page001 (2)'!$A:$K,10,0)&"%" | H14: =VLOOKUP(F14,'[3]Page001 (2)'!$A:$K,11,0)&"%"
B15: ='Summary '!D5 | C15: ='Summary '!E5 | D15: ='Summary '!F5 | F15: Low Duration - Funds ( Return CAGR ) | G15: 3-Year Return | H15: 1-Year Return
B16: ='Summary '!D6 | C16: ='Summary '!E6 | D16: ='Summary '!F6 | F16: ='Summary '!J8 | G16: ='Summary '!K8 | H16: ='Summary '!L8
B17: SIP of 50000*36=1800000, Maturity Value Would be | C17: 2572605 | F17: ='Summary '!J9 | G17: ='Summary '!K9 | H17: ='Summary '!L9
F18: ='Summary '!J10 | G18: ='Summary '!K10 | H18: ='Summary '!L10
B19: Large & Mid Cap - Funds | C19: 3-Year Return | D19: 1-Year Return
B20: ='Summary '!D8 | C20: ='Summary '!E8 | D20: ='Summary '!F8 | F20: Debt Mutual Funds (Short Duration) | G20: 3-Year Return | H20: 1-Year Return
B21: ='Summary '!D9 | C21: ='Summary '!E9 | D21: ='Summary '!F9 | F21: NIFTY Short Duration Debt Index A-II | G21: =VLOOKUP(F21,'[3]Table003 (Page 3)'!$A$2:$K$78,9,0)&"%" | H21: =VLOOKUP(F21,'[3]Table003 (Page 3)'!$A$2:$K$78,10,0)&"%"
B22: ='Summary '!D10 | C22: ='Summary '!E10 | D22: ='Summary '!F10 | F22: Medium Term - Funds ( Return CAGR ) | G22: 3-Year Return | H22: 1-Year Return
B23: SIP of 50000*36=1800000, Maturity Value Would be | C23: 2646895 | F23: ='Summary '!J12 | G23: ='Summary '!K12 | H23: ='Summary '!L12
F24: ='Summary '!J13 | G24: ='Summary '!K13 | H24: ='Summary '!L13
B25: Mid Cap - Funds | C25: 3-Year Return | D25: 1-Year Return | F25: ='Summary '!J14 | G25: ='Summary '!K14 | H25: ='Summary '!L14
B26: NIFTY Midcap 100 | C26: =VLOOKUP(B26,'[3]Table001 (Page 1-2)'!$A:$E,5,0)&"%" | D26: =VLOOKUP(B26,'[3]Table001 (Page 1-2)'!$A:$E,4,0)&"%"
B27: Mid Cap - Funds (Return CAGR) | C27: 3-Year CAGR | D27: 1-Year Return | F27: Debt Mutual Funds (Medium Duration) | G27: 3-Year Return | H27: 1-Year Return
B28: ='Summary '!D12 | C28: ='Summary '!E12 | D28: ='Summary '!F12 | F28: NIFTY Medium Duration Debt Index A-III | G28: =VLOOKUP(F28,'[3]Table003 (Page 3)'!$A$2:$K$78,9,0)&"%" | H28: =VLOOKUP(F28,'[3]Table003 (Page 3)'!$A$2:$K$78,10,0)&"%"
B29: ='Summary '!D13 | C29: ='Summary '!E13 | D29: ='Summary '!F13 | F29: Medium Term - Funds ( Return CAGR ) | G29: 3-Year Return | H29: 1-Year Return
B30: ='Summary '!D14 | C30: ='Summary '!E14 | D30: ='Summary '!F14 | F30: ='Summary '!J16 | G30: ='Summary '!K16 | H30: ='Summary '!L16
B31: SIP of 50000*36=1800000 , Maturity Value Would be | C31: 2767450 | F31: ='Summary '!J17 | G31: ='Summary '!K17 | H31: ='Summary '!L17
F32: ='Summary '!J18 | G32: ='Summary '!K18 | H32: ='Summary '!L18
B33: Small Cap - Funds | C33: 3-Year Return | D33: 1-Year Return
B34: NIFTY Smallcap 100 | C34: =VLOOKUP(B34,'[3]Table001 (Page 1-2)'!$A:$E,5,0)&"%" | D34: =VLOOKUP(B34,'[3]Table001 (Page 1-2)'!$A:$E,4,0)&"%" | F34: Debt Mutual Funds (Medium to Long Duration) | G34: 3-Year Return | H34: 1-Year Return
B35: Small Cap - Funds ( Return CAGR ) | C35: 3-Yr CAGR | D35: 1-Yr Return | F35: NIFTY Medium to Long Duration Debt Index | G35: =VLOOKUP(F35,'[3]Table001 (Page 1)'!$A$2:$K$78,9,0)&"%" | H35: =VLOOKUP(F35,'[3]Table001 (Page 1)'!$A$2:$K$78,8,0)&"%"
B36: ='Summary '!D16 | C36: ='Summary '!E16 | D36: ='Summary '!F16 | F36: Medium to Long Term - Funds ( Return CAGR ) | G36: 3-Year Return | H36: 1-Year Return
B37: ='Summary '!D17 | C37: ='Summary '!E17 | D37: ='Summary '!F17 | F37: ='Summary '!J20 | G37: ='Summary '!K20 | H37: ='Summary '!L20
B38: ='Summary '!D18 | C38: ='Summary '!E18 | D38: ='Summary '!F18 | F38: ='Summary '!J21 | G38: ='Summary '!K21 | H38: ='Summary '!L21
B39: SIP of 50000*36=1800000 , Maturity Value Would be | C39: 2767450 | F39: ='Summary '!J22 | G39: ='Summary '!K22 | H39: ='Summary '!L22
F40: Others
B41: Flexi Cap - Funds | C41: 3-Year Return | D41: 1-Year Return | F41: Multi Asset | G41: 3-Year Return | H41: 1-Year Return
B42: ='Summary '!D20 | C42: ='Summary '!E20 | D42: ='Summary '!F20 | F42: Nifty 500 | G42: =VLOOKUP(F42,'[3]Table001 (Page 1-2)'!$A:$E,5,0)&"%" | H42: =VLOOKUP(F42,'[3]Table001 (Page 1-2)'!$A:$E,4,0)&"%"
B43: ='Summary '!D21 | C43: ='Summary '!E21 | D43: ='Summary '!F21 | F43: ='Summary '!D28 | G43: ='Summary '!E28 | H43: ='Summary '!F28
B44: ='Summary '!D22 | C44: ='Summary '!E22 | D44: ='Summary '!F22 | F44: ='Summary '!D29 | G44: ='Summary '!E29 | H44: ='Summary '!F29
B45: SIP of 50000*36=1800000 , Maturity Value Would be | C45: 2669566 | F45: ='Summary '!D30 | G45: ='Summary '!E30 | H45: ='Summary '!F30
B47: Thematic | C47: 3-Year Return | D47: 1-Year Return | F47: BAF | G47: 3-Year Return | H47: 1-Year Return
B48: Nifty 500 | C48: =VLOOKUP(B48,'[3]Table001 (Page 1-2)'!$A:$E,5,0)&"%" | D48: =VLOOKUP(B48,'[3]Table001 (Page 1-2)'!$A:$E,4,0)&"%" | F48: Nifty 50 | G48: =VLOOKUP(F48,'[3]Table001 (Page 1-2)'!$A:$E,5,0)&"%" | H48: =VLOOKUP(F48,'[3]Table001 (Page 1-2)'!$A:$E,4,0)&"%"
B49: ='Summary '!D43 | C49: ='Summary '!E43 | D49: ='Summary '!F43 | F49: ='Summary '!D24 | G49: ='Summary '!E24 | H49: ='Summary '!F24
B50: ='Summary '!D44 | C50: ='Summary '!E44 | D50: ='Summary '!F44 | F50: ='Summary '!D25 | G50: ='Summary '!E25 | H50: ='Summary '!F25
B51: ='Summary '!D45 | C51: ='Summary '!E45 | D51: ='Summary '!F45 | F51: ='Summary '!D26 | G51: ='Summary '!E26 | H51: ='Summary '!F26
H52: Page 1

Sheet Table 2 FD PMS AIF
B2: Financial Product Catalog: A Ready Reckoner , As on 18h July 2025
B4: Credit ratings assessed by (e.g., CRISIL, ICRA, CARE)
B6: Corporate FD's
B7: Institution | C7: 3-Year FD Rate | E7: 1-Year FD Rate
B8: SBI Bank FD | C8: 6.70%-6.95% | E8: 6.30%-6.55%
B9: Shriram Finance | C9: 8.40% – 8.90% | E9: 7.65% – 8.15%
B10: Bajaj Finance | C10: 7.25% – 7.80% | E10: 7% – 8.55%
B11: PNB Housing Finance | C11: 7.65% – 7.90% | E11: 7.40% – 7.65%
B12: ICICI Home Finance | C12: 7.60% -7.85% | E12: 7.05% – 7.25%
B13: LIC Housing Finance | C13: 7.35% -7.60% | E13: 7.00% – 7.25%
B14: Capital Gain Bonds/NCD
B15: Index Name | C15: 5-Year Return
B16: NIFTY 10 Year Benchmark G-Sec Index | C16: 0.0552
B17: Issuer | C17: Interest Rate | D17: Tenure
B18: IRFC | C18: 5.25% p.a. | D18: 5 years
B19: PFC | C19: 5.25% p.a. | D19: 5 years
B20: REC | C20: 5.25% p.a. | D20: 5 years
B22: RBI Floating Rate Savings Bond | D22: Interest Rate
B23: HDFC | D23: 7.90% p.a.
B25: Portfolio Management Services
B27: Large Cap/Multi Cap | C27: 3-Year Return | E27: 1-Year Return
B28: NIFTY 50 | C28: ='Table 1'!C12 | E28: ='Table 1'!D12
B29: Scheme Name | C29: 3-Year Return | E29: 1-Year Return
B30: ICICI Prudential Large Cap Strategy | C30: 0.2903 | E30: 0.0566
B31: White Oak India Pioneers Equity Portfolio | C31: 0.1969 | E31: 0.0871
B33: Midcap | C33: 3-Year Return | E33: 1-Year Return
B34: NIFTY Midcap 150 | C34: =VLOOKUP(B34,'[3]Table001 (Page 1-2)'!$A:$E,5,0)&"%" | E34: =VLOOKUP(B34,'[3]Table001 (Page 1-2)'!$A:$E,4,0)&"%"
B35: Scheme Name | C35: 3-Year Return | E35: 1-Year Return
B36: ICICI Prudential PIPE Strategy (Mid & Small Cap) | C36: 0.3313 | E36: 0.0379
B37: White Oak India Digital Leaders Portfolio | C37: 0.1924 | E37: 0.1471
B39: Smallcap | C39: 3-Year Return | E39: 1-Year Return
B40: NIFTY Smallcap 250 | C40: =VLOOKUP(B40,'[3]Table001 (Page 1-2)'!$A:$E,5,0)&"%" | E40: =VLOOKUP(B40,'[3]Table001 (Page 1-2)'!$A:$E,4,0)&"%"
B41: Scheme Name | C41: 3-Year Return | E41: 1-Year Return
B42: ICICI Prudential PIPE Strategy (Mid & Small Cap) | C42: 0.3313 | E42: 0.0379
B43: Kotak Mahindra Mid & Small Cap Strategy | C43: 0.1856 | E43: -0.072
B45: Alternative Investment Fund
B46: AIF - Fund | C46: Investment Strategy | D46: 2-Year Return | E46: 1-Year Return
B47: ICICI Prudential Equity Opportunities Fund | C47: Contrarian Investing | D47: 0.2648 | E47: 0.0476
B48: ICICI Prudential Enhanced Dynamic Equity Fund | C48: Derivative Strategies | D48: 0.2132 | E48: 0.0699
B50: REITs & INVITs
B51: REIT Stock | D51: 1-Yr Div in rs (Last 4 qtr) | E51: 01 Yr Mkt Ret
B52: Embassy Office Parks REIT | D52: 23.01 | E52: 0.07
B53: Mindspace Business Parks REIT | D53: 21.95 | E53: 0.23
B54: Brookfield India Real Estate Trust (BIRET) | D54: 19.25 | E54: 0.14
B55: INVITs | D55: 1-Yr Div in rs (Last 4 qtr) | E55: 01 Yr Mkt Ret
B56: IndiGrid (India Grid Trust) | D56: 15.35 | E56: 0.12
B57: PowerGrid Infrastructure Investment Trust (PGInvIT) | D57: 12 | E57: -0.03
B58: IRB InvIT Fund | D58: 8 | E58: -0.08
B60: Contact Zuari Finserv Ltd
B61: RM Name
B62: Contact No.-
J63: Page 2

Sheet Summary 
B2: Equity | H2: Debt
B3: Category | C3: Rank | D3: Fund | E3: 3 year Return | F3: 1 year Return | H3: Category | I3: Rank | J3: Fund | K3: 3 year Return | L3: 1 year Return
B4: Large Cap | C4: 1 | D4: =VLOOKUP(C4, 'Fund Ranking_Equity'!$C$5:$D$12,2,FALSE) | E4: =_xlfn.CONCAT((ROUND(VLOOKUP($D4,'Fund Ranking_Equity'!$B$6:$T$137,5,FALSE),2)),"%") | F4: =_xlfn.CONCAT((ROUND(VLOOKUP($D4,'Fund Ranking_Equity'!$B$6:$T$137,4,FALSE),2)),"%") | H4: ='Fund Ranking Criteria'!C24 | I4: 1 | J4: =VLOOKUP($I4, 'Fund Ranking_Debt'!$C$7:$N$13,3,FALSE) | K4: =_xlfn.CONCAT(ROUND(VLOOKUP($I4, 'Fund Ranking_Debt'!$C$7:$N$13,12,FALSE),2),"%") | L4: =_xlfn.CONCAT(ROUND(VLOOKUP($I4, 'Fund Ranking_Debt'!$C$7:$N$13,10,FALSE),2),"%")
C5: 2 | D5: =VLOOKUP(C5, 'Fund Ranking_Equity'!$C$5:$D$12,2,FALSE) | E5: =_xlfn.CONCAT((ROUND(VLOOKUP($D5,'Fund Ranking_Equity'!$B$6:$T$137,5,FALSE),2)),"%") | F5: =_xlfn.CONCAT((ROUND(VLOOKUP($D5,'Fund Ranking_Equity'!$B$6:$T$137,4,FALSE),2)),"%") | I5: 2 | J5: =VLOOKUP($I5, 'Fund Ranking_Debt'!$C$7:$N$13,3,FALSE) | K5: =_xlfn.CONCAT(ROUND(VLOOKUP($I5, 'Fund Ranking_Debt'!$C$7:$N$13,12,FALSE),2),"%") | L5: =_xlfn.CONCAT(ROUND(VLOOKUP($I5, 'Fund Ranking_Debt'!$C$7:$N$13,10,FALSE),2),"%")
C6: 3 | D6: =VLOOKUP(C6, 'Fund Ranking_Equity'!$C$5:$D$12,2,FALSE) | E6: =_xlfn.CONCAT((ROUND(VLOOKUP($D6,'Fund Ranking_Equity'!$B$6:$T$137,5,FALSE),2)),"%") | F6: =_xlfn.CONCAT((ROUND(VLOOKUP($D6,'Fund Ranking_Equity'!$B$6:$T$137,4,FALSE),2)),"%") | I6: 3 | J6: =VLOOKUP($I6, 'Fund Ranking_Debt'!$C$7:$N$13,3,FALSE) | K6: =_xlfn.CONCAT(ROUND(VLOOKUP($I6, 'Fund Ranking_Debt'!$C$7:$N$13,12,FALSE),2),"%") | L6: =_xlfn.CONCAT(ROUND(VLOOKUP($I6, 'Fund Ranking_Debt'!$C$7:$N$13,10,FALSE),2),"%")
B8: ='Fund Ranking Criteria'!D4 | C8: 1 | D8: =VLOOKUP(C8, 'Fund Ranking_Equity'!$C$17:$D$23,2,FALSE) | E8: =_xlfn.CONCAT((ROUND(VLOOKUP($D8,'Fund Ranking_Equity'!$B$6:$T$137,5,FALSE),2)),"%") | F8: =_xlfn.CONCAT((ROUND(VLOOKUP($D8,'Fund Ranking_Equity'!$B$6:$T$137,4,FALSE),2)),"%") | H8: ='Fund Ranking Criteria'!D24 | I8: 1 | J8: =VLOOKUP($I8, 'Fund Ranking_Debt'!$C$19:$N$25,3,FALSE) | K8: =_xlfn.CONCAT(ROUND(VLOOKUP($I8, 'Fund Ranking_Debt'!$C$19:$N$25,12,FALSE),2),"%") | L8: =_xlfn.CONCAT(ROUND(VLOOKUP($I8, 'Fund Ranking_Debt'!$C$19:$N$25,10,FALSE),2),"%")
C9: 2 | D9: =VLOOKUP(C9, 'Fund Ranking_Equity'!$C$17:$D$23,2,FALSE) | E9: =_xlfn.CONCAT((ROUND(VLOOKUP($D9,'Fund Ranking_Equity'!$B$6:$T$137,5,FALSE),2)),"%") | F9: =_xlfn.CONCAT((ROUND(VLOOKUP($D9,'Fund Ranking_Equity'!$B$6:$T$137,4,FALSE),2)),"%") | I9: 2 | J9: =VLOOKUP($I9, 'Fund Ranking_Debt'!$C$19:$N$25,3,FALSE) | K9: =_xlfn.CONCAT(ROUND(VLOOKUP($I9, 'Fund Ranking_Debt'!$C$19:$N$25,12,FALSE),2),"%") | L9: =_xlfn.CONCAT(ROUND(VLOOKUP($I9, 'Fund Ranking_Debt'!$C$19:$N$25,10,FALSE),2),"%")
C10: 3 | D10: =VLOOKUP(C10, 'Fund Ranking_Equity'!$C$17:$D$23,2,FALSE) | E10: =_xlfn.CONCAT((ROUND(VLOOKUP($D10,'Fund Ranking_Equity'!$B$6:$T$137,5,FALSE),2)),"%") | F10: =_xlfn.CONCAT((ROUND(VLOOKUP($D10,'Fund Ranking_Equity'!$B$6:$T$137,4,FALSE),2)),"%") | I10: 3 | J10: =VLOOKUP($I10, 'Fund Ranking_Debt'!$C$19:$N$25,3,FALSE) | K10: =_xlfn.CONCAT(ROUND(VLOOKUP($I10, 'Fund Ranking_Debt'!$C$19:$N$25,12,FALSE),2),"%") | L10: =_xlfn.CONCAT(ROUND(VLOOKUP($I10, 'Fund Ranking_Debt'!$C$19:$N$25,10,FALSE),2),"%")
B12: ='Fund Ranking Criteria'!F4 | C12: 1 | D12: =VLOOKUP(C12, 'Fund Ranking_Equity'!$C$28:$D$34,2,FALSE) | E12: =_xlfn.CONCAT((ROUND(VLOOKUP($D12,'Fund Ranking_Equity'!$B$6:$T$137,5,FALSE),2)),"%") | F12: =_xlfn.CONCAT((ROUND(VLOOKUP($D12,'Fund Ranking_Equity'!$B$6:$T$137,4,FALSE),2)),"%") | H12: ='Fund Ranking Criteria'!E24 | I12: 1 | J12: =VLOOKUP($I12, 'Fund Ranking_Debt'!$C$31:$N$37,3,FALSE) | K12: =_xlfn.CONCAT(ROUND(VLOOKUP($I12, 'Fund Ranking_Debt'!$C$31:$N$37,12,FALSE),2),"%") | L12: =_xlfn.CONCAT(ROUND(VLOOKUP($I12, 'Fund Ranking_Debt'!$C$31:$N$37,10,FALSE),2),"%")
C13: 2 | D13: =VLOOKUP(C13, 'Fund Ranking_Equity'!$C$28:$D$34,2,FALSE) | E13: =_xlfn.CONCAT((ROUND(VLOOKUP($D13,'Fund Ranking_Equity'!$B$6:$T$137,5,FALSE),2)),"%") | F13: =_xlfn.CONCAT((ROUND(VLOOKUP($D13,'Fund Ranking_Equity'!$B$6:$T$137,4,FALSE),2)),"%") | I13: 2 | J13: =VLOOKUP($I13, 'Fund Ranking_Debt'!$C$31:$N$37,3,FALSE) | K13: =_xlfn.CONCAT(ROUND(VLOOKUP($I13, 'Fund Ranking_Debt'!$C$31:$N$37,12,FALSE),2),"%") | L13: =_xlfn.CONCAT(ROUND(VLOOKUP($I13, 'Fund Ranking_Debt'!$C$31:$N$37,10,FALSE),2),"%")
C14: 3 | D14: =VLOOKUP(C14, 'Fund Ranking_Equity'!$C$28:$D$34,2,FALSE) | E14: =_xlfn.CONCAT((ROUND(VLOOKUP($D14,'Fund Ranking_Equity'!$B$6:$T$137,5,FALSE),2)),"%") | F14: =_xlfn.CONCAT((ROUND(VLOOKUP($D14,'Fund Ranking_Equity'!$B$6:$T$137,4,FALSE),2)),"%") | I14: 3 | J14: =VLOOKUP($I14, 'Fund Ranking_Debt'!$C$31:$N$37,3,FALSE) | K14: =_xlfn.CONCAT(ROUND(VLOOKUP($I14, 'Fund Ranking_Debt'!$C$31:$N$37,12,FALSE),2),"%") | L14: =_xlfn.CONCAT(ROUND(VLOOKUP($I14, 'Fund Ranking_Debt'!$C$31:$N$37,10,FALSE),2),"%")
B16: ='Fund Ranking Criteria'!G4 | C16: 1 | D16: =VLOOKUP(C16, 'Fund Ranking_Equity'!$C$39:$D$45,2,FALSE) | E16: =_xlfn.CONCAT((ROUND(VLOOKUP($D16,'Fund Ranking_Equity'!$B$6:$T$137,5,FALSE),2)),"%") | F16: =_xlfn.CONCAT((ROUND(VLOOKUP($D16,'Fund Ranking_Equity'!$B$6:$T$137,4,FALSE),2)),"%") | H16: ='Fund Ranking Criteria'!F24 | I16: 1 | J16: =VLOOKUP($I16, 'Fund Ranking_Debt'!$C$42:$N$48,3,FALSE) | K16: =_xlfn.CONCAT(ROUND(VLOOKUP($I16, 'Fund Ranking_Debt'!$C$42:$N$48,12,FALSE),2),"%") | L16: =_xlfn.CONCAT(ROUND(VLOOKUP($I16, 'Fund Ranking_Debt'!$C$42:$N$48,10,FALSE),2),"%")
C17: 2 | D17: =VLOOKUP(C17, 'Fund Ranking_Equity'!$C$39:$D$45,2,FALSE) | E17: =_xlfn.CONCAT((ROUND(VLOOKUP($D17,'Fund Ranking_Equity'!$B$6:$T$137,5,FALSE),2)),"%") | F17: =_xlfn.CONCAT((ROUND(VLOOKUP($D17,'Fund Ranking_Equity'!$B$6:$T$137,4,FALSE),2)),"%") | I17: 2 | J17: =VLOOKUP($I17, 'Fund Ranking_Debt'!$C$42:$N$48,3,FALSE) | K17: =_xlfn.CONCAT(ROUND(VLOOKUP($I17, 'Fund Ranking_Debt'!$C$42:$N$48,12,FALSE),2),"%") | L17: =_xlfn.CONCAT(ROUND(VLOOKUP($I17, 'Fund Ranking_Debt'!$C$42:$N$48,10,FALSE),2),"%")
C18: 3 | D18: =VLOOKUP(C18, 'Fund Ranking_Equity'!$C$39:$D$45,2,FALSE) | E18: =_xlfn.CONCAT((ROUND(VLOOKUP($D18,'Fund Ranking_Equity'!$B$6:$T$137,5,FALSE),2)),"%") | F18: =_xlfn.CONCAT((ROUND(VLOOKUP($D18,'Fund Ranking_Equity'!$B$6:$T$137,4,FALSE),2)),"%") | I18: 3 | J18: =VLOOKUP($I18, 'Fund Ranking_Debt'!$C$42:$N$48,3,FALSE) | K18: =_xlfn.CONCAT(ROUND(VLOOKUP($I18, 'Fund Ranking_Debt'!$C$42:$N$48,12,FALSE),2),"%") | L18: =_xlfn.CONCAT(ROUND(VLOOKUP($I18, 'Fund Ranking_Debt'!$C$42:$N$48,10,FALSE),2),"%")
B20: Flexicap | C20: 1 | D20: =VLOOKUP(C20, 'Fund Ranking_Equity'!$C$50:$D$53,2,FALSE) | E20: =_xlfn.CONCAT((ROUND(VLOOKUP($D20,'Fund Ranking_Equity'!$B$6:$T$137,5,FALSE),2)),"%") | F20: =_xlfn.CONCAT((ROUND(VLOOKUP($D20,'Fund Ranking_Equity'!$B$6:$T$137,4,FALSE),2)),"%") | H20: Medium to Long Duration Fund | I20: 1 | J20: =VLOOKUP($I20, 'Fund Ranking_Debt'!$C$53:$N$59,3,FALSE) | K20: =_xlfn.CONCAT(ROUND(VLOOKUP($I20, 'Fund Ranking_Debt'!$C$53:$N$59,12,FALSE),2),"%") | L20: =_xlfn.CONCAT(ROUND(VLOOKUP($I20, 'Fund Ranking_Debt'!$C$53:$N$59,10,FALSE),2),"%")
C21: 2 | D21: =VLOOKUP(C21, 'Fund Ranking_Equity'!$C$50:$D$53,2,FALSE) | E21: =_xlfn.CONCAT((ROUND(VLOOKUP($D21,'Fund Ranking_Equity'!$B$6:$T$137,5,FALSE),2)),"%") | F21: =_xlfn.CONCAT((ROUND(VLOOKUP($D21,'Fund Ranking_Equity'!$B$6:$T$137,4,FALSE),2)),"%") | I21: 2 | J21: =VLOOKUP($I21, 'Fund Ranking_Debt'!$C$53:$N$59,3,FALSE) | K21: =_xlfn.CONCAT(ROUND(VLOOKUP($I21, 'Fund Ranking_Debt'!$C$53:$N$59,12,FALSE),2),"%") | L21: =_xlfn.CONCAT(ROUND(VLOOKUP($I21, 'Fund Ranking_Debt'!$C$53:$N$59,10,FALSE),2),"%")
C22: 3 | D22: =VLOOKUP(C22, 'Fund Ranking_Equity'!$C$50:$D$56,2,FALSE) | E22: =_xlfn.CONCAT((ROUND(VLOOKUP($D22,'Fund Ranking_Equity'!$B$6:$T$137,5,FALSE),2)),"%") | F22: =_xlfn.CONCAT((ROUND(VLOOKUP($D22,'Fund Ranking_Equity'!$B$6:$T$137,4,FALSE),2)),"%") | I22: 3 | J22: =VLOOKUP($I22, 'Fund Ranking_Debt'!$C$53:$N$59,3,FALSE) | K22: =_xlfn.CONCAT(ROUND(VLOOKUP($I22, 'Fund Ranking_Debt'!$C$53:$N$59,12,FALSE),2),"%") | L22: =_xlfn.CONCAT(ROUND(VLOOKUP($I22, 'Fund Ranking_Debt'!$C$53:$N$59,10,FALSE),2),"%")
B24: ='Fund Ranking Criteria'!H4 | C24: 1 | D24: =VLOOKUP($C24,'Fund Ranking_Equity'!$C$61:$E$67,2,FALSE) | E24: =_xlfn.CONCAT((ROUND(VLOOKUP($D24,'Fund Ranking_Equity'!$B$6:$T$137,5,FALSE),2)),"%") | F24: =_xlfn.CONCAT((ROUND(VLOOKUP($D24,'Fund Ranking_Equity'!$B$6:$T$137,4,FALSE),2)),"%")
C25: 2 | D25: =VLOOKUP($C25,'Fund Ranking_Equity'!$C$61:$E$67,2,FALSE) | E25: =_xlfn.CONCAT((ROUND(VLOOKUP($D25,'Fund Ranking_Equity'!$B$6:$T$137,5,FALSE),2)),"%") | F25: =_xlfn.CONCAT((ROUND(VLOOKUP($D25,'Fund Ranking_Equity'!$B$6:$T$137,4,FALSE),2)),"%")
C26: 3 | D26: =VLOOKUP($C26,'Fund Ranking_Equity'!$C$61:$E$67,2,FALSE) | E26: =_xlfn.CONCAT((ROUND(VLOOKUP($D26,'Fund Ranking_Equity'!$B$6:$T$137,5,FALSE),2)),"%") | F26: =_xlfn.CONCAT((ROUND(VLOOKUP($D26,'Fund Ranking_Equity'!$B$6:$T$137,4,FALSE),2)),"%")
B28: Multi-Asset | C28: 1 | D28: =VLOOKUP(C28, 'Fund Ranking_Equity'!$C$72:$D$78,2,FALSE) | E28: =_xlfn.CONCAT((ROUND(VLOOKUP($D28,'Fund Ranking_Equity'!$B$6:$T$137,5,FALSE),2)),"%") | F28: =_xlfn.CONCAT((ROUND(VLOOKUP($D28,'Fund Ranking_Equity'!$B$6:$T$137,4,FALSE),2)),"%")
C29: 2 | D29: =VLOOKUP(C29, 'Fund Ranking_Equity'!$C$72:$D$78,2,FALSE) | E29: =_xlfn.CONCAT((ROUND(VLOOKUP($D29,'Fund Ranking_Equity'!$B$6:$T$137,5,FALSE),2)),"%") | F29: =_xlfn.CONCAT((ROUND(VLOOKUP($D29,'Fund Ranking_Equity'!$B$6:$T$137,4,FALSE),2)),"%")
C30: 3 | D30: =VLOOKUP(C30, 'Fund Ranking_Equity'!$C$72:$D$78,2,FALSE) | E30: =_xlfn.CONCAT((ROUND(VLOOKUP($D30,'Fund Ranking_Equity'!$B$6:$T$137,5,FALSE),2)),"%") | F30: =_xlfn.CONCAT((ROUND(VLOOKUP($D30,'Fund Ranking_Equity'!$B$6:$T$137,4,FALSE),2)),"%")
C32: Ranking | D32: Funds (Equity)
B33: Consolidated | C33: 1 | D33: =VLOOKUP(C33,#REF!, 2,FALSE)
C34: 2 | D34: =VLOOKUP(C34,#REF!, 2,FALSE)
C35: =C34+1 | D35: =VLOOKUP(C35,#REF!, 2,FALSE)
C36: =C35+1 | D36: =VLOOKUP(C36,#REF!, 2,FALSE)
C37: =C36+1 | D37: =VLOOKUP(C37,#REF!, 2,FALSE)
C38: =C37+1 | D38: =VLOOKUP(C38,#REF!, 2,FALSE)
C39: =C38+1 | D39: =VLOOKUP(C39,#REF!, 2,FALSE)
C40: =C39+1 | D40: =VLOOKUP(C40,#REF!, 2,FALSE)
C41: =C40+1 | D41: =VLOOKUP(C41,#REF!, 2,FALSE)
C42: =C41+1 | D42: =VLOOKUP(C42,#REF!, 2,FALSE)
B43: Thematic | C43: 1 | D43: =VLOOKUP('Summary '!$C24,'Fund Ranking_Equity'!$C$83:$E$137,2,FALSE) | E43: =_xlfn.CONCAT((ROUND(VLOOKUP($D43,'Fund Ranking_Equity'!$B$6:$T$137,5,FALSE),2)),"%") | F43: =_xlfn.CONCAT((ROUND(VLOOKUP($D43,'Fund Ranking_Equity'!$B$6:$T$137,4,FALSE),2)),"%")
C44: 2 | D44: =VLOOKUP('Summary '!$C25,'Fund Ranking_Equity'!$C$83:$E$137,2,FALSE) | E44: =_xlfn.CONCAT((ROUND(VLOOKUP($D44,'Fund Ranking_Equity'!$B$6:$T$137,5,FALSE),2)),"%") | F44: =_xlfn.CONCAT((ROUND(VLOOKUP($D44,'Fund Ranking_Equity'!$B$6:$T$137,4,FALSE),2)),"%")
C45: 3 | D45: =VLOOKUP('Summary '!$C26,'Fund Ranking_Equity'!$C$83:$E$137,2,FALSE) | E45: =_xlfn.CONCAT((ROUND(VLOOKUP($D45,'Fund Ranking_Equity'!$B$6:$T$137,5,FALSE),2)),"%") | F45: =_xlfn.CONCAT((ROUND(VLOOKUP($D45,'Fund Ranking_Equity'!$B$6:$T$137,4,FALSE),2)),"%")

Sheet Investor Profile
B3: S.No. | C3: Question | D3: Options | E3: Score Assigned | G3: Questions | I3: Investor Profile
B4: Personal & Financial Information | G4: Age | I4: Early Career | J4: Mid-Career | K4: Pre-Retirement | L4: Retirement
B5: 1 | C5: Age | D5: 18-30 | E5: 4 | G5: (Question 1) | I5: 4 | J5: 3 | K5: 2 | L5: 1
D6: 31-45 | E6: 3 | G6: Financial Standing | I6: Limited Resources | J6: Stable Financials | K6: Affluent | L6: HNI/UHNI
D7: 46-60 | E7: 2 | G7: (Question 2+3+4) | I7: <5 | J7: (6 - 8) | K7: (9-12) | L7: 13>
D8: 60+ | E8: 1 | G8: Investment Objectives | I8: Wealth Creation | J8: Regular Income | K8: Safety & Stability | L8: Aggressive Growth
B9: =B5+1 | C9: Annual Income | D9: Below ₹5 lakh | E9: 0 | G9: (Question 6) | I9: 1 | J9: 2 | K9: 3 | L9: 4
D10: ₹5-10 lakh | E10: 1 | G10: Time Horizon | I10: Short Term | J10: Short to Medium Term | K10: Medium Term | L10: Long Term
D11: ₹10-25 lakh | E11: 2 | G11: (Question 7) | I11: 1 | J11: 2 | K11: 3 | L11: 4
D12: ₹25-50 lakh | E12: 3 | G12: Risk Appetite | I12: Conservative | J12: Aggressive
D13: ₹50-100 lakh | E13: 4 | G13: (Question 8) | I13: 1 | J13: 2
D14: Above ₹1 Cr | E14: 5 | G14: Investment Knowledge | I14: Beginner | J14: Basic Knowledge | K14: Moderate Knowledge | L14: Advanced Knowledge
B15: 3 | C15: Annual Family Income | D15: ₹5-10 lakh | E15: 1 | G15: (Question 9 + 10 ) | I15: 2 | J15: 3 | K15: 4 | L15: 5
D16: ₹10-25 lakh | E16: 2
D17: ₹25-50 lakh | E17: 3
D18: ₹50-100 lakh | E18: 4 | G18: Questions | I18: Model Portfolio
D19: Above ₹1 Cr | E19: 5 | G19: Age | I19: Early Career | J19: Mid-Career | K19: Pre-Retirement | L19: Retirement
B20: 4 | C20: Monthly Savings | D20: Less than 10% | E20: 1 | G20: Type of MF | I20: SIP | J20: Lumpsum/SIP | K20: =J20 | L20: =K20
D21: 10%-15% | E21: 2 | G21: Equity:Debt | I21: 80:20 | J21: 70:30 | K21: 50:50 | L21: 40:60
D22: 15-20% | E22: 3 | G22: Suggested Funds: Equity | I22: =_xlfn.CONCAT(Backup!$B$36, ", ",Backup!$B$38,", ",Backup!$B$37, ", ",Backup!$B$40, ", ",Backup!$B$41) | J22: =_xlfn.CONCAT(Backup!$B$35, ", ", Backup!$B$36, ", ",Backup!$B$37, ", ",Backup!$B$40, ", ",Backup!$B$41) | K22: =_xlfn.CONCAT(Backup!$B$35, ", ", Backup!$B$36, ", ",Backup!$B$37, ", ",Backup!$B$40, ", ",Backup!$B$41) | L22: =_xlfn.CONCAT(Backup!$B$35, ", ", Backup!$B$36)
D23: 20-30% | E23: 4 | G23: Suggested Funds: Debt | I23: =_xlfn.CONCAT(Backup!$C$35, " ,",Backup!$C$36) | J23: =_xlfn.CONCAT(Backup!$C$35, " ,",Backup!$C$36, " ,",Backup!$C$37 ) | K23: =_xlfn.CONCAT(Backup!$C$35, " ,",Backup!$C$36, " ,",Backup!$C$37 ) | L23: =_xlfn.CONCAT(Backup!$C$35, " ,",Backup!$C$36, " ,",Backup!$C$37 )
D24: More than 30% | E24: 5 | G24: Financial Standing | I24: Limited Resources | J24: Stable Financials | K24: Affluent | L24: HNI/UHNI
B25: Investment Objective | G25: Type of MF | I25: SIP | J25: Lumpsum/SIP | K25: =J25 | L25: =K25
B26: 6 | C26: Investment Goal | D26: Wealth Creation | E26: 1 | G26: Equity:Debt | I26: 40:60 | J26: 50:50 | K26: 70:30 | L26: 70:30
D27: Income-Oriented | E27: 2 | G27: Suggested Funds: Equity | I27: =L22 | J27: =K22 | K27: =J22 | L27: =_xlfn.CONCAT(Backup!$B$36, ", ",Backup!$B$38,", ",Backup!$B$37, ", ",Backup!$B$40, ", ",Backup!$B$41)
D28: Capital Protection | E28: 3 | G28: Suggested Funds: Debt | I28: =I23 | J28: =L23 | K28: =K23 | L28: =K28
D29: Aggressive Growth | E29: 4 | G29: Investment Objectives | I29: Wealth Creation | J29: Regular Income | K29: Safety & Stability | L29: Aggressive Growth
B30: 7 | C30: Investment Horizon | D30: Less than 1 year | E30: 1 | G30: Type of MF | I30: Lumpsum/SIP | J30: Lumpsum | K30: Lumpsum/SIP | L30: SIP
D31: 1-3 years | E31: 2 | G31: Equity:Debt | I31: =L31 | J31: =J26 | K31: 20:80 | L31: 80:20
D32: 3-5 years | E32: 3 | G32: Suggested Funds: Equity | I32: =J27 | J32: =J27 | K32: =_xlfn.CONCAT(Backup!$B$35, ", ", Backup!$B$36) | L32: =_xlfn.CONCAT(Backup!$B$39, ", ", Backup!$B$38)
D33: 5+ years | E33: 4 | G33: Suggested Funds: Debt | I33: =I28 | J33: =J28 | K33: =I33 | L33: =I43
B34: Risk Appetite | G34: Time Horizon | I34: Short Term | J34: Short to Medium Term | K34: Medium Term | L34: Long Term
B35: 8 | C35: Will you be okay with? | D35: Gain/Loss of 15% | E35: 2 | G35: Type of MF | I35: =I40 | J35: =I35 | K35: =K30 | L35: =K35
D36: Fixed gain of 5% | E36: 1 | G36: Equity:Debt | I36: 80:20 | J36: 50:50 | K36: 50:50 | L36: 20:80
B37: Market Experience | G37: Suggested Funds: Equity | I37: =L32 | J37: =_xlfn.CONCAT(Backup!$B$39, ", ", Backup!$B$38, ", ",Backup!$B$37, ", ",Backup!$B$40, ", ",Backup!$B$41) | K37: =_xlfn.CONCAT(Backup!$B$38, ", ",Backup!$B$37, ", ",Backup!$B$40, ", ",Backup!$B$41) | L37: =_xlfn.CONCAT(Backup!$B$35, ", ", Backup!$B$36)
B38: 9 | C38: Market Experience | D38: No exposure | E38: 1 | G38: Suggested Funds: Debt | I38: =I33 | J38: =J33 | K38: =K33 | L38: =L33
D39: Limited exposure | E39: 2 | G39: Risk Appetite | I39: Conservative | J39: Aggressive
D40: Actively invest or trade | E40: 3 | G40: Type of MF | I40: Lumpsum | J40: SIP
B41: 10 | C41: Knowledge of Investments | D41: Very Little to no knowledge | E41: 1 | G41: Equity:Debt | I41: 20:80 | J41: 80:20
D42: Moderate level of knowledge | E42: 2 | G42: Suggested Funds: Equity | I42: =_xlfn.CONCAT(Backup!$B$37, ", ",Backup!$B$40, ", ",Backup!$B$41, Backup!$B$35, ", ", Backup!$B$36) | J42: =J37
D43: Extensive investment knowledge | E43: 3 | G43: Suggested Funds: Debt | I43: =_xlfn.CONCAT(Backup!$C$38," ,",Backup!$C$37," ,",Backup!$C$39) | J43: =_xlfn.CONCAT(Backup!$C$35, " ,",Backup!$C$36)
G44: Investment Knowledge | I44: Beginner | J44: Basic Knowledge | K44: Moderate Knowledge | L44: Advanced Knowledge
G45: Type of MF | I45: SIP | J45: =K45 | K45: =I45 | L45: Lumpsum/SIP
G46: Equity:Debt | I46: 70:30 | J46: =K46 | K46: 50:50 | L46: 80:20
G47: Suggested Funds: Equity | I47: =L37 | J47: =K47 | K47: =K37 | L47: =J37
G48: Suggested Funds: Debt | I48: =J43 | J48: =K48 | K48: Ultra Short Duration Fund ,Low Duration Fund ,Short Duration Fund | L48: =L38

Sheet Investor Persona
F2: 2 | G2: 3 | H2: 4 | I2: 5
B3: Quesitons | C3: Option | D3: Points | E3: Persona | F3: Type of MF | G3: Equity:Debt | H3: Suggested Funds: Equity | I3: Suggested Funds: Debt
B4: Age | C4: 18-30 | D4: =VLOOKUP($C4, 'Investor Profile'!$D$5:$E$14,2,FALSE) | E4: {=_xlfn.IFS(D4='Investor Profile'!I5,'Investor Profile'!I4, D4='Investor Profile'!J5, 'Investor Profile'!J4, D4='Investor Profile'!K5, 'Investor Profile'!K4, D4='Investor Profile'!L5, 'Investor Profile'!L4)} | F4: =HLOOKUP('Investor Persona'!$E$4, 'Investor Profile'!$I$19:$L$23,F$2,FALSE) | G4: =HLOOKUP('Investor Persona'!$E$4, 'Investor Profile'!$I$19:$L$23,G$2,FALSE) | H4: =HLOOKUP('Investor Persona'!$E$4, 'Investor Profile'!$I$19:$L$23,H$2,FALSE) | I4: =HLOOKUP('Investor Persona'!$E$4, 'Investor Profile'!$I$19:$L$23,I$2,FALSE)
B5: Annual Income | C5: ₹10-25 lakh | D5: =VLOOKUP($C5, 'Investor Profile'!$D$5:$E$14,2,FALSE) | E5: =IF(SUM($D$5:$D$7)<5,"Limited Resources",IF(SUM($D$5:$D$7)<=8,"Stable Financials",IF(SUM($D$5:$D$7)<=12,"Affluent",IF(SUM($D$5:$D$7)>=13,"HNI/UHNI","")))) | F5: =HLOOKUP('Investor Persona'!$E$5, 'Investor Profile'!$I$24:$L$28,F$2,FALSE) | G5: =HLOOKUP('Investor Persona'!$E$5, 'Investor Profile'!$I$24:$L$28,G$2,FALSE) | H5: =HLOOKUP('Investor Persona'!$E$5, 'Investor Profile'!$I$24:$L$28,H$2,FALSE) | I5: =HLOOKUP('Investor Persona'!$E$5, 'Investor Profile'!$I$24:$L$28,I$2,FALSE)
B6: Annual Family Income | C6: ₹25-50 lakh | D6: =VLOOKUP($C6, 'Investor Profile'!$D$15:$E$19,2,FALSE)
B7: Monthly Savings | C7: Less than 10% | D7: =VLOOKUP($C7, 'Investor Profile'!$D$20:$E$24,2,FALSE)
B8: Investment Goal | C8: Aggressive Growth | D8: =VLOOKUP($C8, 'Investor Profile'!$D$26:$E$33,2,FALSE) | E8: {=_xlfn.IFS(D8='Investor Profile'!I9,'Investor Profile'!I8, D8='Investor Profile'!J9, 'Investor Profile'!J8, D8='Investor Profile'!K9, 'Investor Profile'!K8, D8='Investor Profile'!L9, 'Investor Profile'!L8)} | F8: =HLOOKUP('Investor Persona'!$E$8, 'Investor Profile'!$I$29:$L$33,F$2,FALSE) | G8: =HLOOKUP('Investor Persona'!$E$8, 'Investor Profile'!$I$29:$L$33,G$2,FALSE) | H8: =HLOOKUP('Investor Persona'!$E$8, 'Investor Profile'!$I$29:$L$33,H$2,FALSE) | I8: =HLOOKUP('Investor Persona'!$E$8, 'Investor Profile'!$I$29:$L$33,I$2,FALSE)
B9: Investment Horizon | C9: Less than 1 year | D9: =VLOOKUP($C9, 'Investor Profile'!$D$26:$E$33,2,FALSE) | E9: {=_xlfn.IFS(D9='Investor Profile'!I11,'Investor Profile'!I10, D9='Investor Profile'!J11, 'Investor Profile'!J10, D9='Investor Profile'!K11, 'Investor Profile'!K10, D9='Investor Profile'!L11, 'Investor Profile'!L10)} | F9: =HLOOKUP('Investor Persona'!$E$9, 'Investor Profile'!$I$34:$L$38,F$2,FALSE) | G9: =HLOOKUP('Investor Persona'!$E$9, 'Investor Profile'!$I$34:$L$38,G$2,FALSE) | H9: =HLOOKUP('Investor Persona'!$E$9, 'Investor Profile'!$I$34:$L$38,H$2,FALSE) | I9: =HLOOKUP('Investor Persona'!$E$9, 'Investor Profile'!$I$34:$L$38,I$2,FALSE)
B10: Will you be okay with? | C10: Fixed gain of 5% | D10: =VLOOKUP($C10,'Investor Profile'!$D$35:$E$36,2,FALSE) | E10: =IF(SUM($D$10:$D$10)=1,"Conservative",IF(SUM($D$10:$D$10)=2,"Aggressive","")) | F10: =HLOOKUP('Investor Persona'!$E$10,'Investor Profile'!$I$39:$J$43,F$2,FALSE) | G10: =HLOOKUP('Investor Persona'!$E$10,'Investor Profile'!$I$39:$J$43,G$2,FALSE) | H10: =HLOOKUP('Investor Persona'!$E$10,'Investor Profile'!$I$39:$J$43,H$2,FALSE) | I10: =HLOOKUP('Investor Persona'!$E$10,'Investor Profile'!$I$39:$J$43,I$2,FALSE)
B11: Market Experience | C11: Actively invest or trade | D11: =VLOOKUP($C11, 'Investor Profile'!$D$38:$E$43,2,FALSE) | E11: {=_xlfn.IFS(SUM($D$11:$D$12)='Investor Profile'!I15,'Investor Profile'!I14, SUM($D$11:$D$12)='Investor Profile'!J15, 'Investor Profile'!J14, SUM($D$11:$D$12)='Investor Profile'!K15, 'Investor Profile'!K14, SUM($D$11:$D$12)='Investor Profile'!L15, 'Investor Profile'!L14, SUM($D$11:$D$12)=6, 'Investor Profile'!L14)} | F11: =HLOOKUP('Investor Persona'!$E$11,'Investor Profile'!$I$44:$L$48,F$2,FALSE) | G11: =HLOOKUP('Investor Persona'!$E$11,'Investor Profile'!$I$44:$L$48,G$2,FALSE) | H11: =HLOOKUP('Investor Persona'!$E$11,'Investor Profile'!$I$44:$L$48,H$2,FALSE) | I11: =HLOOKUP('Investor Persona'!$E$11,'Investor Profile'!$I$44:$L$48,I$2,FALSE)
B12: Knowledge of Investments | C12: Extensive investment knowledge | D12: =VLOOKUP($C12, 'Investor Profile'!$D$38:$E$43,2,FALSE)
B14: Investable Surplus
B15: Annual Savings | C15: =10*10^5
B16: Additonal Funds avbl | C16: =20*10^5

Sheet Fund Ranking_Equity
B1: (Match with morningstar)
B2: Model Portfolio | E2: 2 | F2: =E2+1 | G2: =F2+1 | H2: =G2+1 | I2: =H2+1 | J2: =I2+1 | K2: =J2+1 | L2: =K2+1 | M2: =L2+1 | ... O2: =N2+1
B3: Equity Large Cap
E4: Actuals | M4: Normalized
B5: Funds | C5: Rank | E5: 1 Yr Ret (%) | F5: 3 Yr Ret (%) | G5: 5 Yr Ret (%) | H5: 10 Yr Ret (%) | I5: Sharpe | J5: Alpha | K5: Beta | L5: SD | M5: =F5 | N5: =G5 | O5: =H5 | P5: Sharpe | Q5: Alpha | R5: Beta | S5: SD | T5: Score
B6: Aditya Birla Sun Life Large Cap Fund - Reg - Growth | C6: =RANK(T6,$T$6:$T$12,0) | D6: =B6 | E6: -2.002 | F6: 11.2256 | G6: 11.1189 | H6: 11.8935 | I6: 0.049888288 | J6: 0.059299269 | K6: 1.0051105 | L6: 12.136713 | M6: =(F6-MIN(F$6:F$12))/(MAX(F$6:F$12)-MIN(F$6:F$12)) | N6: =(G6-MIN(G$6:G$12))/(MAX(G$6:G$12)-MIN(G$6:G$12)) | O6: =(H6-MIN(H$6:H$12))/(MAX(H$6:H$12)-MIN(H$6:H$12)) | P6: =(I6-MIN(I$6:I$12))/(MAX(I$6:I$12)-MIN(I$6:I$12)) | Q6: =(J6-MIN(J$6:J$12))/(MAX(J$6:J$12)-MIN(J$6:J$12)) | R6: =(MAX(K$6:K$12)-K6)/(MAX(K$6:K$12)-MIN(K$6:K$12)) | S6: =(MAX(L$6:L$12)-L6)/(MAX(L$6:L$12)-MIN(L$6:L$12)) | T6: =(M6*'Fund Ranking Criteria'!$C$9)+('Fund Ranking_Equity'!N6*'Fund Ranking Criteria'!$C$10)+('Fund Ranking_Equity'!O6*'Fund Ranking Criteria'!$C$11)+('Fund Ranking_Equity'!P6*'Fund Ranking Criteria'!$C$16)+('Fund Ranking_Equity'!Q6*'Fund Ranking Criteria'!$C$12)+('Fund Ranking_Equity'!R6*'Fund Ranking Criteria'!$C$14)+('Fund Ranking_Equity'!S6*'Fund Ranking Criteria'!$C$15) | Z6: 1 | AA6: 21 | AB6: =(Z6-MIN(Z$6:Z$10))/(MAX(Z$6:Z$10)-MIN(R$6:R$12)) | AC6: =(AA6-MIN(AA$6:AA$10))/(MAX(AA$6:AA$10)-MIN(S$6:S$12))
B7: HDFC Large Cap Fund - Growth | C7: =RANK(T7,$T$6:$T$12,0) | D7: =B7 | E7: -0.4423 | F7: 11.4781 | G7: 12.4019 | H7: 12.791 | I7: 0.052728061 | J7: 0.088750739 | K7: 0.94065441 | L7: 11.377351 | M7: =(F7-MIN(F$6:F$12))/(MAX(F$6:F$12)-MIN(F$6:F$12)) | N7: =(G7-MIN(G$6:G$12))/(MAX(G$6:G$12)-MIN(G$6:G$12)) | O7: =(H7-MIN(H$6:H$12))/(MAX(H$6:H$12)-MIN(H$6:H$12)) | P7: =(I7-MIN(I$6:I$12))/(MAX(I$6:I$12)-MIN(I$6:I$12)) | Q7: =(J7-MIN(J$6:J$12))/(MAX(J$6:J$12)-MIN(J$6:J$12)) | R7: =(MAX(K$6:K$12)-K7)/(MAX(K$6:K$12)-MIN(K$6:K$12)) | S7: =(MAX(L$6:L$12)-L7)/(MAX(L$6:L$12)-MIN(L$6:L$12)) | T7: =(M7*'Fund Ranking Criteria'!$C$9)+('Fund Ranking_Equity'!N7*'Fund Ranking Criteria'!$C$10)+('Fund Ranking_Equity'!O7*'Fund Ranking Criteria'!$C$11)+('Fund Ranking_Equity'!P7*'Fund Ranking Criteria'!$C$16)+('Fund Ranking_Equity'!Q7*'Fund Ranking Criteria'!$C$12)+('Fund Ranking_Equity'!R7*'Fund Ranking Criteria'!$C$14)+('Fund Ranking_Equity'!S7*'Fund Ranking Criteria'!$C$15) | Z7: 2 | AA7: 22 | AB7: =(Z7-MIN(Z$6:Z$10))/(MAX(Z$6:Z$10)-MIN(R$6:R$12)) | AC7: =(AA7-MIN(AA$6:AA$10))/(MAX(AA$6:AA$10)-MIN(S$6:S$12))
B8: ICICI Prudential Large Cap Fund - Growth | C8: =RANK(T8,$T$6:$T$12,0) | D8: =B8 | E8: -0.4865 | F8: 13.8612 | G8: 13.5597 | H8: 13.8737 | I8: 0.068997685 | J8: 0.27377151 | K8: 0.93611663 | L8: 11.340389 | M8: =(F8-MIN(F$6:F$12))/(MAX(F$6:F$12)-MIN(F$6:F$12)) | N8: =(G8-MIN(G$6:G$12))/(MAX(G$6:G$12)-MIN(G$6:G$12)) | O8: =(H8-MIN(H$6:H$12))/(MAX(H$6:H$12)-MIN(H$6:H$12)) | P8: =(I8-MIN(I$6:I$12))/(MAX(I$6:I$12)-MIN(I$6:I$12)) | Q8: =(J8-MIN(J$6:J$12))/(MAX(J$6:J$12)-MIN(J$6:J$12)) | R8: =(MAX(K$6:K$12)-K8)/(MAX(K$6:K$12)-MIN(K$6:K$12)) | S8: =(MAX(L$6:L$12)-L8)/(MAX(L$6:L$12)-MIN(L$6:L$12)) | T8: =(M8*'Fund Ranking Criteria'!$C$9)+('Fund Ranking_Equity'!N8*'Fund Ranking Criteria'!$C$10)+('Fund Ranking_Equity'!O8*'Fund Ranking Criteria'!$C$11)+('Fund Ranking_Equity'!P8*'Fund Ranking Criteria'!$C$16)+('Fund Ranking_Equity'!Q8*'Fund Ranking Criteria'!$C$12)+('Fund Ranking_Equity'!R8*'Fund Ranking Criteria'!$C$14)+('Fund Ranking_Equity'!S8*'Fund Ranking Criteria'!$C$15) | Z8: 3 | AA8: 23 | AB8: =(Z8-MIN(Z$6:Z$10))/(MAX(Z$6:Z$10)-MIN(R$6:R$12)) | AC8: =(AA8-MIN(AA$6:AA$10))/(MAX(AA$6:AA$10)-MIN(S$6:S$12))
B9: Kotak Large Cap Fund - Reg - Growth | C9: =RANK(T9,$T$6:$T$12,0) | D9: =B9 | E9: -0.5757 | F9: 11.7087 | G9: 10.7128 | H9: 12.3551 | I9: 0.051061581 | J9: 0.076524436 | K9: 1.0025883 | L9: 12.168335 | M9: =(F9-MIN(F$6:F$12))/(MAX(F$6:F$12)-MIN(F$6:F$12)) | N9: =(G9-MIN(G$6:G$12))/(MAX(G$6:G$12)-MIN(G$6:G$12)) | O9: =(H9-MIN(H$6:H$12))/(MAX(H$6:H$12)-MIN(H$6:H$12)) | P9: =(I9-MIN(I$6:I$12))/(MAX(I$6:I$12)-MIN(I$6:I$12)) | Q9: =(J9-MIN(J$6:J$12))/(MAX(J$6:J$12)-MIN(J$6:J$12)) | R9: =(MAX(K$6:K$12)-K9)/(MAX(K$6:K$12)-MIN(K$6:K$12)) | S9: =(MAX(L$6:L$12)-L9)/(MAX(L$6:L$12)-MIN(L$6:L$12)) | T9: =(M9*'Fund Ranking Criteria'!$C$9)+('Fund Ranking_Equity'!N9*'Fund Ranking Criteria'!$C$10)+('Fund Ranking_Equity'!O9*'Fund Ranking Criteria'!$C$11)+('Fund Ranking_Equity'!P9*'Fund Ranking Criteria'!$C$16)+('Fund Ranking_Equity'!Q9*'Fund Ranking Criteria'!$C$12)+('Fund Ranking_Equity'!R9*'Fund Ranking Criteria'!$C$14)+('Fund Ranking_Equity'!S9*'Fund Ranking Criteria'!$C$15) | Z9: 4 | AA9: 24 | AB9: =(Z9-MIN(Z$6:Z$10))/(MAX(Z$6:Z$10)-MIN(R$6:R$12)) | AC9: =(AA9-MIN(AA$6:AA$10))/(MAX(AA$6:AA$10)-MIN(S$6:S$12))
B10: Nippon India Large Cap Fund - Reg - Growth | C10: =RANK(T10,$T$6:$T$12,0) | D10: =B10 | E10: 0.4303 | F10: 13.9831 | G10: 15.4461 | H10: 14.4275 | I10: 0.066561396 | J10: 0.26438514 | K10: 0.99026881 | L10: 12.058927 | M10: =(F10-MIN(F$6:F$12))/(MAX(F$6:F$12)-MIN(F$6:F$12)) | N10: =(G10-MIN(G$6:G$12))/(MAX(G$6:G$12)-MIN(G$6:G$12)) | O10: =(H10-MIN(H$6:H$12))/(MAX(H$6:H$12)-MIN(H$6:H$12)) | P10: =(I10-MIN(I$6:I$12))/(MAX(I$6:I$12)-MIN(I$6:I$12)) | Q10: =(J10-MIN(J$6:J$12))/(MAX(J$6:J$12)-MIN(J$6:J$12)) | R10: =(MAX(K$6:K$12)-K10)/(MAX(K$6:K$12)-MIN(K$6:K$12)) | S10: =(MAX(L$6:L$12)-L10)/(MAX(L$6:L$12)-MIN(L$6:L$12)) | T10: =(M10*'Fund Ranking Criteria'!$C$9)+('Fund Ranking_Equity'!N10*'Fund Ranking Criteria'!$C$10)+('Fund Ranking_Equity'!O10*'Fund Ranking Criteria'!$C$11)+('Fund Ranking_Equity'!P10*'Fund Ranking Criteria'!$C$16)+('Fund Ranking_Equity'!Q10*'Fund Ranking Criteria'!$C$12)+('Fund Ranking_Equity'!R10*'Fund Ranking Criteria'!$C$14)+('Fund Ranking_Equity'!S10*'Fund Ranking Criteria'!$C$15) | Z10: 5 | AA10: 25 | AB10: =(Z10-MIN(Z$6:Z$10))/(MAX(Z$6:Z$10)-MIN(R$6:R$12)) | AC10: =(AA10-MIN(AA$6:AA$10))/(MAX(AA$6:AA$10)-MIN(S$6:S$12))
B11: SBI Large Cap Fund - Growth | C11: =RANK(T11,$T$6:$T$12,0) | D11: =B11 | E11: 2.9892 | F11: 10.9705 | G11: 11.5415 | H11: 12.193 | I11: 0.051727733 | J11: 0.080917883 | K11: 0.90560494 | L11: 11.080547 | M11: =(F11-MIN(F$6:F$12))/(MAX(F$6:F$12)-MIN(F$6:F$12)) | N11: =(G11-MIN(G$6:G$12))/(MAX(G$6:G$12)-MIN(G$6:G$12)) | O11: =(H11-MIN(H$6:H$12))/(MAX(H$6:H$12)-MIN(H$6:H$12)) | P11: =(I11-MIN(I$6:I$12))/(MAX(I$6:I$12)-MIN(I$6:I$12)) | Q11: =(J11-MIN(J$6:J$12))/(MAX(J$6:J$12)-MIN(J$6:J$12)) | R11: =(MAX(K$6:K$12)-K11)/(MAX(K$6:K$12)-MIN(K$6:K$12)) | S11: =(MAX(L$6:L$12)-L11)/(MAX(L$6:L$12)-MIN(L$6:L$12)) | T11: =(M11*'Fund Ranking Criteria'!$C$9)+('Fund Ranking_Equity'!N11*'Fund Ranking Criteria'!$C$10)+('Fund Ranking_Equity'!O11*'Fund Ranking Criteria'!$C$11)+('Fund Ranking_Equity'!P11*'Fund Ranking Criteria'!$C$16)+('Fund Ranking_Equity'!Q11*'Fund Ranking Criteria'!$C$12)+('Fund Ranking_Equity'!R11*'Fund Ranking Criteria'!$C$14)+('Fund Ranking_Equity'!S11*'Fund Ranking Criteria'!$C$15)
B12: UTI Large Cap Fund - Growth | C12: =RANK(T12,$T$6:$T$12,0) | D12: =B12 | E12: -3.5665 | F12: 8.9278 | G12: 8.5846 | H12: 11.3686 | I12: 0.03611377 | J12: -0.10210614 | K12: 0.9635905 | L12: 11.676056 | M12: =(F12-MIN(F$6:F$12))/(MAX(F$6:F$12)-MIN(F$6:F$12)) | N12: =(G12-MIN(G$6:G$12))/(MAX(G$6:G$12)-MIN(G$6:G$12)) | O12: =(H12-MIN(H$6:H$12))/(MAX(H$6:H$12)-MIN(H$6:H$12)) | P12: =(I12-MIN(I$6:I$12))/(MAX(I$6:I$12)-MIN(I$6:I$12)) | Q12: =(J12-MIN(J$6:J$12))/(MAX(J$6:J$12)-MIN(J$6:J$12)) | R12: =(MAX(K$6:K$12)-K12)/(MAX(K$6:K$12)-MIN(K$6:K$12)) | S12: =(MAX(L$6:L$12)-L12)/(MAX(L$6:L$12)-MIN(L$6:L$12)) | T12: =(M12*'Fund Ranking Criteria'!$C$9)+('Fund Ranking_Equity'!N12*'Fund Ranking Criteria'!$C$10)+('Fund Ranking_Equity'!O12*'Fund Ranking Criteria'!$C$11)+('Fund Ranking_Equity'!P12*'Fund Ranking Criteria'!$C$16)+('Fund Ranking_Equity'!Q12*'Fund Ranking Criteria'!$C$12)+('Fund Ranking_Equity'!R12*'Fund Ranking Criteria'!$C$14)+('Fund Ranking_Equity'!S12*'Fund Ranking Criteria'!$C$15)
B14: Equity Large & Mid Cap
E15: Actuals | M15: Normalized
B16: Funds | C16: Rank | E16: 1 Yr Ret (%) | F16: 3 Yr Ret (%) | G16: 5 Yr Ret (%) | H16: 10 Yr Ret (%) | I16: Sharpe | J16: Alpha | K16: Beta | L16: SD | M16: =F16 | N16: =G16 | O16: =H16 | P16: Sharpe | Q16: Alpha | R16: Beta | S16: SD
B17: SBI Large & Midcap Fund - Growth | C17: =RANK(T17,$T$17:$T$23,0) | D17: =B17 | E17: 5.387 | F17: 14.3265 | G17: 14.6185 | H17: 14.9006 | I17: 0.07160622 | J17: 0.10237556 | K17: 0.84584071 | L17: 11.693356 | M17: =(F17-MIN(F$17:F$23))/(MAX(F$17:F$23)-MIN(F$17:F$23)) | N17: =(G17-MIN(G$17:G$23))/(MAX(G$17:G$23)-MIN(G$17:G$23)) | O17: =(H17-MIN(H$17:H$23))/(MAX(H$17:H$23)-MIN(H$17:H$23)) | P17: =(I17-MIN(I$17:I$23))/(MAX(I$17:I$23)-MIN(I$17:I$23)) | Q17: =(J17-MIN(J$17:J$23))/(MAX(J$17:J$23)-MIN(J$17:J$23)) | R17: =(MAX(K$17:K$23)-K17)/(MAX(K$17:K$23)-MIN(K$17:K$23)) | S17: =(MAX(L$17:L$23)-L17)/(MAX(L$17:L$23)-MIN(L$17:L$23)) | T17: =(M17*'Fund Ranking Criteria'!$D$9)+('Fund Ranking_Equity'!N17*'Fund Ranking Criteria'!$D$10)+('Fund Ranking_Equity'!O17*'Fund Ranking Criteria'!$D$11)+('Fund Ranking_Equity'!P17*'Fund Ranking Criteria'!$D$16)+('Fund Ranking_Equity'!Q17*'Fund Ranking Criteria'!$D$12)+('Fund Ranking_Equity'!R17*'Fund Ranking Criteria'!$D$14)+('Fund Ranking_Equity'!S17*'Fund Ranking Criteria'!$D$15)
B18: Kotak Large & Midcap Fund - Reg - Growth | C18: =RANK(T18,$T$17:$T$23,0) | D18: =B18 | E18: 4.3694 | F18: 15.5595 | G18: 14.8181 | H18: 15.4403 | I18: 0.071487234 | J18: 0.093242012 | K18: 0.94584857 | L18: 13.45391 | M18: =(F18-MIN(F$17:F$23))/(MAX(F$17:F$23)-MIN(F$17:F$23)) | N18: =(G18-MIN(G$17:G$23))/(MAX(G$17:G$23)-MIN(G$17:G$23)) | O18: =(H18-MIN(H$17:H$23))/(MAX(H$17:H$23)-MIN(H$17:H$23)) | P18: =(I18-MIN(I$17:I$23))/(MAX(I$17:I$23)-MIN(I$17:I$23)) | Q18: =(J18-MIN(J$17:J$23))/(MAX(J$17:J$23)-MIN(J$17:J$23)) | R18: =(MAX(K$17:K$23)-K18)/(MAX(K$17:K$23)-MIN(K$17:K$23)) | S18: =(MAX(L$17:L$23)-L18)/(MAX(L$17:L$23)-MIN(L$17:L$23)) | T18: =(M18*'Fund Ranking Criteria'!$D$9)+('Fund Ranking_Equity'!N18*'Fund Ranking Criteria'!$D$10)+('Fund Ranking_Equity'!O18*'Fund Ranking Criteria'!$D$11)+('Fund Ranking_Equity'!P18*'Fund Ranking Criteria'!$D$16)+('Fund Ranking_Equity'!Q18*'Fund Ranking Criteria'!$D$12)+('Fund Ranking_Equity'!R18*'Fund Ranking Criteria'!$D$14)+('Fund Ranking_Equity'!S18*'Fund Ranking Criteria'!$D$15)
B19: HDFC Large and Mid Cap Fund - Growth | C19: =RANK(T19,$T$17:$T$23,0) | D19: =B19 | E19: 1.7108 | F19: 16.0245 | G19: 16.1077 | H19: 14.7294 | I19: 0.073292083 | J19: 0.07128643 | K19: 1.0220328 | L19: 13.777541 | M19: =(F19-MIN(F$17:F$23))/(MAX(F$17:F$23)-MIN(F$17:F$23)) | N19: =(G19-MIN(G$17:G$23))/(MAX(G$17:G$23)-MIN(G$17:G$23)) | O19: =(H19-MIN(H$17:H$23))/(MAX(H$17:H$23)-MIN(H$17:H$23)) | P19: =(I19-MIN(I$17:I$23))/(MAX(I$17:I$23)-MIN(I$17:I$23)) | Q19: =(J19-MIN(J$17:J$23))/(MAX(J$17:J$23)-MIN(J$17:J$23)) | R19: =(MAX(K$17:K$23)-K19)/(MAX(K$17:K$23)-MIN(K$17:K$23)) | S19: =(MAX(L$17:L$23)-L19)/(MAX(L$17:L$23)-MIN(L$17:L$23)) | T19: =(M19*'Fund Ranking Criteria'!$D$9)+('Fund Ranking_Equity'!N19*'Fund Ranking Criteria'!$D$10)+('Fund Ranking_Equity'!O19*'Fund Ranking Criteria'!$D$11)+('Fund Ranking_Equity'!P19*'Fund Ranking Criteria'!$D$16)+('Fund Ranking_Equity'!Q19*'Fund Ranking Criteria'!$D$12)+('Fund Ranking_Equity'!R19*'Fund Ranking Criteria'!$D$14)+('Fund Ranking_Equity'!S19*'Fund Ranking Criteria'!$D$15)
B20: ICICI Prudential Large & Mid Cap Fund - Growth | C20: =RANK(T20,$T$17:$T$23,0) | D20: =B20 | E20: 2.8165 | F20: 17.8307 | G20: 17.8535 | H20: 15.591 | I20: 0.088025083 | J20: 0.28500134 | K20: 0.84648897 | L20: 12.068192 | M20: =(F20-MIN(F$17:F$23))/(MAX(F$17:F$23)-MIN(F$17:F$23)) | N20: =(G20-MIN(G$17:G$23))/(MAX(G$17:G$23)-MIN(G$17:G$23)) | O20: =(H20-MIN(H$17:H$23))/(MAX(H$17:H$23)-MIN(H$17:H$23)) | P20: =(I20-MIN(I$17:I$23))/(MAX(I$17:I$23)-MIN(I$17:I$23)) | Q20: =(J20-MIN(J$17:J$23))/(MAX(J$17:J$23)-MIN(J$17:J$23)) | R20: =(MAX(K$17:K$23)-K20)/(MAX(K$17:K$23)-MIN(K$17:K$23)) | S20: =(MAX(L$17:L$23)-L20)/(MAX(L$17:L$23)-MIN(L$17:L$23)) | T20: =(M20*'Fund Ranking Criteria'!$D$9)+('Fund Ranking_Equity'!N20*'Fund Ranking Criteria'!$D$10)+('Fund Ranking_Equity'!O20*'Fund Ranking Criteria'!$D$11)+('Fund Ranking_Equity'!P20*'Fund Ranking Criteria'!$D$16)+('Fund Ranking_Equity'!Q20*'Fund Ranking Criteria'!$D$12)+('Fund Ranking_Equity'!R20*'Fund Ranking Criteria'!$D$14)+('Fund Ranking_Equity'!S20*'Fund Ranking Criteria'!$D$15)
B21: Nippon India Vision Large & Mid Cap Fund - Reg - Growth | C21: =RANK(T21,$T$17:$T$23,0) | D21: =B21 | E21: 3.9117 | F21: 17.5794 | G21: 15.7253 | H21: 13.2293 | I21: 0.081764803 | J21: 0.1987195 | K21: 0.97754042 | L21: 13.408726 | M21: =(F21-MIN(F$17:F$23))/(MAX(F$17:F$23)-MIN(F$17:F$23)) | N21: =(G21-MIN(G$17:G$23))/(MAX(G$17:G$23)-MIN(G$17:G$23)) | O21: =(H21-MIN(H$17:H$23))/(MAX(H$17:H$23)-MIN(H$17:H$23)) | P21: =(I21-MIN(I$17:I$23))/(MAX(I$17:I$23)-MIN(I$17:I$23)) | Q21: =(J21-MIN(J$17:J$23))/(MAX(J$17:J$23)-MIN(J$17:J$23)) | R21: =(MAX(K$17:K$23)-K21)/(MAX(K$17:K$23)-MIN(K$17:K$23)) | S21: =(MAX(L$17:L$23)-L21)/(MAX(L$17:L$23)-MIN(L$17:L$23)) | T21: =(M21*'Fund Ranking Criteria'!$D$9)+('Fund Ranking_Equity'!N21*'Fund Ranking Criteria'!$D$10)+('Fund Ranking_Equity'!O21*'Fund Ranking Criteria'!$D$11)+('Fund Ranking_Equity'!P21*'Fund Ranking Criteria'!$D$16)+('Fund Ranking_Equity'!Q21*'Fund Ranking Criteria'!$D$12)+('Fund Ranking_Equity'!R21*'Fund Ranking Criteria'!$D$14)+('Fund Ranking_Equity'!S21*'Fund Ranking Criteria'!$D$15)
B22: Aditya Birla Sun Life Large & Mid Cap Fund - Growth | C22: =RANK(T22,$T$17:$T$23,0) | D22: =B22 | E22: 3.9164 | F22: 12.7926 | G22: 9.4649 | H22: 11.8385 | I22: 0.054046338 | J22: -0.17747134 | K22: 1.0212671 | L22: 14.067997 | M22: =(F22-MIN(F$17:F$23))/(MAX(F$17:F$23)-MIN(F$17:F$23)) | N22: =(G22-MIN(G$17:G$23))/(MAX(G$17:G$23)-MIN(G$17:G$23)) | O22: =(H22-MIN(H$17:H$23))/(MAX(H$17:H$23)-MIN(H$17:H$23)) | P22: =(I22-MIN(I$17:I$23))/(MAX(I$17:I$23)-MIN(I$17:I$23)) | Q22: =(J22-MIN(J$17:J$23))/(MAX(J$17:J$23)-MIN(J$17:J$23)) | R22: =(MAX(K$17:K$23)-K22)/(MAX(K$17:K$23)-MIN(K$17:K$23)) | S22: =(MAX(L$17:L$23)-L22)/(MAX(L$17:L$23)-MIN(L$17:L$23)) | T22: =(M22*'Fund Ranking Criteria'!$D$9)+('Fund Ranking_Equity'!N22*'Fund Ranking Criteria'!$D$10)+('Fund Ranking_Equity'!O22*'Fund Ranking Criteria'!$D$11)+('Fund Ranking_Equity'!P22*'Fund Ranking Criteria'!$D$16)+('Fund Ranking_Equity'!Q22*'Fund Ranking Criteria'!$D$12)+('Fund Ranking_Equity'!R22*'Fund Ranking Criteria'!$D$14)+('Fund Ranking_Equity'!S22*'Fund Ranking Criteria'!$D$15)
B23: UTI Large & Mid Cap Fund - Growth | C23: =RANK(T23,$T$17:$T$23,0) | D23: =B23 | E23: 3.1799 | F23: 18.3076 | G23: 15.7241 | H23: 14.1577 | I23: 0.087478152 | J23: 0.2737974 | K23: 0.91924911 | L23: 12.779337 | M23: =(F23-MIN(F$17:F$23))/(MAX(F$17:F$23)-MIN(F$17:F$23)) | N23: =(G23-MIN(G$17:G$23))/(MAX(G$17:G$23)-MIN(G$17:G$23)) | O23: =(H23-MIN(H$17:H$23))/(MAX(H$17:H$23)-MIN(H$17:H$23)) | P23: =(I23-MIN(I$17:I$23))/(MAX(I$17:I$23)-MIN(I$17:I$23)) | Q23: =(J23-MIN(J$17:J$23))/(MAX(J$17:J$23)-MIN(J$17:J$23)) | R23: =(MAX(K$17:K$23)-K23)/(MAX(K$17:K$23)-MIN(K$17:K$23)) | S23: =(MAX(L$17:L$23)-L23)/(MAX(L$17:L$23)-MIN(L$17:L$23)) | T23: =(M23*'Fund Ranking Criteria'!$D$9)+('Fund Ranking_Equity'!N23*'Fund Ranking Criteria'!$D$10)+('Fund Ranking_Equity'!O23*'Fund Ranking Criteria'!$D$11)+('Fund Ranking_Equity'!P23*'Fund Ranking Criteria'!$D$16)+('Fund Ranking_Equity'!Q23*'Fund Ranking Criteria'!$D$12)+('Fund Ranking_Equity'!R23*'Fund Ranking Criteria'!$D$14)+('Fund Ranking_Equity'!S23*'Fund Ranking Criteria'!$D$15)
B25: Equity Mid Cap
E26: Actuals | M26: Normalized
B27: Funds | C27: Rank | E27: 1 Yr Ret (%) | F27: 3 Yr Ret (%) | G27: 5 Yr Ret (%) | H27: 10 Yr Ret (%) | I27: Sharpe | J27: Alpha | K27: Beta | L27: SD | M27: =F27 | N27: =G27 | O27: =H27 | P27: Sharpe | Q27: Alpha | R27: Beta | S27: SD
B28: HDFC Mid Cap Fund - Growth | C28: =RANK(T28,$T$28:$T$34,0) | D28: =B28 | E28: 6.7685 | F28: 20.2216 | G28: 20.2516 | H28: 17.9558 | I28: 0.095249973 | J28: 0.24203524 | K28: 0.8971852 | L28: 14.679632 | M28: =(F28-MIN(F$28:F$34))/(MAX(F$28:F$34)-MIN(F$28:F$34)) | N28: =(G28-MIN(G$28:G$34))/(MAX(G$28:G$34)-MIN(G$28:G$34)) | O28: =(H28-MIN(H$28:H$34))/(MAX(H$28:H$34)-MIN(H$28:H$34)) | P28: =(I28-MIN(I$28:I$34))/(MAX(I$28:I$34)-MIN(I$28:I$34)) | Q28: =(J28-MIN(J$28:J$34))/(MAX(J$28:J$34)-MIN(J$28:J$34)) | R28: =(MAX(K$28:K$34)-K28)/(MAX(K$28:K$34)-MIN(K$28:K$34)) | S28: =(MAX(L$28:L$34)-L28)/(MAX(L$28:L$34)-MIN(L$28:L$34)) | T28: =(M28*'Fund Ranking Criteria'!$F$9)+('Fund Ranking_Equity'!N28*'Fund Ranking Criteria'!$F$10)+('Fund Ranking_Equity'!O28*'Fund Ranking Criteria'!$F$11)+('Fund Ranking_Equity'!P28*'Fund Ranking Criteria'!$F$16)+('Fund Ranking_Equity'!Q28*'Fund Ranking Criteria'!$F$12)+('Fund Ranking_Equity'!R28*'Fund Ranking Criteria'!$F$14)+('Fund Ranking_Equity'!S28*'Fund Ranking Criteria'!$F$15)
B29: Kotak Midcap Fund - Reg - Growth | C29: =RANK(T29,$T$28:$T$34,0) | D29: =B29 | E29: 8.7559 | F29: 19.9967 | G29: 17.8926 | H29: 17.6831 | I29: 0.08577326 | J29: 0.18078249 | K29: 0.88745739 | L29: 15.441242 | M29: =(F29-MIN(F$28:F$34))/(MAX(F$28:F$34)-MIN(F$28:F$34)) | N29: =(G29-MIN(G$28:G$34))/(MAX(G$28:G$34)-MIN(G$28:G$34)) | O29: =(H29-MIN(H$28:H$34))/(MAX(H$28:H$34)-MIN(H$28:H$34)) | P29: =(I29-MIN(I$28:I$34))/(MAX(I$28:I$34)-MIN(I$28:I$34)) | Q29: =(J29-MIN(J$28:J$34))/(MAX(J$28:J$34)-MIN(J$28:J$34)) | R29: =(MAX(K$28:K$34)-K29)/(MAX(K$28:K$34)-MIN(K$28:K$34)) | S29: =(MAX(L$28:L$34)-L29)/(MAX(L$28:L$34)-MIN(L$28:L$34)) | T29: =(M29*'Fund Ranking Criteria'!$F$9)+('Fund Ranking_Equity'!N29*'Fund Ranking Criteria'!$F$10)+('Fund Ranking_Equity'!O29*'Fund Ranking Criteria'!$F$11)+('Fund Ranking_Equity'!P29*'Fund Ranking Criteria'!$F$16)+('Fund Ranking_Equity'!Q29*'Fund Ranking Criteria'!$F$12)+('Fund Ranking_Equity'!R29*'Fund Ranking Criteria'!$F$14)+('Fund Ranking_Equity'!S29*'Fund Ranking Criteria'!$F$15)
B30: Nippon India Growth Mid Cap Fund - Reg - Growth | C30: =RANK(T30,$T$28:$T$34,0) | D30: =B30 | E30: 9.7726 | F30: 22.7395 | G30: 21.0592 | H30: 18.8102 | I30: 0.095504452 | J30: 0.28478388 | K30: 0.96977353 | L30: 16.067602 | M30: =(F30-MIN(F$28:F$34))/(MAX(F$28:F$34)-MIN(F$28:F$34)) | N30: =(G30-MIN(G$28:G$34))/(MAX(G$28:G$34)-MIN(G$28:G$34)) | O30: =(H30-MIN(H$28:H$34))/(MAX(H$28:H$34)-MIN(H$28:H$34)) | P30: =(I30-MIN(I$28:I$34))/(MAX(I$28:I$34)-MIN(I$28:I$34)) | Q30: =(J30-MIN(J$28:J$34))/(MAX(J$28:J$34)-MIN(J$28:J$34)) | R30: =(MAX(K$28:K$34)-K30)/(MAX(K$28:K$34)-MIN(K$28:K$34)) | S30: =(MAX(L$28:L$34)-L30)/(MAX(L$28:L$34)-MIN(L$28:L$34)) | T30: =(M30*'Fund Ranking Criteria'!$F$9)+('Fund Ranking_Equity'!N30*'Fund Ranking Criteria'!$F$10)+('Fund Ranking_Equity'!O30*'Fund Ranking Criteria'!$F$11)+('Fund Ranking_Equity'!P30*'Fund Ranking Criteria'!$F$16)+('Fund Ranking_Equity'!Q30*'Fund Ranking Criteria'!$F$12)+('Fund Ranking_Equity'!R30*'Fund Ranking Criteria'!$F$14)+('Fund Ranking_Equity'!S30*'Fund Ranking Criteria'!$F$15)
B31: SBI Midcap Fund - Growth | C31: =RANK(T31,$T$28:$T$34,0) | D31: =B31 | E31: 2.4159 | F31: 12.5367 | G31: 15.346 | H31: 14.0855 | I31: 0.057280038 | J31: -0.2675327 | K31: 0.8300446 | L31: 14.00388 | M31: =(F31-MIN(F$28:F$34))/(MAX(F$28:F$34)-MIN(F$28:F$34)) | N31: =(G31-MIN(G$28:G$34))/(MAX(G$28:G$34)-MIN(G$28:G$34)) | O31: =(H31-MIN(H$28:H$34))/(MAX(H$28:H$34)-MIN(H$28:H$34)) | P31: =(I31-MIN(I$28:I$34))/(MAX(I$28:I$34)-MIN(I$28:I$34)) | Q31: =(J31-MIN(J$28:J$34))/(MAX(J$28:J$34)-MIN(J$28:J$34)) | R31: =(MAX(K$28:K$34)-K31)/(MAX(K$28:K$34)-MIN(K$28:K$34)) | S31: =(MAX(L$28:L$34)-L31)/(MAX(L$28:L$34)-MIN(L$28:L$34)) | T31: =(M31*'Fund Ranking Criteria'!$F$9)+('Fund Ranking_Equity'!N31*'Fund Ranking Criteria'!$F$10)+('Fund Ranking_Equity'!O31*'Fund Ranking Criteria'!$F$11)+('Fund Ranking_Equity'!P31*'Fund Ranking Criteria'!$F$16)+('Fund Ranking_Equity'!Q31*'Fund Ranking Criteria'!$F$12)+('Fund Ranking_Equity'!R31*'Fund Ranking Criteria'!$F$14)+('Fund Ranking_Equity'!S31*'Fund Ranking Criteria'!$F$15)
B32: UTI Mid Cap Fund - Growth | C32: =RANK(T32,$T$28:$T$34,0) | D32: =B32 | E32: 2.2864 | F32: 14.1966 | G32: 13.795 | H32: 14.1916 | I32: 0.060533343 | J32: -0.2735268 | K32: 0.93376788 | L32: 15.360402 | M32: =(F32-MIN(F$28:F$34))/(MAX(F$28:F$34)-MIN(F$28:F$34)) | N32: =(G32-MIN(G$28:G$34))/(MAX(G$28:G$34)-MIN(G$28:G$34)) | O32: =(H32-MIN(H$28:H$34))/(MAX(H$28:H$34)-MIN(H$28:H$34)) | P32: =(I32-MIN(I$28:I$34))/(MAX(I$28:I$34)-MIN(I$28:I$34)) | Q32: =(J32-MIN(J$28:J$34))/(MAX(J$28:J$34)-MIN(J$28:J$34)) | R32: =(MAX(K$28:K$34)-K32)/(MAX(K$28:K$34)-MIN(K$28:K$34)) | S32: =(MAX(L$28:L$34)-L32)/(MAX(L$28:L$34)-MIN(L$28:L$34)) | T32: =(M32*'Fund Ranking Criteria'!$F$9)+('Fund Ranking_Equity'!N32*'Fund Ranking Criteria'!$F$10)+('Fund Ranking_Equity'!O32*'Fund Ranking Criteria'!$F$11)+('Fund Ranking_Equity'!P32*'Fund Ranking Criteria'!$F$16)+('Fund Ranking_Equity'!Q32*'Fund Ranking Criteria'!$F$12)+('Fund Ranking_Equity'!R32*'Fund Ranking Criteria'!$F$14)+('Fund Ranking_Equity'!S32*'Fund Ranking Criteria'!$F$15)
B33: ICICI Prudential MidCap Fund - Growth | C33: =RANK(T33,$T$28:$T$34,0) | D33: =B33 | E33: 15.9774 | F33: 24.4417 | G33: 19.169 | H33: 17.3693 | I33: 0.10143763 | J33: 0.39376631 | K33: 0.96213032 | L33: 16.10507 | M33: =(F33-MIN(F$28:F$34))/(MAX(F$28:F$34)-MIN(F$28:F$34)) | N33: =(G33-MIN(G$28:G$34))/(MAX(G$28:G$34)-MIN(G$28:G$34)) | O33: =(H33-MIN(H$28:H$34))/(MAX(H$28:H$34)-MIN(H$28:H$34)) | P33: =(I33-MIN(I$28:I$34))/(MAX(I$28:I$34)-MIN(I$28:I$34)) | Q33: =(J33-MIN(J$28:J$34))/(MAX(J$28:J$34)-MIN(J$28:J$34)) | R33: =(MAX(K$28:K$34)-K33)/(MAX(K$28:K$34)-MIN(K$28:K$34)) | S33: =(MAX(L$28:L$34)-L33)/(MAX(L$28:L$34)-MIN(L$28:L$34)) | T33: =(M33*'Fund Ranking Criteria'!$F$9)+('Fund Ranking_Equity'!N33*'Fund Ranking Criteria'!$F$10)+('Fund Ranking_Equity'!O33*'Fund Ranking Criteria'!$F$11)+('Fund Ranking_Equity'!P33*'Fund Ranking Criteria'!$F$16)+('Fund Ranking_Equity'!Q33*'Fund Ranking Criteria'!$F$12)+('Fund Ranking_Equity'!R33*'Fund Ranking Criteria'!$F$14)+('Fund Ranking_Equity'!S33*'Fund Ranking Criteria'!$F$15)
B34: Aditya Birla Sun Life Mid Cap Fund - Plan A - Growth | C34: =RANK(T34,$T$28:$T$34,0) | D34: =B34 | E34: 6.1269 | F34: 18.2307 | G34: 16.2812 | H34: 14.0915 | I34: 0.075474294 | J34: -0.048694459 | K34: 0.9718557 | L34: 15.948907 | M34: =(F34-MIN(F$28:F$34))/(MAX(F$28:F$34)-MIN(F$28:F$34)) | N34: =(G34-MIN(G$28:G$34))/(MAX(G$28:G$34)-MIN(G$28:G$34)) | O34: =(H34-MIN(H$28:H$34))/(MAX(H$28:H$34)-MIN(H$28:H$34)) | P34: =(I34-MIN(I$28:I$34))/(MAX(I$28:I$34)-MIN(I$28:I$34)) | Q34: =(J34-MIN(J$28:J$34))/(MAX(J$28:J$34)-MIN(J$28:J$34)) | R34: =(MAX(K$28:K$34)-K34)/(MAX(K$28:K$34)-MIN(K$28:K$34)) | S34: =(MAX(L$28:L$34)-L34)/(MAX(L$28:L$34)-MIN(L$28:L$34)) | T34: =(M34*'Fund Ranking Criteria'!$F$9)+('Fund Ranking_Equity'!N34*'Fund Ranking Criteria'!$F$10)+('Fund Ranking_Equity'!O34*'Fund Ranking Criteria'!$F$11)+('Fund Ranking_Equity'!P34*'Fund Ranking Criteria'!$F$16)+('Fund Ranking_Equity'!Q34*'Fund Ranking Criteria'!$F$12)+('Fund Ranking_Equity'!R34*'Fund Ranking Criteria'!$F$14)+('Fund Ranking_Equity'!S34*'Fund Ranking Criteria'!$F$15)
B36: Equity Small Cap
E37: Actuals | M37: Normalized
B38: Funds | C38: Rank | E38: 1 Yr Ret (%) | F38: 3 Yr Ret (%) | G38: 5 Yr Ret (%) | H38: 10 Yr Ret (%) | I38: Sharpe | J38: Alpha | K38: Beta | L38: SD | M38: =F38 | N38: =G38 | O38: =H38 | P38: Sharpe | Q38: Alpha | R38: Beta | S38: SD
B39: Nippon India Small Cap Fund - Reg - Growth | C39: =RANK(T39,$T$39:$T$45,0) | D39: =B39 | E39: 6.8382 | F39: 18.644 | G39: 20.7852 | H39: 21.027 | I39: 0.072041199 | J39: 0.16912469 | K39: 0.8506729 | L39: 17.78838 | M39: =(F39-MIN(F$39:F$45))/(MAX(F$39:F$45)-MIN(F$39:F$45)) | N39: =(G39-MIN(G$39:G$45))/(MAX(G$39:G$45)-MIN(G$39:G$45)) | O39: =(H39-MIN(H$39:H$45))/(MAX(H$39:H$45)-MIN(H$39:H$45)) | P39: =(I39-MIN(I$39:I$45))/(MAX(I$39:I$45)-MIN(I$39:I$45)) | Q39: =(J39-MIN(J$39:J$45))/(MAX(J$39:J$45)-MIN(J$39:J$45)) | R39: =(MAX(K$39:K$45)-K39)/(MAX(K$39:K$45)-MIN(K$39:K$45)) | S39: =(MAX(L$39:L$45)-L39)/(MAX(L$39:L$45)-MIN(L$39:L$45)) | T39: =(M39*'Fund Ranking Criteria'!$G$9)+('Fund Ranking_Equity'!N39*'Fund Ranking Criteria'!$G$10)+('Fund Ranking_Equity'!O39*'Fund Ranking Criteria'!$G$11)+('Fund Ranking_Equity'!P39*'Fund Ranking Criteria'!$G$16)+('Fund Ranking_Equity'!Q39*'Fund Ranking Criteria'!$G$12)+('Fund Ranking_Equity'!R39*'Fund Ranking Criteria'!$G$14)+('Fund Ranking_Equity'!S39*'Fund Ranking Criteria'!$G$15)
B40: HDFC Small Cap Fund - Growth | C40: =RANK(T40,$T$39:$T$45,0) | D40: =B40 | E40: 0.3458 | F40: 13.8735 | G40: 16.5378 | H40: 17.511 | I40: 0.055060324 | J40: -0.048567351 | K40: 0.8055795 | L40: 16.380372 | M40: =(F40-MIN(F$39:F$45))/(MAX(F$39:F$45)-MIN(F$39:F$45)) | N40: =(G40-MIN(G$39:G$45))/(MAX(G$39:G$45)-MIN(G$39:G$45)) | O40: =(H40-MIN(H$39:H$45))/(MAX(H$39:H$45)-MIN(H$39:H$45)) | P40: =(I40-MIN(I$39:I$45))/(MAX(I$39:I$45)-MIN(I$39:I$45)) | Q40: =(J40-MIN(J$39:J$45))/(MAX(J$39:J$45)-MIN(J$39:J$45)) | R40: =(MAX(K$39:K$45)-K40)/(MAX(K$39:K$45)-MIN(K$39:K$45)) | S40: =(MAX(L$39:L$45)-L40)/(MAX(L$39:L$45)-MIN(L$39:L$45)) | T40: =(M40*'Fund Ranking Criteria'!$G$9)+('Fund Ranking_Equity'!N40*'Fund Ranking Criteria'!$G$10)+('Fund Ranking_Equity'!O40*'Fund Ranking Criteria'!$G$11)+('Fund Ranking_Equity'!P40*'Fund Ranking Criteria'!$G$16)+('Fund Ranking_Equity'!Q40*'Fund Ranking Criteria'!$G$12)+('Fund Ranking_Equity'!R40*'Fund Ranking Criteria'!$G$14)+('Fund Ranking_Equity'!S40*'Fund Ranking Criteria'!$G$15)
B41: SBI Small Cap Fund - Growth | C41: =RANK(T41,$T$39:$T$45,0) | D41: =B41 | E41: 2.3501 | F41: 12.5053 | G41: 14.2385 | H41: 18.0403 | I41: 0.045796957 | J41: -0.19013885 | K41: 0.79694095 | L41: 16.379795 | M41: =(F41-MIN(F$39:F$45))/(MAX(F$39:F$45)-MIN(F$39:F$45)) | N41: =(G41-MIN(G$39:G$45))/(MAX(G$39:G$45)-MIN(G$39:G$45)) | O41: =(H41-MIN(H$39:H$45))/(MAX(H$39:H$45)-MIN(H$39:H$45)) | P41: =(I41-MIN(I$39:I$45))/(MAX(I$39:I$45)-MIN(I$39:I$45)) | Q41: =(J41-MIN(J$39:J$45))/(MAX(J$39:J$45)-MIN(J$39:J$45)) | R41: =(MAX(K$39:K$45)-K41)/(MAX(K$39:K$45)-MIN(K$39:K$45)) | S41: =(MAX(L$39:L$45)-L41)/(MAX(L$39:L$45)-MIN(L$39:L$45)) | T41: =(M41*'Fund Ranking Criteria'!$G$9)+('Fund Ranking_Equity'!N41*'Fund Ranking Criteria'!$G$10)+('Fund Ranking_Equity'!O41*'Fund Ranking Criteria'!$G$11)+('Fund Ranking_Equity'!P41*'Fund Ranking Criteria'!$G$16)+('Fund Ranking_Equity'!Q41*'Fund Ranking Criteria'!$G$12)+('Fund Ranking_Equity'!R41*'Fund Ranking Criteria'!$G$14)+('Fund Ranking_Equity'!S41*'Fund Ranking Criteria'!$G$15)
B42: Kotak Small Cap Fund - Reg - Growth | C42: =RANK(T42,$T$39:$T$45,0) | D42: =B42 | E42: 0.5998 | F42: 13.0357 | G42: 13.7509 | H42: 16.7386 | I42: 0.050280804 | J42: -0.18611576 | K42: 0.79578053 | L42: 16.994089 | M42: =(F42-MIN(F$39:F$45))/(MAX(F$39:F$45)-MIN(F$39:F$45)) | N42: =(G42-MIN(G$39:G$45))/(MAX(G$39:G$45)-MIN(G$39:G$45)) | O42: =(H42-MIN(H$39:H$45))/(MAX(H$39:H$45)-MIN(H$39:H$45)) | P42: =(I42-MIN(I$39:I$45))/(MAX(I$39:I$45)-MIN(I$39:I$45)) | Q42: =(J42-MIN(J$39:J$45))/(MAX(J$39:J$45)-MIN(J$39:J$45)) | R42: =(MAX(K$39:K$45)-K42)/(MAX(K$39:K$45)-MIN(K$39:K$45)) | S42: =(MAX(L$39:L$45)-L42)/(MAX(L$39:L$45)-MIN(L$39:L$45)) | T42: =(M42*'Fund Ranking Criteria'!$G$9)+('Fund Ranking_Equity'!N42*'Fund Ranking Criteria'!$G$10)+('Fund Ranking_Equity'!O42*'Fund Ranking Criteria'!$G$11)+('Fund Ranking_Equity'!P42*'Fund Ranking Criteria'!$G$16)+('Fund Ranking_Equity'!Q42*'Fund Ranking Criteria'!$G$12)+('Fund Ranking_Equity'!R42*'Fund Ranking Criteria'!$G$14)+('Fund Ranking_Equity'!S42*'Fund Ranking Criteria'!$G$15)
B43: ICICI Prudential Smallcap Fund - Growth | C43: =RANK(T43,$T$39:$T$45,0) | D43: =B43 | E43: 3.1188 | F43: 13.2993 | G43: 15.7487 | H43: 16.2191 | I43: 0.055567053 | J43: -0.098572945 | K43: 0.74854952 | L43: 15.84137 | M43: =(F43-MIN(F$39:F$45))/(MAX(F$39:F$45)-MIN(F$39:F$45)) | N43: =(G43-MIN(G$39:G$45))/(MAX(G$39:G$45)-MIN(G$39:G$45)) | O43: =(H43-MIN(H$39:H$45))/(MAX(H$39:H$45)-MIN(H$39:H$45)) | P43: =(I43-MIN(I$39:I$45))/(MAX(I$39:I$45)-MIN(I$39:I$45)) | Q43: =(J43-MIN(J$39:J$45))/(MAX(J$39:J$45)-MIN(J$39:J$45)) | R43: =(MAX(K$39:K$45)-K43)/(MAX(K$39:K$45)-MIN(K$39:K$45)) | S43: =(MAX(L$39:L$45)-L43)/(MAX(L$39:L$45)-MIN(L$39:L$45)) | T43: =(M43*'Fund Ranking Criteria'!$G$9)+('Fund Ranking_Equity'!N43*'Fund Ranking Criteria'!$G$10)+('Fund Ranking_Equity'!O43*'Fund Ranking Criteria'!$G$11)+('Fund Ranking_Equity'!P43*'Fund Ranking Criteria'!$G$16)+('Fund Ranking_Equity'!Q43*'Fund Ranking Criteria'!$G$12)+('Fund Ranking_Equity'!R43*'Fund Ranking Criteria'!$G$14)+('Fund Ranking_Equity'!S43*'Fund Ranking Criteria'!$G$15)
B44: Aditya Birla Sun Life Small Cap Fund - Growth | C44: =RANK(T44,$T$39:$T$45,0) | D44: =B44 | E44: 10.0516 | F44: 16.9852 | G44: 14.0657 | H44: 13.1867 | I44: 0.061871412 | J44: 0.080521811 | K44: 0.89950365 | L44: 18.454657 | M44: =(F44-MIN(F$39:F$45))/(MAX(F$39:F$45)-MIN(F$39:F$45)) | N44: =(G44-MIN(G$39:G$45))/(MAX(G$39:G$45)-MIN(G$39:G$45)) | O44: =(H44-MIN(H$39:H$45))/(MAX(H$39:H$45)-MIN(H$39:H$45)) | P44: =(I44-MIN(I$39:I$45))/(MAX(I$39:I$45)-MIN(I$39:I$45)) | Q44: =(J44-MIN(J$39:J$45))/(MAX(J$39:J$45)-MIN(J$39:J$45)) | R44: =(MAX(K$39:K$45)-K44)/(MAX(K$39:K$45)-MIN(K$39:K$45)) | S44: =(MAX(L$39:L$45)-L44)/(MAX(L$39:L$45)-MIN(L$39:L$45)) | T44: =(M44*'Fund Ranking Criteria'!$G$9)+('Fund Ranking_Equity'!N44*'Fund Ranking Criteria'!$G$10)+('Fund Ranking_Equity'!O44*'Fund Ranking Criteria'!$G$11)+('Fund Ranking_Equity'!P44*'Fund Ranking Criteria'!$G$16)+('Fund Ranking_Equity'!Q44*'Fund Ranking Criteria'!$G$12)+('Fund Ranking_Equity'!R44*'Fund Ranking Criteria'!$G$14)+('Fund Ranking_Equity'!S44*'Fund Ranking Criteria'!$G$15)
B45: UTI Small Cap Fund - Reg - Growth | C45: =RANK(T45,$T$39:$T$45,0) | D45: =B45 | E45: 3.5378 | F45: 15.861 | G45: 16.1383 | H45: 0 | I45: 0.060530759 | J45: -0.03481154 | K45: 0.84300184 | L45: 17.636141 | M45: =(F45-MIN(F$39:F$45))/(MAX(F$39:F$45)-MIN(F$39:F$45)) | N45: =(G45-MIN(G$39:G$45))/(MAX(G$39:G$45)-MIN(G$39:G$45)) | O45: =(H45-MIN(H$39:H$45))/(MAX(H$39:H$45)-MIN(H$39:H$45)) | P45: =(I45-MIN(I$39:I$45))/(MAX(I$39:I$45)-MIN(I$39:I$45)) | Q45: =(J45-MIN(J$39:J$45))/(MAX(J$39:J$45)-MIN(J$39:J$45)) | R45: =(MAX(K$39:K$45)-K45)/(MAX(K$39:K$45)-MIN(K$39:K$45)) | S45: =(MAX(L$39:L$45)-L45)/(MAX(L$39:L$45)-MIN(L$39:L$45)) | T45: =(M45*'Fund Ranking Criteria'!$G$9)+('Fund Ranking_Equity'!N45*'Fund Ranking Criteria'!$G$10)+('Fund Ranking_Equity'!O45*'Fund Ranking Criteria'!$G$11)+('Fund Ranking_Equity'!P45*'Fund Ranking Criteria'!$G$16)+('Fund Ranking_Equity'!Q45*'Fund Ranking Criteria'!$G$12)+('Fund Ranking_Equity'!R45*'Fund Ranking Criteria'!$G$14)+('Fund Ranking_Equity'!S45*'Fund Ranking Criteria'!$G$15)
B47: Equity Focused Fund
E48: Actuals | M48: Normalized
B49: Funds | C49: Rank | E49: 1 Yr Ret (%) | F49: 3 Yr Ret (%) | G49: 5 Yr Ret (%) | H49: 10 Yr Ret (%) | I49: Sharpe | J49: Alpha | K49: Beta | L49: SD | M49: =F49 | N49: =G49 | O49: =H49 | P49: Sharpe | Q49: Alpha | R49: Beta | S49: SD
B50: SBI Focused Fund - Growth | C50: =RANK(T50,$T$50:$T$56,0) | D50: =B50 | E50: 10.629 | F50: 16.2664 | G50: 12.9653 | H50: 14.8535 | I50: 0.099581379 | J50: 0.508848 | K50: 0.64071027 | L50: 9.1967873 | M50: =(F50-MIN(F$50:F$56))/(MAX(F$50:F$56)-MIN(F$50:F$56)) | N50: =(G50-MIN(G$50:G$56))/(MAX(G$50:G$56)-MIN(G$50:G$56)) | O50: =(H50-MIN(H$50:H$56))/(MAX(H$50:H$56)-MIN(H$50:H$56)) | P50: =(I50-MIN(I$50:I$56))/(MAX(I$50:I$56)-MIN(I$50:I$56)) | Q50: =(J50-MIN(J$50:J$56))/(MAX(J$50:J$56)-MIN(J$50:J$56)) | R50: =(MAX(K$50:K$56)-K50)/(MAX(K$50:K$56)-MIN(K$50:K$56)) | S50: =(MAX(L$50:L$56)-L50)/(MAX(L$50:L$56)-MIN(L$50:L$56)) | T50: =(M50*'Fund Ranking Criteria'!$E$9)+('Fund Ranking_Equity'!N50*'Fund Ranking Criteria'!$E$10)+('Fund Ranking_Equity'!O50*'Fund Ranking Criteria'!$E$11)+('Fund Ranking_Equity'!P50*'Fund Ranking Criteria'!$E$16)+('Fund Ranking_Equity'!Q50*'Fund Ranking Criteria'!$E$12)+('Fund Ranking_Equity'!R50*'Fund Ranking Criteria'!$E$14)+('Fund Ranking_Equity'!S50*'Fund Ranking Criteria'!$E$15)
B51: HDFC Focused Fund - Growth | C51: =RANK(T51,$T$50:$T$56,0) | D51: =B51 | E51: 1.0817 | F51: 16.725 | G51: 18.8966 | H51: 14.1675 | I51: 0.086321788 | J51: 0.3844446 | K51: 0.83239365 | L51: 11.513751 | M51: =(F51-MIN(F$50:F$56))/(MAX(F$50:F$56)-MIN(F$50:F$56)) | N51: =(G51-MIN(G$50:G$56))/(MAX(G$50:G$56)-MIN(G$50:G$56)) | O51: =(H51-MIN(H$50:H$56))/(MAX(H$50:H$56)-MIN(H$50:H$56)) | P51: =(I51-MIN(I$50:I$56))/(MAX(I$50:I$56)-MIN(I$50:I$56)) | Q51: =(J51-MIN(J$50:J$56))/(MAX(J$50:J$56)-MIN(J$50:J$56)) | R51: =(MAX(K$50:K$56)-K51)/(MAX(K$50:K$56)-MIN(K$50:K$56)) | S51: =(MAX(L$50:L$56)-L51)/(MAX(L$50:L$56)-MIN(L$50:L$56)) | T51: =(M51*'Fund Ranking Criteria'!$E$9)+('Fund Ranking_Equity'!N51*'Fund Ranking Criteria'!$E$10)+('Fund Ranking_Equity'!O51*'Fund Ranking Criteria'!$E$11)+('Fund Ranking_Equity'!P51*'Fund Ranking Criteria'!$E$16)+('Fund Ranking_Equity'!Q51*'Fund Ranking Criteria'!$E$12)+('Fund Ranking_Equity'!R51*'Fund Ranking Criteria'!$E$14)+('Fund Ranking_Equity'!S51*'Fund Ranking Criteria'!$E$15)
B52: Axis Focused Fund - Growth | C52: =RANK(T52,$T$50:$T$56,0) | D52: =B52 | E52: -2.1109 | F52: 8.1432 | G52: 5.4014 | H52: 11.4322 | I52: 0.0344157 | J52: -0.24371034 | K52: 0.96649298 | L52: 13.479733 | M52: =(F52-MIN(F$50:F$56))/(MAX(F$50:F$56)-MIN(F$50:F$56)) | N52: =(G52-MIN(G$50:G$56))/(MAX(G$50:G$56)-MIN(G$50:G$56)) | O52: =(H52-MIN(H$50:H$56))/(MAX(H$50:H$56)-MIN(H$50:H$56)) | P52: =(I52-MIN(I$50:I$56))/(MAX(I$50:I$56)-MIN(I$50:I$56)) | Q52: =(J52-MIN(J$50:J$56))/(MAX(J$50:J$56)-MIN(J$50:J$56)) | R52: =(MAX(K$50:K$56)-K52)/(MAX(K$50:K$56)-MIN(K$50:K$56)) | S52: =(MAX(L$50:L$56)-L52)/(MAX(L$50:L$56)-MIN(L$50:L$56)) | T52: =(M52*'Fund Ranking Criteria'!$E$9)+('Fund Ranking_Equity'!N52*'Fund Ranking Criteria'!$E$10)+('Fund Ranking_Equity'!O52*'Fund Ranking Criteria'!$E$11)+('Fund Ranking_Equity'!P52*'Fund Ranking Criteria'!$E$16)+('Fund Ranking_Equity'!Q52*'Fund Ranking Criteria'!$E$12)+('Fund Ranking_Equity'!R52*'Fund Ranking Criteria'!$E$14)+('Fund Ranking_Equity'!S52*'Fund Ranking Criteria'!$E$15)
B53: ICICI Prudential Focused Equity Fund - Ret - Growth | C53: =RANK(T53,$T$50:$T$56,0) | D53: =B53 | E53: 6.9878 | F53: 25.7403 | G53: 25.3462 | H53: 14.723 | I53: 0.12267997 | J53: 0.46840512 | K53: 0.92061035 | L53: 13.520135 | M53: =(F53-MIN(F$50:F$56))/(MAX(F$50:F$56)-MIN(F$50:F$56)) | N53: =(G53-MIN(G$50:G$56))/(MAX(G$50:G$56)-MIN(G$50:G$56)) | O53: =(H53-MIN(H$50:H$56))/(MAX(H$50:H$56)-MIN(H$50:H$56)) | P53: =(I53-MIN(I$50:I$56))/(MAX(I$50:I$56)-MIN(I$50:I$56)) | Q53: =(J53-MIN(J$50:J$56))/(MAX(J$50:J$56)-MIN(J$50:J$56)) | R53: =(MAX(K$50:K$56)-K53)/(MAX(K$50:K$56)-MIN(K$50:K$56)) | S53: =(MAX(L$50:L$56)-L53)/(MAX(L$50:L$56)-MIN(L$50:L$56)) | T53: =(M53*'Fund Ranking Criteria'!$E$9)+('Fund Ranking_Equity'!N53*'Fund Ranking Criteria'!$E$10)+('Fund Ranking_Equity'!O53*'Fund Ranking Criteria'!$E$11)+('Fund Ranking_Equity'!P53*'Fund Ranking Criteria'!$E$16)+('Fund Ranking_Equity'!Q53*'Fund Ranking Criteria'!$E$12)+('Fund Ranking_Equity'!R53*'Fund Ranking Criteria'!$E$14)+('Fund Ranking_Equity'!S53*'Fund Ranking Criteria'!$E$15)
B54: Nippon India Focused Fund - Reg - Growth | C54: =RANK(T54,$T$50:$T$56,0) | D54: =B54 | E54: 2.5554 | F54: 12.8529 | G54: 12.45 | H54: 13.6535 | I54: 0.056091597 | J54: 0.057070461 | K54: 0.96712022 | L54: 13.098378 | M54: =(F54-MIN(F$50:F$56))/(MAX(F$50:F$56)-MIN(F$50:F$56)) | N54: =(G54-MIN(G$50:G$56))/(MAX(G$50:G$56)-MIN(G$50:G$56)) | O54: =(H54-MIN(H$50:H$56))/(MAX(H$50:H$56)-MIN(H$50:H$56)) | P54: =(I54-MIN(I$50:I$56))/(MAX(I$50:I$56)-MIN(I$50:I$56)) | Q54: =(J54-MIN(J$50:J$56))/(MAX(J$50:J$56)-MIN(J$50:J$56)) | R54: =(MAX(K$50:K$56)-K54)/(MAX(K$50:K$56)-MIN(K$50:K$56)) | S54: =(MAX(L$50:L$56)-L54)/(MAX(L$50:L$56)-MIN(L$50:L$56)) | T54: =(M54*'Fund Ranking Criteria'!$E$9)+('Fund Ranking_Equity'!N54*'Fund Ranking Criteria'!$E$10)+('Fund Ranking_Equity'!O54*'Fund Ranking Criteria'!$E$11)+('Fund Ranking_Equity'!P54*'Fund Ranking Criteria'!$E$16)+('Fund Ranking_Equity'!Q54*'Fund Ranking Criteria'!$E$12)+('Fund Ranking_Equity'!R54*'Fund Ranking Criteria'!$E$14)+('Fund Ranking_Equity'!S54*'Fund Ranking Criteria'!$E$15)
B55: Kotak Focused Fund - Reg - Growth | C55: =RANK(T55,$T$50:$T$56,0) | D55: =B55 | E55: 9.177 | F55: 15.5158 | G55: 13.1586 | H55: 0 | I55: 0.074525015 | J55: 0.24246966 | K55: 0.91833746 | L55: 12.27557 | M55: =(F55-MIN(F$50:F$56))/(MAX(F$50:F$56)-MIN(F$50:F$56)) | N55: =(G55-MIN(G$50:G$56))/(MAX(G$50:G$56)-MIN(G$50:G$56)) | O55: =(H55-MIN(H$50:H$56))/(MAX(H$50:H$56)-MIN(H$50:H$56)) | P55: =(I55-MIN(I$50:I$56))/(MAX(I$50:I$56)-MIN(I$50:I$56)) | Q55: =(J55-MIN(J$50:J$56))/(MAX(J$50:J$56)-MIN(J$50:J$56)) | R55: =(MAX(K$50:K$56)-K55)/(MAX(K$50:K$56)-MIN(K$50:K$56)) | S55: =(MAX(L$50:L$56)-L55)/(MAX(L$50:L$56)-MIN(L$50:L$56)) | T55: =(M55*'Fund Ranking Criteria'!$E$9)+('Fund Ranking_Equity'!N55*'Fund Ranking Criteria'!$E$10)+('Fund Ranking_Equity'!O55*'Fund Ranking Criteria'!$E$11)+('Fund Ranking_Equity'!P55*'Fund Ranking Criteria'!$E$16)+('Fund Ranking_Equity'!Q55*'Fund Ranking Criteria'!$E$12)+('Fund Ranking_Equity'!R55*'Fund Ranking Criteria'!$E$14)+('Fund Ranking_Equity'!S55*'Fund Ranking Criteria'!$E$15)
B56: UTI Focused Fund - Reg - Growth | C56: =RANK(T56,$T$50:$T$56,0) | D56: =B56 | E56: -2.3042 | F56: 10.3924 | G56: 0 | H56: 0 | I56: 0.046817028 | J56: -0.095272745 | K56: 0.93384428 | L56: 12.569103 | M56: =(F56-MIN(F$50:F$56))/(MAX(F$50:F$56)-MIN(F$50:F$56)) | N56: =(G56-MIN(G$50:G$56))/(MAX(G$50:G$56)-MIN(G$50:G$56)) | O56: =(H56-MIN(H$50:H$56))/(MAX(H$50:H$56)-MIN(H$50:H$56)) | P56: =(I56-MIN(I$50:I$56))/(MAX(I$50:I$56)-MIN(I$50:I$56)) | Q56: =(J56-MIN(J$50:J$56))/(MAX(J$50:J$56)-MIN(J$50:J$56)) | R56: =(MAX(K$50:K$56)-K56)/(MAX(K$50:K$56)-MIN(K$50:K$56)) | S56: =(MAX(L$50:L$56)-L56)/(MAX(L$50:L$56)-MIN(L$50:L$56)) | T56: =(M56*'Fund Ranking Criteria'!$E$9)+('Fund Ranking_Equity'!N56*'Fund Ranking Criteria'!$E$10)+('Fund Ranking_Equity'!O56*'Fund Ranking Criteria'!$E$11)+('Fund Ranking_Equity'!P56*'Fund Ranking Criteria'!$E$16)+('Fund Ranking_Equity'!Q56*'Fund Ranking Criteria'!$E$12)+('Fund Ranking_Equity'!R56*'Fund Ranking Criteria'!$E$14)+('Fund Ranking_Equity'!S56*'Fund Ranking Criteria'!$E$15)
E57: 2 | F57: 3 | G57: 4 | H57: 6 | I57: 7 | J57: =I57+1 | K57: =J57+1 | L57: =K57+1 | M57: =L57+1 | N57: =M57+1
B58: BAF
E59: Actuals | L59: Normalized
B60: Funds | C60: Rank | E60: 1 Yr Ret (%) | F60: 3 Yr Ret (%) | G60: 5 Yr Ret (%) | H60: 10 Yr Ret (%) | I60: Sharpe | J60: Alpha | K60: Beta | L60: SD | M60: =E60 | N60: =F60 | O60: =G60 | P60: Sharpe | Q60: Alpha | R60: Beta | S60: SD
B61: HDFC Balanced Advantage Fund - Growth | C61: =RANK(T61,$T$61:$T$67,0) | D61: =B61 | E61: 1.0595 | F61: 14.4785 | G61: 15.3021 | H61: 14.4676 | I61: 0.082921158 | J61: 0 | K61: 0 | L61: 9.2727479 | M61: =(E61-MIN(E$61:E$67))/(MAX(E$61:E$67)-MIN(E$61:E$67)) | N61: =(F61-MIN(F$61:F$67))/(MAX(F$61:F$67)-MIN(F$61:F$67)) | O61: 0 | P61: =(I61-MIN(I$61:I$67))/(MAX(I$61:I$67)-MIN(I$61:I$67)) | S61: =(MAX(L$61:L$67)-L61)/(MAX(L$61:L$67)-MIN(L$61:L$67)) | T61: =(M61*'Fund Ranking Criteria'!$F$9)+('Fund Ranking_Equity'!N61*'Fund Ranking Criteria'!$F$10)+('Fund Ranking_Equity'!O61*'Fund Ranking Criteria'!$F$11)+('Fund Ranking_Equity'!P61*'Fund Ranking Criteria'!$F$16)+('Fund Ranking_Equity'!Q61*'Fund Ranking Criteria'!$F$12)+('Fund Ranking_Equity'!R61*'Fund Ranking Criteria'!$F$14)+('Fund Ranking_Equity'!S61*'Fund Ranking Criteria'!$F$15)
B62: ICICI Prudential Balanced Advantage Fund - Reg - Growth | C62: =RANK(T62,$T$61:$T$67,0) | D62: =B62 | E62: 5.4987 | F62: 11.8269 | G62: 10.8951 | H62: 11.0726 | I62: 0.086077282 | J62: 0 | K62: 0 | L62: 6.2916941 | M62: =(E62-MIN(E$61:E$67))/(MAX(E$61:E$67)-MIN(E$61:E$67)) | N62: =(F62-MIN(F$61:F$67))/(MAX(F$61:F$67)-MIN(F$61:F$67)) | O62: =(G62-MIN(G$61:G$67))/(MAX(G$61:G$67)-MIN(G$61:G$67)) | P62: =(I62-MIN(I$61:I$67))/(MAX(I$61:I$67)-MIN(I$61:I$67)) | S62: =(MAX(L$61:L$67)-L62)/(MAX(L$61:L$67)-MIN(L$61:L$67)) | T62: =(M62*'Fund Ranking Criteria'!$F$9)+('Fund Ranking_Equity'!N62*'Fund Ranking Criteria'!$F$10)+('Fund Ranking_Equity'!O62*'Fund Ranking Criteria'!$F$11)+('Fund Ranking_Equity'!P62*'Fund Ranking Criteria'!$F$16)+('Fund Ranking_Equity'!Q62*'Fund Ranking Criteria'!$F$12)+('Fund Ranking_Equity'!R62*'Fund Ranking Criteria'!$F$14)+('Fund Ranking_Equity'!S62*'Fund Ranking Criteria'!$F$15)
B63: SBI Balanced Advantage Fund - Reg - Growth | C63: =RANK(T63,$T$61:$T$67,0) | D63: =B63 | E63: 3.7876 | F63: 11.0595 | G63: 0 | H63: 0 | I63: 0.083080752 | J63: 0 | K63: 0 | L63: 5.9661226 | M63: =(E63-MIN(E$61:E$67))/(MAX(E$61:E$67)-MIN(E$61:E$67)) | N63: =(F63-MIN(F$61:F$67))/(MAX(F$61:F$67)-MIN(F$61:F$67)) | O63: =(G63-MIN(G$61:G$67))/(MAX(G$61:G$67)-MIN(G$61:G$67)) | P63: =(I63-MIN(I$61:I$67))/(MAX(I$61:I$67)-MIN(I$61:I$67)) | S63: =(MAX(L$61:L$67)-L63)/(MAX(L$61:L$67)-MIN(L$61:L$67)) | T63: =(M63*'Fund Ranking Criteria'!$F$9)+('Fund Ranking_Equity'!N63*'Fund Ranking Criteria'!$F$10)+('Fund Ranking_Equity'!O63*'Fund Ranking Criteria'!$F$11)+('Fund Ranking_Equity'!P63*'Fund Ranking Criteria'!$F$16)+('Fund Ranking_Equity'!Q63*'Fund Ranking Criteria'!$F$12)+('Fund Ranking_Equity'!R63*'Fund Ranking Criteria'!$F$14)+('Fund Ranking_Equity'!S63*'Fund Ranking Criteria'!$F$15)
B64: Kotak Balanced Advantage Fund - Reg - Growth | C64: =RANK(T64,$T$61:$T$67,0) | D64: =B64 | E64: 2.2366 | F64: 9.707 | G64: 8.8336 | H64: 0 | I64: 0.052463637 | J64: 0 | K64: 0 | L64: 7.4152273 | M64: =(E64-MIN(E$61:E$67))/(MAX(E$61:E$67)-MIN(E$61:E$67)) | N64: =(F64-MIN(F$61:F$67))/(MAX(F$61:F$67)-MIN(F$61:F$67)) | O64: =(G64-MIN(G$61:G$67))/(MAX(G$61:G$67)-MIN(G$61:G$67)) | P64: =(I64-MIN(I$61:I$67))/(MAX(I$61:I$67)-MIN(I$61:I$67)) | S64: =(MAX(L$61:L$67)-L64)/(MAX(L$61:L$67)-MIN(L$61:L$67)) | T64: =(M64*'Fund Ranking Criteria'!$F$9)+('Fund Ranking_Equity'!N64*'Fund Ranking Criteria'!$F$10)+('Fund Ranking_Equity'!O64*'Fund Ranking Criteria'!$F$11)+('Fund Ranking_Equity'!P64*'Fund Ranking Criteria'!$F$16)+('Fund Ranking_Equity'!Q64*'Fund Ranking Criteria'!$F$12)+('Fund Ranking_Equity'!R64*'Fund Ranking Criteria'!$F$14)+('Fund Ranking_Equity'!S64*'Fund Ranking Criteria'!$F$15)
B65: UTI Balanced Advantage Fund - Reg - Growth | C65: =RANK(T65,$T$61:$T$67,0) | E65: -1.0919 | F65: 0 | G65: 0 | H65: 0 | I65: 0.031967865 | J65: 0 | K65: 0 | L65: 7.1409456 | M65: =(E65-MIN(E$61:E$67))/(MAX(E$61:E$67)-MIN(E$61:E$67)) | N65: =(F65-MIN(F$61:F$67))/(MAX(F$61:F$67)-MIN(F$61:F$67)) | O65: =(G65-MIN(G$61:G$67))/(MAX(G$61:G$67)-MIN(G$61:G$67)) | P65: =(I65-MIN(I$61:I$67))/(MAX(I$61:I$67)-MIN(I$61:I$67)) | S65: =(MAX(L$61:L$67)-L65)/(MAX(L$61:L$67)-MIN(L$61:L$67)) | T65: =(M65*'Fund Ranking Criteria'!$F$9)+('Fund Ranking_Equity'!N65*'Fund Ranking Criteria'!$F$10)+('Fund Ranking_Equity'!O65*'Fund Ranking Criteria'!$F$11)+('Fund Ranking_Equity'!P65*'Fund Ranking Criteria'!$F$16)+('Fund Ranking_Equity'!Q65*'Fund Ranking Criteria'!$F$12)+('Fund Ranking_Equity'!R65*'Fund Ranking Criteria'!$F$14)+('Fund Ranking_Equity'!S65*'Fund Ranking Criteria'!$F$15)
B66: Nippon India Balanced Advantage Fund - Reg - Growth | C66: =RANK(T66,$T$61:$T$67,0) | D66: =B66 | E66: 3.9559 | F66: 10.9263 | G66: 9.5562 | H66: 10.7794 | I66: 0.067215968 | J66: 0 | K66: 0 | L66: 7.3394626 | M66: =(E66-MIN(E$61:E$67))/(MAX(E$61:E$67)-MIN(E$61:E$67)) | N66: =(F66-MIN(F$61:F$67))/(MAX(F$61:F$67)-MIN(F$61:F$67)) | O66: =(G66-MIN(G$61:G$67))/(MAX(G$61:G$67)-MIN(G$61:G$67)) | P66: =(I66-MIN(I$61:I$67))/(MAX(I$61:I$67)-MIN(I$61:I$67)) | S66: =(MAX(L$61:L$67)-L66)/(MAX(L$61:L$67)-MIN(L$61:L$67)) | T66: =(M66*'Fund Ranking Criteria'!$F$9)+('Fund Ranking_Equity'!N66*'Fund Ranking Criteria'!$F$10)+('Fund Ranking_Equity'!O66*'Fund Ranking Criteria'!$F$11)+('Fund Ranking_Equity'!P66*'Fund Ranking Criteria'!$F$16)+('Fund Ranking_Equity'!Q66*'Fund Ranking Criteria'!$F$12)+('Fund Ranking_Equity'!R66*'Fund Ranking Criteria'!$F$14)+('Fund Ranking_Equity'!S66*'Fund Ranking Criteria'!$F$15)
B67: Aditya Birla Sun Life Balanced Advantage Fund - Growth | C67: =RANK(T67,$T$61:$T$67,0) | D67: =B67 | E67: 5.0076 | F67: 11.5148 | G67: 9.8314 | H67: 10.7277 | I67: 0.074498404 | J67: 0 | K67: 0 | L67: 7.2367983 | M67: =(E67-MIN(E$61:E$67))/(MAX(E$61:E$67)-MIN(E$61:E$67)) | N67: =(F67-MIN(F$61:F$67))/(MAX(F$61:F$67)-MIN(F$61:F$67)) | O67: =(G67-MIN(G$61:G$67))/(MAX(G$61:G$67)-MIN(G$61:G$67)) | P67: =(I67-MIN(I$61:I$67))/(MAX(I$61:I$67)-MIN(I$61:I$67)) | S67: =(MAX(L$61:L$67)-L67)/(MAX(L$61:L$67)-MIN(L$61:L$67)) | T67: =(M67*'Fund Ranking Criteria'!$F$9)+('Fund Ranking_Equity'!N67*'Fund Ranking Criteria'!$F$10)+('Fund Ranking_Equity'!O67*'Fund Ranking Criteria'!$F$11)+('Fund Ranking_Equity'!P67*'Fund Ranking Criteria'!$F$16)+('Fund Ranking_Equity'!Q67*'Fund Ranking Criteria'!$F$12)+('Fund Ranking_Equity'!R67*'Fund Ranking Criteria'!$F$14)+('Fund Ranking_Equity'!S67*'Fund Ranking Criteria'!$F$15)
B69: Multi Asset Fund
E70: Actuals | L70: Normalized
B71: Funds | C71: Rank | E71: 1 Yr Ret (%) | F71: 3 Yr Ret (%) | G71: 5 Yr Ret (%) | H71: 10 Yr Ret (%) | I71: Sharpe | J71: Alpha | K71: Beta | L71: SD | M71: =E71 | N71: =F71 | O71: =G71 | P71: Sharpe | Q71: Alpha | R71: Beta | S71: SD
B72: ICICI Prudential Multi-Asset Fund - Growth | C72: =RANK(T72,$T$72:$T$78,0) | D72: =B72 | E72: 6.7346 | F72: 16.5644 | G72: 17.5131 | H72: 15.7354 | I72: 0.12647475 | J72: 0 | K72: 0 | L72: 82.577547 | M72: =(E72-MIN(E$72:E$78))/(MAX(E$72:E$78)-MIN(E$72:E$78)) | N72: =(F72-MIN(F$72:F$78))/(MAX(F$72:F$78)-MIN(F$72:F$78)) | O72: =(G72-MIN(G$72:G$78))/(MAX(G$72:G$78)-MIN(G$72:G$78)) | P72: =(I72-MIN(I$72:I$78))/(MAX(I$72:I$78)-MIN(I$72:I$78)) | Q72: =(J72-MIN(J$72:J$78))/(MAX(J$72:J$78)-MIN(J$72:J$78)) | R72: =(MAX(K$72:K$78)-K72)/(MAX(K$72:K$78)-MIN(K$72:K$78)) | S72: =(MAX(L$72:L$78)-L72)/(MAX(L$72:L$78)-MIN(L$72:L$78)) | T72: =(M72*'Fund Ranking Criteria'!$I$9)+('Fund Ranking_Equity'!N72*'Fund Ranking Criteria'!$I$10)+('Fund Ranking_Equity'!O72*'Fund Ranking Criteria'!$I$11)+('Fund Ranking_Equity'!P72*'Fund Ranking Criteria'!$I$16)+('Fund Ranking_Equity'!Q72*'Fund Ranking Criteria'!$I$12)+('Fund Ranking_Equity'!R72*'Fund Ranking Criteria'!$I$14)+('Fund Ranking_Equity'!S72*'Fund Ranking Criteria'!$I$15)
B73: SBI Multi Asset Allocation Fund - Growth | C73: =RANK(T73,$T$72:$T$78,0) | D73: =B73 | E73: 12.8972 | F73: 16.5855 | G73: 13.5848 | H73: 11.4581 | I73: 0.1215957 | J73: 0 | K73: 0 | L73: 86.213761 | M73: =(E73-MIN(E$72:E$78))/(MAX(E$72:E$78)-MIN(E$72:E$78)) | N73: =(F73-MIN(F$72:F$78))/(MAX(F$72:F$78)-MIN(F$72:F$78)) | O73: =(G73-MIN(G$72:G$78))/(MAX(G$72:G$78)-MIN(G$72:G$78)) | P73: =(I73-MIN(I$72:I$78))/(MAX(I$72:I$78)-MIN(I$72:I$78)) | Q73: =(J73-MIN(J$72:J$78))/(MAX(J$72:J$78)-MIN(J$72:J$78)) | R73: =(MAX(K$72:K$78)-K73)/(MAX(K$72:K$78)-MIN(K$72:K$78)) | S73: =(MAX(L$72:L$78)-L73)/(MAX(L$72:L$78)-MIN(L$72:L$78)) | T73: =(M73*'Fund Ranking Criteria'!$I$9)+('Fund Ranking_Equity'!N73*'Fund Ranking Criteria'!$I$10)+('Fund Ranking_Equity'!O73*'Fund Ranking Criteria'!$I$11)+('Fund Ranking_Equity'!P73*'Fund Ranking Criteria'!$I$16)+('Fund Ranking_Equity'!Q73*'Fund Ranking Criteria'!$I$12)+('Fund Ranking_Equity'!R73*'Fund Ranking Criteria'!$I$14)+('Fund Ranking_Equity'!S73*'Fund Ranking Criteria'!$I$15)
B74: Kotak Multi Asset Allocation Fund -Reg - Growth | C74: =RANK(T74,$T$72:$T$78,0) | D74: =B74 | E74: 20.9116 | F74: 0 | G74: 0 | H74: 0 | I74: 0.10256021 | J74: 0 | K74: 0 | L74: 118.10988 | M74: =(E74-MIN(E$72:E$78))/(MAX(E$72:E$78)-MIN(E$72:E$78)) | N74: =(F74-MIN(F$72:F$78))/(MAX(F$72:F$78)-MIN(F$72:F$78)) | O74: =(G74-MIN(G$72:G$78))/(MAX(G$72:G$78)-MIN(G$72:G$78)) | P74: =(I74-MIN(I$72:I$78))/(MAX(I$72:I$78)-MIN(I$72:I$78)) | Q74: =(J74-MIN(J$72:J$78))/(MAX(J$72:J$78)-MIN(J$72:J$78)) | R74: =(MAX(K$72:K$78)-K74)/(MAX(K$72:K$78)-MIN(K$72:K$78)) | S74: =(MAX(L$72:L$78)-L74)/(MAX(L$72:L$78)-MIN(L$72:L$78)) | T74: =(M74*'Fund Ranking Criteria'!$I$9)+('Fund Ranking_Equity'!N74*'Fund Ranking Criteria'!$I$10)+('Fund Ranking_Equity'!O74*'Fund Ranking Criteria'!$I$11)+('Fund Ranking_Equity'!P74*'Fund Ranking Criteria'!$I$16)+('Fund Ranking_Equity'!Q74*'Fund Ranking Criteria'!$I$12)+('Fund Ranking_Equity'!R74*'Fund Ranking Criteria'!$I$14)+('Fund Ranking_Equity'!S74*'Fund Ranking Criteria'!$I$15)
B75: Nippon India Multi Asset Allocation Fund - Reg - Growth | C75: =RANK(T75,$T$72:$T$78,0) | D75: =B75 | E75: 15.5863 | F75: 19.22 | G75: 15.5969 | H75: 0 | I75: 0.13657493 | J75: 0 | K75: 0 | L75: 96.341687 | M75: =(E75-MIN(E$72:E$78))/(MAX(E$72:E$78)-MIN(E$72:E$78)) | N75: =(F75-MIN(F$72:F$78))/(MAX(F$72:F$78)-MIN(F$72:F$78)) | O75: =(G75-MIN(G$72:G$78))/(MAX(G$72:G$78)-MIN(G$72:G$78)) | P75: =(I75-MIN(I$72:I$78))/(MAX(I$72:I$78)-MIN(I$72:I$78)) | Q75: =(J75-MIN(J$72:J$78))/(MAX(J$72:J$78)-MIN(J$72:J$78)) | R75: =(MAX(K$72:K$78)-K75)/(MAX(K$72:K$78)-MIN(K$72:K$78)) | S75: =(MAX(L$72:L$78)-L75)/(MAX(L$72:L$78)-MIN(L$72:L$78)) | T75: =(M75*'Fund Ranking Criteria'!$I$9)+('Fund Ranking_Equity'!N75*'Fund Ranking Criteria'!$I$10)+('Fund Ranking_Equity'!O75*'Fund Ranking Criteria'!$I$11)+('Fund Ranking_Equity'!P75*'Fund Ranking Criteria'!$I$16)+('Fund Ranking_Equity'!Q75*'Fund Ranking Criteria'!$I$12)+('Fund Ranking_Equity'!R75*'Fund Ranking Criteria'!$I$14)+('Fund Ranking_Equity'!S75*'Fund Ranking Criteria'!$I$15)
B76: UTI Multi Asset Allocation Fund - Growth | C76: =RANK(T76,$T$72:$T$78,0) | D76: =B76 | E76: 6.7006 | F76: 15.968 | G76: 13.5476 | H76: 10.8395 | I76: 0.10835541 | J76: 0 | K76: 0 | L76: 99.447885 | M76: =(E76-MIN(E$72:E$78))/(MAX(E$72:E$78)-MIN(E$72:E$78)) | N76: =(F76-MIN(F$72:F$78))/(MAX(F$72:F$78)-MIN(F$72:F$78)) | O76: =(G76-MIN(G$72:G$78))/(MAX(G$72:G$78)-MIN(G$72:G$78)) | P76: =(I76-MIN(I$72:I$78))/(MAX(I$72:I$78)-MIN(I$72:I$78)) | Q76: =(J76-MIN(J$72:J$78))/(MAX(J$72:J$78)-MIN(J$72:J$78)) | R76: =(MAX(K$72:K$78)-K76)/(MAX(K$72:K$78)-MIN(K$72:K$78)) | S76: =(MAX(L$72:L$78)-L76)/(MAX(L$72:L$78)-MIN(L$72:L$78)) | T76: =(M76*'Fund Ranking Criteria'!$I$9)+('Fund Ranking_Equity'!N76*'Fund Ranking Criteria'!$I$10)+('Fund Ranking_Equity'!O76*'Fund Ranking Criteria'!$I$11)+('Fund Ranking_Equity'!P76*'Fund Ranking Criteria'!$I$16)+('Fund Ranking_Equity'!Q76*'Fund Ranking Criteria'!$I$12)+('Fund Ranking_Equity'!R76*'Fund Ranking Criteria'!$I$14)+('Fund Ranking_Equity'!S76*'Fund Ranking Criteria'!$I$15)
B77: HDFC Multi - Asset Fund - Growth | C77: =RANK(T77,$T$72:$T$78,0) | D77: =B77 | E77: 7.1325 | F77: 15.63 | G77: 16.2162 | H77: 11.0444 | I77: 0.12029263 | J77: 3.6452247 | K77: 0.49482937 | L77: 81.466544 | M77: =(E77-MIN(E$72:E$78))/(MAX(E$72:E$78)-MIN(E$72:E$78)) | N77: =(F77-MIN(F$72:F$78))/(MAX(F$72:F$78)-MIN(F$72:F$78)) | O77: =(G77-MIN(G$72:G$78))/(MAX(G$72:G$78)-MIN(G$72:G$78)) | P77: =(I77-MIN(I$72:I$78))/(MAX(I$72:I$78)-MIN(I$72:I$78)) | Q77: =(J77-MIN(J$72:J$78))/(MAX(J$72:J$78)-MIN(J$72:J$78)) | R77: =(MAX(K$72:K$78)-K77)/(MAX(K$72:K$78)-MIN(K$72:K$78)) | S77: =(MAX(L$72:L$78)-L77)/(MAX(L$72:L$78)-MIN(L$72:L$78)) | T77: =(M77*'Fund Ranking Criteria'!$I$9)+('Fund Ranking_Equity'!N77*'Fund Ranking Criteria'!$I$10)+('Fund Ranking_Equity'!O77*'Fund Ranking Criteria'!$I$11)+('Fund Ranking_Equity'!P77*'Fund Ranking Criteria'!$I$16)+('Fund Ranking_Equity'!Q77*'Fund Ranking Criteria'!$I$12)+('Fund Ranking_Equity'!R77*'Fund Ranking Criteria'!$I$14)+('Fund Ranking_Equity'!S77*'Fund Ranking Criteria'!$I$15)
B78: Aditya Birla Sun Life Multi Asset Allocation Fund - Reg - Growth | C78: =RANK(T78,$T$72:$T$78,0) | D78: =B78 | E78: 14.0136 | F78: 16.0028 | G78: 0 | H78: 0 | I78: 0.10021829 | J78: 0 | K78: 0 | L78: 104.52919 | M78: =(E78-MIN(E$72:E$78))/(MAX(E$72:E$78)-MIN(E$72:E$78)) | N78: =(F78-MIN(F$72:F$78))/(MAX(F$72:F$78)-MIN(F$72:F$78)) | O78: =(G78-MIN(G$72:G$78))/(MAX(G$72:G$78)-MIN(G$72:G$78)) | P78: =(I78-MIN(I$72:I$78))/(MAX(I$72:I$78)-MIN(I$72:I$78)) | Q78: =(J78-MIN(J$72:J$78))/(MAX(J$72:J$78)-MIN(J$72:J$78)) | R78: =(MAX(K$72:K$78)-K78)/(MAX(K$72:K$78)-MIN(K$72:K$78)) | S78: =(MAX(L$72:L$78)-L78)/(MAX(L$72:L$78)-MIN(L$72:L$78)) | T78: =(M78*'Fund Ranking Criteria'!$I$9)+('Fund Ranking_Equity'!N78*'Fund Ranking Criteria'!$I$10)+('Fund Ranking_Equity'!O78*'Fund Ranking Criteria'!$I$11)+('Fund Ranking_Equity'!P78*'Fund Ranking Criteria'!$I$16)+('Fund Ranking_Equity'!Q78*'Fund Ranking Criteria'!$I$12)+('Fund Ranking_Equity'!R78*'Fund Ranking Criteria'!$I$14)+('Fund Ranking_Equity'!S78*'Fund Ranking Criteria'!$I$15)
B80: Thematic
E81: Actuals | L81: Normalized
B82: Funds | C82: Rank | E82: 1 Yr Ret (%) | F82: 3 Yr Ret (%) | G82: 5 Yr Ret (%) | H82: 10 Yr Ret (%) | I82: Sharpe | J82: Alpha | K82: Beta | L82: SD | M82: =E82 | N82: =F82 | O82: =G82 | P82: Alpha | Q82: Beta | R82: SD | S82: Sharpe
B83: Aditya Birla Sun Life PSU Equity Fund - Reg - Growth | C83: =RANK(T83,$T$83:$T$137,0) | D83: =B83 | E83: 12.4123 | F83: 26.3701 | G83: 23.776 | H83: 0 | I83: 0.083751563 | J83: 0.067907402 | K83: 0.94372152 | L83: 20.821814 | M83: =(E83-MIN(E$83:E$137))/(MAX(E$83:E$137)-MIN(E$83:E$137)) | N83: =(F83-MIN(F$83:F$137))/(MAX(F$83:F$137)-MIN(F$83:F$137)) | O83: =(G83-MIN(G$83:G$137))/(MAX(G$83:G$137)-MIN(G$83:G$137)) | P83: =(J83-MIN(J$83:J$137))/(MAX(J$83:J$137)-MIN(J$83:J$137)) | Q83: =(MAX(K$83:K$137)-K83)/(MAX(K$83:K$137)-MIN(K$83:K$137)) | R83: =(MAX(L$83:L$137)-L83)/(MAX(L$83:L$137)-MIN(L$83:L$137)) | S83: =(I83-MIN(I$83:I$137))/(MAX(I$83:I$137)-MIN(I$83:I$137)) | T83: {=SUMPRODUCT(M83:P83,TRANSPOSE('Fund Ranking Criteria'!$K$9:$K$12))+SUMPRODUCT('Fund Ranking_Equity'!Q83:S83, TRANSPOSE('Fund Ranking Criteria'!$K$14:$K$16))}
B84: Aditya Birla Sun Life Banking and Financial Services Fund - Reg - Growth | C84: =RANK(T84,$T$83:$T$137,0) | D84: =B84 | E84: 3.7948 | F84: 12.7134 | G84: 11.9785 | H84: 12.9355 | I84: 0.050382773 | J84: 0.25927097 | K84: 0.91830404 | L84: 14.153184 | M84: =(E84-MIN(E$83:E$137))/(MAX(E$83:E$137)-MIN(E$83:E$137)) | N84: =(F84-MIN(F$83:F$137))/(MAX(F$83:F$137)-MIN(F$83:F$137)) | O84: =(G84-MIN(G$83:G$137))/(MAX(G$83:G$137)-MIN(G$83:G$137)) | P84: =(H84-MIN(H$83:H$137))/(MAX(H$83:H$137)-MIN(H$83:H$137)) | Q84: =(MAX(K$83:K$137)-K84)/(MAX(K$83:K$137)-MIN(K$83:K$137)) | R84: =(MAX(L$83:L$137)-L84)/(MAX(L$83:L$137)-MIN(L$83:L$137)) | S84: =(I84-MIN(I$83:I$137))/(MAX(I$83:I$137)-MIN(I$83:I$137)) | T84: {=SUMPRODUCT(M84:P84,TRANSPOSE('Fund Ranking Criteria'!$K$9:$K$12))+SUMPRODUCT('Fund Ranking_Equity'!Q84:S84, TRANSPOSE('Fund Ranking Criteria'!$K$14:$K$16))}
B85: Aditya Birla Sun Life Quant Fund - Reg - Growth | C85: =RANK(T85,$T$83:$T$137,0) | D85: =B85 | E85: 7.7088 | F85: 0 | G85: 0 | H85: 0 | I85: -0.029636514 | J85: -0.059540444 | K85: 1.0733081 | L85: 13.736123 | M85: =(E85-MIN(E$83:E$137))/(MAX(E$83:E$137)-MIN(E$83:E$137)) | N85: =(F85-MIN(F$83:F$137))/(MAX(F$83:F$137)-MIN(F$83:F$137)) | O85: =(G85-MIN(G$83:G$137))/(MAX(G$83:G$137)-MIN(G$83:G$137)) | P85: =(H85-MIN(H$83:H$137))/(MAX(H$83:H$137)-MIN(H$83:H$137)) | Q85: =(MAX(K$83:K$137)-K85)/(MAX(K$83:K$137)-MIN(K$83:K$137)) | R85: =(MAX(L$83:L$137)-L85)/(MAX(L$83:L$137)-MIN(L$83:L$137)) | S85: =(I85-MIN(I$83:I$137))/(MAX(I$83:I$137)-MIN(I$83:I$137)) | T85: {=SUMPRODUCT(M85:P85,TRANSPOSE('Fund Ranking Criteria'!$K$9:$K$12))+SUMPRODUCT('Fund Ranking_Equity'!Q85:S85, TRANSPOSE('Fund Ranking Criteria'!$K$14:$K$16))}
B86: Aditya Birla Sun Life Business Cycle Fund - Reg - Growth | C86: =RANK(T86,$T$83:$T$137,0) | D86: =B86 | E86: 1.94 | F86: 12.3077 | G86: 0 | H86: 0 | I86: 0.052394657 | J86: 0.051738858 | K86: 1.010447 | L86: 13.237558 | M86: =(E86-MIN(E$83:E$137))/(MAX(E$83:E$137)-MIN(E$83:E$137)) | N86: =(F86-MIN(F$83:F$137))/(MAX(F$83:F$137)-MIN(F$83:F$137)) | O86: =(G86-MIN(G$83:G$137))/(MAX(G$83:G$137)-MIN(G$83:G$137)) | P86: =(H86-MIN(H$83:H$137))/(MAX(H$83:H$137)-MIN(H$83:H$137)) | Q86: =(MAX(K$83:K$137)-K86)/(MAX(K$83:K$137)-MIN(K$83:K$137)) | R86: =(MAX(L$83:L$137)-L86)/(MAX(L$83:L$137)-MIN(L$83:L$137)) | S86: =(I86-MIN(I$83:I$137))/(MAX(I$83:I$137)-MIN(I$83:I$137)) | T86: {=SUMPRODUCT(M86:P86,TRANSPOSE('Fund Ranking Criteria'!$K$9:$K$12))+SUMPRODUCT('Fund Ranking_Equity'!Q86:S86, TRANSPOSE('Fund Ranking Criteria'!$K$14:$K$16))}
B87: Aditya Birla Sun Life Conglomerate Fund - Reg - Growth | C87: =RANK(T87,$T$83:$T$137,0) | D87: =B87 | E87: 2.649 | F87: 0 | G87: 0 | H87: 0 | I87: 0.0061267408 | J87: 0 | K87: 0 | L87: 14.174903 | M87: =(E87-MIN(E$83:E$137))/(MAX(E$83:E$137)-MIN(E$83:E$137)) | N87: =(F87-MIN(F$83:F$137))/(MAX(F$83:F$137)-MIN(F$83:F$137)) | O87: =(G87-MIN(G$83:G$137))/(MAX(G$83:G$137)-MIN(G$83:G$137)) | P87: =(H87-MIN(H$83:H$137))/(MAX(H$83:H$137)-MIN(H$83:H$137)) | Q87: =(MAX(K$83:K$137)-K87)/(MAX(K$83:K$137)-MIN(K$83:K$137)) | R87: =(MAX(L$83:L$137)-L87)/(MAX(L$83:L$137)-MIN(L$83:L$137)) | S87: =(I87-MIN(I$83:I$137))/(MAX(I$83:I$137)-MIN(I$83:I$137)) | T87: {=SUMPRODUCT(M87:P87,TRANSPOSE('Fund Ranking Criteria'!$K$9:$K$12))+SUMPRODUCT('Fund Ranking_Equity'!Q87:S87, TRANSPOSE('Fund Ranking Criteria'!$K$14:$K$16))}
B88: Aditya Birla Sun Life Transportation and Logistics Fund - Reg - Growth | C88: =RANK(T88,$T$83:$T$137,0) | D88: =B88 | E88: 15.6273 | F88: 0 | G88: 0 | H88: 0 | I88: 0.060165355 | J88: 0.21601745 | K88: 0.98000892 | L88: 17.847936 | M88: =(E88-MIN(E$83:E$137))/(MAX(E$83:E$137)-MIN(E$83:E$137)) | N88: =(F88-MIN(F$83:F$137))/(MAX(F$83:F$137)-MIN(F$83:F$137)) | O88: =(G88-MIN(G$83:G$137))/(MAX(G$83:G$137)-MIN(G$83:G$137)) | P88: =(H88-MIN(H$83:H$137))/(MAX(H$83:H$137)-MIN(H$83:H$137)) | Q88: =(MAX(K$83:K$137)-K88)/(MAX(K$83:K$137)-MIN(K$83:K$137)) | R88: =(MAX(L$83:L$137)-L88)/(MAX(L$83:L$137)-MIN(L$83:L$137)) | S88: =(I88-MIN(I$83:I$137))/(MAX(I$83:I$137)-MIN(I$83:I$137)) | T88: {=SUMPRODUCT(M88:P88,TRANSPOSE('Fund Ranking Criteria'!$K$9:$K$12))+SUMPRODUCT('Fund Ranking_Equity'!Q88:S88, TRANSPOSE('Fund Ranking Criteria'!$K$14:$K$16))}
B89: Aditya Birla Sun Life Manufacturing Equity Fund - Reg - Growth | C89: =RANK(T89,$T$83:$T$137,0) | D89: =B89 | E89: 17.8674 | F89: 20.511 | G89: 14.1089 | H89: 14.0559 | I89: 0.090404046 | J89: 0.12950659 | K89: 0.99374404 | L89: 15.03827 | M89: =(E89-MIN(E$83:E$137))/(MAX(E$83:E$137)-MIN(E$83:E$137)) | N89: =(F89-MIN(F$83:F$137))/(MAX(F$83:F$137)-MIN(F$83:F$137)) | O89: =(G89-MIN(G$83:G$137))/(MAX(G$83:G$137)-MIN(G$83:G$137)) | P89: =(H89-MIN(H$83:H$137))/(MAX(H$83:H$137)-MIN(H$83:H$137)) | Q89: =(MAX(K$83:K$137)-K89)/(MAX(K$83:K$137)-MIN(K$83:K$137)) | R89: =(MAX(L$83:L$137)-L89)/(MAX(L$83:L$137)-MIN(L$83:L$137)) | S89: =(I89-MIN(I$83:I$137))/(MAX(I$83:I$137)-MIN(I$83:I$137)) | T89: {=SUMPRODUCT(M89:P89,TRANSPOSE('Fund Ranking Criteria'!$K$9:$K$12))+SUMPRODUCT('Fund Ranking_Equity'!Q89:S89, TRANSPOSE('Fund Ranking Criteria'!$K$14:$K$16))}
B90: Aditya Birla Sun Life Pharma & Healthcare Fund - Reg - Growth | C90: =RANK(T90,$T$83:$T$137,0) | D90: =B90 | E90: 12.3787 | F90: 22.2382 | G90: 12.9199 | H90: 0 | I90: 0.11204406 | J90: -0.058776534 | K90: 0.94328839 | L90: 13.152926 | M90: =(E90-MIN(E$83:E$137))/(MAX(E$83:E$137)-MIN(E$83:E$137)) | N90: =(F90-MIN(F$83:F$137))/(MAX(F$83:F$137)-MIN(F$83:F$137)) | O90: =(G90-MIN(G$83:G$137))/(MAX(G$83:G$137)-MIN(G$83:G$137)) | P90: =(H90-MIN(H$83:H$137))/(MAX(H$83:H$137)-MIN(H$83:H$137)) | Q90: =(MAX(K$83:K$137)-K90)/(MAX(K$83:K$137)-MIN(K$83:K$137)) | R90: =(MAX(L$83:L$137)-L90)/(MAX(L$83:L$137)-MIN(L$83:L$137)) | S90: =(I90-MIN(I$83:I$137))/(MAX(I$83:I$137)-MIN(I$83:I$137)) | T90: {=SUMPRODUCT(M90:P90,TRANSPOSE('Fund Ranking Criteria'!$K$9:$K$12))+SUMPRODUCT('Fund Ranking_Equity'!Q90:S90, TRANSPOSE('Fund Ranking Criteria'!$K$14:$K$16))}
B91: Aditya Birla Sun Life Special Opportunities Fund - Reg - Growth | C91: =RANK(T91,$T$83:$T$137,0) | D91: =B91 | E91: 15.4549 | F91: 20.3702 | G91: 15.1693 | H91: 0 | I91: 0.096975563 | J91: 0.60092584 | K91: 1.0307684 | L91: 13.644273 | M91: =(E91-MIN(E$83:E$137))/(MAX(E$83:E$137)-MIN(E$83:E$137)) | N91: =(F91-MIN(F$83:F$137))/(MAX(F$83:F$137)-MIN(F$83:F$137)) | O91: =(G91-MIN(G$83:G$137))/(MAX(G$83:G$137)-MIN(G$83:G$137)) | P91: =(H91-MIN(H$83:H$137))/(MAX(H$83:H$137)-MIN(H$83:H$137)) | Q91: =(MAX(K$83:K$137)-K91)/(MAX(K$83:K$137)-MIN(K$83:K$137)) | R91: =(MAX(L$83:L$137)-L91)/(MAX(L$83:L$137)-MIN(L$83:L$137)) | S91: =(I91-MIN(I$83:I$137))/(MAX(I$83:I$137)-MIN(I$83:I$137)) | T91: {=SUMPRODUCT(M91:P91,TRANSPOSE('Fund Ranking Criteria'!$K$9:$K$12))+SUMPRODUCT('Fund Ranking_Equity'!Q91:S91, TRANSPOSE('Fund Ranking Criteria'!$K$14:$K$16))}
B92: Aditya Birla Sun Life ESG Integration Strategy Fund - Reg - Growth | C92: =RANK(T92,$T$83:$T$137,0) | D92: =B92 | E92: -0.1698 | F92: 11.7168 | G92: 9.3301 | H92: 0 | I92: 0.048176049 | J92: -0.005238879 | K92: 1.0158994 | L92: 13.849979 | M92: =(E92-MIN(E$83:E$137))/(MAX(E$83:E$137)-MIN(E$83:E$137)) | N92: =(F92-MIN(F$83:F$137))/(MAX(F$83:F$137)-MIN(F$83:F$137)) | O92: =(G92-MIN(G$83:G$137))/(MAX(G$83:G$137)-MIN(G$83:G$137)) | P92: =(H92-MIN(H$83:H$137))/(MAX(H$83:H$137)-MIN(H$83:H$137)) | Q92: =(MAX(K$83:K$137)-K92)/(MAX(K$83:K$137)-MIN(K$83:K$137)) | R92: =(MAX(L$83:L$137)-L92)/(MAX(L$83:L$137)-MIN(L$83:L$137)) | S92: =(I92-MIN(I$83:I$137))/(MAX(I$83:I$137)-MIN(I$83:I$137)) | T92: {=SUMPRODUCT(M92:P92,TRANSPOSE('Fund Ranking Criteria'!$K$9:$K$12))+SUMPRODUCT('Fund Ranking_Equity'!Q92:S92, TRANSPOSE('Fund Ranking Criteria'!$K$14:$K$16))}
B93: UTI Quant Fund - Reg - Growth | C93: =RANK(T93,$T$83:$T$137,0) | D93: =B93 | E93: -2.1351 | F93: 0 | G93: 0 | H93: 0 | I93: 0.0097910486 | J93: -0.15487748 | K93: 0.97694778 | L93: 11.4488 | M93: =(E93-MIN(E$83:E$137))/(MAX(E$83:E$137)-MIN(E$83:E$137)) | N93: =(F93-MIN(F$83:F$137))/(MAX(F$83:F$137)-MIN(F$83:F$137)) | O93: =(G93-MIN(G$83:G$137))/(MAX(G$83:G$137)-MIN(G$83:G$137)) | P93: =(H93-MIN(H$83:H$137))/(MAX(H$83:H$137)-MIN(H$83:H$137)) | Q93: =(MAX(K$83:K$137)-K93)/(MAX(K$83:K$137)-MIN(K$83:K$137)) | R93: =(MAX(L$83:L$137)-L93)/(MAX(L$83:L$137)-MIN(L$83:L$137)) | S93: =(I93-MIN(I$83:I$137))/(MAX(I$83:I$137)-MIN(I$83:I$137)) | T93: {=SUMPRODUCT(M93:P93,TRANSPOSE('Fund Ranking Criteria'!$K$9:$K$12))+SUMPRODUCT('Fund Ranking_Equity'!Q93:S93, TRANSPOSE('Fund Ranking Criteria'!$K$14:$K$16))}
B94: UTI Innovation Fund - Reg - Growth | C94: =RANK(T94,$T$83:$T$137,0) | D94: =B94 | E94: -4.2478 | F94: 0 | G94: 0 | H94: 0 | I94: -0.001511786 | J94: -0.6351482 | K94: 1.2014882 | L94: 19.506515 | M94: =(E94-MIN(E$83:E$137))/(MAX(E$83:E$137)-MIN(E$83:E$137)) | N94: =(F94-MIN(F$83:F$137))/(MAX(F$83:F$137)-MIN(F$83:F$137)) | O94: =(G94-MIN(G$83:G$137))/(MAX(G$83:G$137)-MIN(G$83:G$137)) | P94: =(H94-MIN(H$83:H$137))/(MAX(H$83:H$137)-MIN(H$83:H$137)) | Q94: =(MAX(K$83:K$137)-K94)/(MAX(K$83:K$137)-MIN(K$83:K$137)) | R94: =(MAX(L$83:L$137)-L94)/(MAX(L$83:L$137)-MIN(L$83:L$137)) | S94: =(I94-MIN(I$83:I$137))/(MAX(I$83:I$137)-MIN(I$83:I$137)) | T94: {=SUMPRODUCT(M94:P94,TRANSPOSE('Fund Ranking Criteria'!$K$9:$K$12))+SUMPRODUCT('Fund Ranking_Equity'!Q94:S94, TRANSPOSE('Fund Ranking Criteria'!$K$14:$K$16))}
B95: ICICI Prudential Pharma Healthcare and Diagnostics Fund - Reg - Growth | C95: =RANK(T95,$T$83:$T$137,0) | D95: =B95 | E95: 7.5452 | F95: 25.5129 | G95: 15.7185 | H95: 0 | I95: 0.13096748 | J95: 0.16792189 | K95: 0.93453235 | L95: 12.874802 | M95: =(E95-MIN(E$83:E$137))/(MAX(E$83:E$137)-MIN(E$83:E$137)) | N95: =(F95-MIN(F$83:F$137))/(MAX(F$83:F$137)-MIN(F$83:F$137)) | O95: =(G95-MIN(G$83:G$137))/(MAX(G$83:G$137)-MIN(G$83:G$137)) | P95: =(H95-MIN(H$83:H$137))/(MAX(H$83:H$137)-MIN(H$83:H$137)) | Q95: =(MAX(K$83:K$137)-K95)/(MAX(K$83:K$137)-MIN(K$83:K$137)) | R95: =(MAX(L$83:L$137)-L95)/(MAX(L$83:L$137)-MIN(L$83:L$137)) | S95: =(I95-MIN(I$83:I$137))/(MAX(I$83:I$137)-MIN(I$83:I$137)) | T95: {=SUMPRODUCT(M95:P95,TRANSPOSE('Fund Ranking Criteria'!$K$9:$K$12))+SUMPRODUCT('Fund Ranking_Equity'!Q95:S95, TRANSPOSE('Fund Ranking Criteria'!$K$14:$K$16))}
... B137: Kotak Healthcare Fund - Reg - Growth | C137: =RANK(T137,$T$83:$T$137,0) | D137: =B137 | E137: 17.5398 | F137: 0 | G137: 0 | H137: 0 | I137: 0.075104721 | J137: 0.099349039 | K137: 0.99349116 | L137: 13.95435 | M137: =(E137-MIN(E$83:E$137))/(MAX(E$83:E$137)-MIN(E$83:E$137)) | N137: =(F137-MIN(F$83:F$137))/(MAX(F$83:F$137)-MIN(F$83:F$137)) | O137: =(G137-MIN(G$83:G$137))/(MAX(G$83:G$137)-MIN(G$83:G$137)) | P137: =(H137-MIN(H$83:H$137))/(MAX(H$83:H$137)-MIN(H$83:H$137)) | Q137: =(MAX(K$83:K$137)-K137)/(MAX(K$83:K$137)-MIN(K$83:K$137)) | R137: =(MAX(L$83:L$137)-L137)/(MAX(L$83:L$137)-MIN(L$83:L$137)) | S137: =(I137-MIN(I$83:I$137))/(MAX(I$83:I$137)-MIN(I$83:I$137)) | T137: {=SUMPRODUCT(M137:P137,TRANSPOSE('Fund Ranking Criteria'!$K$9:$K$12))+SUMPRODUCT('Fund Ranking_Equity'!Q137:S137, TRANSPOSE('Fund Ranking Criteria'!$K$14:$K$16))}

Sheet Fund Ranking_Equity (2)
B1: (Match with morningstar)
B2: Model Portfolio | E2: 2 | F2: =E2+1 | G2: =F2+1 | H2: =G2+1 | I2: =H2+1 | J2: =I2+1 | K2: =J2+1 | L2: =K2+1 | M2: =L2+1 | ... O2: =N2+1
B3: Equity Large Cap
E4: Actuals | P4: Normalized | Z4: Score
B5: Funds | C5: Rank | E5: 1 Yr Ret (%) | F5: 3 Yr Ret (%) | G5: 5 Yr Ret (%) | H5: 10 Yr Ret (%) | I5: Sharpe | J5: Sortino | K5: Alpha | L5: Expense Ratio | M5: Turnover Ratio | N5: Beta | O5: SD | P5: =F5 | Q5: =G5 | R5: =H5 | S5: Sharpe | T5: Sortino | U5: Alpha | V5: Expense Ratio | W5: Turnover Ratio | X5: Beta | Y5: SD
B6: Aditya Birla Sun Life Large Cap Fund - Regular Plan | C6: =RANK(Z6,$Z$6:$Z$12,0) | D6: =B6 | E6: =VLOOKUP($B6, Sheet4!$A$2:$L$688, 'Fund Ranking_Equity (2)'!E$2,FALSE) | F6: =VLOOKUP($B6, Sheet4!$A$2:$L$688, 'Fund Ranking_Equity (2)'!F$2,FALSE) | G6: =VLOOKUP($B6, Sheet4!$A$2:$L$688, 'Fund Ranking_Equity (2)'!G$2,FALSE) | H6: =VLOOKUP($B6, Sheet4!$A$2:$L$688, 'Fund Ranking_Equity (2)'!H$2,FALSE) | I6: =VLOOKUP($B6, Sheet4!$A$2:$L$688, 'Fund Ranking_Equity (2)'!I$2,FALSE) | J6: =VLOOKUP($B6, Sheet4!$A$2:$L$688, 'Fund Ranking_Equity (2)'!J$2,FALSE) | K6: =VLOOKUP($B6, Sheet4!$A$2:$L$688, 'Fund Ranking_Equity (2)'!K$2,FALSE) | L6: =VLOOKUP($B6, Sheet4!$A$2:$L$688, 'Fund Ranking_Equity (2)'!L$2,FALSE) | ... O6: =VLOOKUP($B6, Sheet4!$A$2:$L$688, 'Fund Ranking_Equity (2)'!O$2,FALSE) | P6: =(F6-MIN(F$6:F$12))/(MAX(F$6:F$12)-MIN(F$6:F$12)) | Q6: =(G6-MIN(G$6:G$12))/(MAX(G$6:G$12)-MIN(G$6:G$12)) | R6: =(H6-MIN(H$6:H$12))/(MAX(H$6:H$12)-MIN(H$6:H$12)) | S6: =(I6-MIN(I$6:I$12))/(MAX(I$6:I$12)-MIN(I$6:I$12)) | T6: =(J6-MIN(J$6:J$12))/(MAX(J$6:J$12)-MIN(J$6:J$12)) | U6: =(K6-MIN(K$6:K$12))/(MAX(K$6:K$12)-MIN(K$6:K$12)) | V6: =(MAX(L$6:L$12)-L6)/(MAX(L$6:L$12)-MIN(L$6:L$12)) | W6: =(MAX(M$6:M$12)-M6)/(MAX(M$6:M$12)-MIN(M$6:M$12)) | X6: =(MAX(N$6:N$12)-N6)/(MAX(N$6:N$12)-MIN(N$6:N$12)) | Y6: =(MAX(O$6:O$12)-O6)/(MAX(O$6:O$12)-MIN(O$6:O$12)) | Z6: =(P6*'Fund Ranking Criteria'!$C$9)+('Fund Ranking_Equity (2)'!Q6*'Fund Ranking Criteria'!$C$10)+('Fund Ranking_Equity (2)'!R6*'Fund Ranking Criteria'!$C$11)+('Fund Ranking_Equity (2)'!S6*'Fund Ranking Criteria'!$C$16)+('Fund Ranking_Equity (2)'!T6*'Fund Ranking Criteria'!#REF!)+('Fund Ranking_Equity (2)'!U6*'Fund Ranking Criteria'!$C$12)+('Fund Ranking_Equity (2)'!V6*'Fund Ranking Criteria'!#REF!)+('Fund Ranking_Equity (2)'!W6*'Fund Ranking Criteria'!#REF!)+('Fund Ranking_Equity (2)'!X6*'Fund Ranking Criteria'!$C$14)+('Fund Ranking_Equity (2)'!Y6*'Fund Ranking Criteria'!$C$15) | AF6: 1 | AG6: 21 | AH6: =(AF6-MIN(AF$6:AF$10))/(MAX(AF$6:AF$10)-MIN(X$6:X$12)) | AI6: =(AG6-MIN(AG$6:AG$10))/(MAX(AG$6:AG$10)-MIN(Y$6:Y$12))
B7: HDFC Large Cap Fund - Regular Plan | C7: =RANK(Z7,$Z$6:$Z$12,0) | D7: =B7 | E7: =VLOOKUP($B7, Sheet4!$A$2:$L$688, 'Fund Ranking_Equity (2)'!E$2,FALSE) | F7: =VLOOKUP($B7, Sheet4!$A$2:$L$688, 'Fund Ranking_Equity (2)'!F$2,FALSE) | G7: =VLOOKUP($B7, Sheet4!$A$2:$L$688, 'Fund Ranking_Equity (2)'!G$2,FALSE) | H7: =VLOOKUP($B7, Sheet4!$A$2:$L$688, 'Fund Ranking_Equity (2)'!H$2,FALSE) | I7: =VLOOKUP($B7, Sheet4!$A$2:$L$688, 'Fund Ranking_Equity (2)'!I$2,FALSE) | J7: =VLOOKUP($B7, Sheet4!$A$2:$L$688, 'Fund Ranking_Equity (2)'!J$2,FALSE) | K7: =VLOOKUP($B7, Sheet4!$A$2:$L$688, 'Fund Ranking_Equity (2)'!K$2,FALSE) | L7: =VLOOKUP($B7, Sheet4!$A$2:$L$688, 'Fund Ranking_Equity (2)'!L$2,FALSE) | ... O7: =VLOOKUP($B7, Sheet4!$A$2:$L$688, 'Fund Ranking_Equity (2)'!O$2,FALSE) | P7: =(F7-MIN(F$6:F$12))/(MAX(F$6:F$12)-MIN(F$6:F$12)) | Q7: =(G7-MIN(G$6:G$12))/(MAX(G$6:G$12)-MIN(G$6:G$12)) | R7: =(H7-MIN(H$6:H$12))/(MAX(H$6:H$12)-MIN(H$6:H$12)) | S7: =(I7-MIN(I$6:I$12))/(MAX(I$6:I$12)-MIN(I$6:I$12)) | T7: =(J7-MIN(J$6:J$12))/(MAX(J$6:J$12)-MIN(J$6:J$12)) | U7: =(K7-MIN(K$6:K$12))/(MAX(K$6:K$12)-MIN(K$6:K$12)) | V7: =(MAX(L$6:L$12)-L7)/(MAX(L$6:L$12)-MIN(L$6:L$12)) | W7: =(MAX(M$6:M$12)-M7)/(MAX(M$6:M$12)-MIN(M$6:M$12)) | X7: =(MAX(N$6:N$12)-N7)/(MAX(N$6:N$12)-MIN(N$6:N$12)) | Y7: =(MAX(O$6:O$12)-O7)/(MAX(O$6:O$12)-MIN(O$6:O$12)) | Z7: =(P7*'Fund Ranking Criteria'!$C$9)+('Fund Ranking_Equity (2)'!Q7*'Fund Ranking Criteria'!$C$10)+('Fund Ranking_Equity (2)'!R7*'Fund Ranking Criteria'!$C$11)+('Fund Ranking_Equity (2)'!S7*'Fund Ranking Criteria'!$C$16)+('Fund Ranking_Equity (2)'!T7*'Fund Ranking Criteria'!#REF!)+('Fund Ranking_Equity (2)'!U7*'Fund Ranking Criteria'!$C$12)+('Fund Ranking_Equity (2)'!V7*'Fund Ranking Criteria'!#REF!)+('Fund Ranking_Equity (2)'!W7*'Fund Ranking Criteria'!#REF!)+('Fund Ranking_Equity (2)'!X7*'Fund Ranking Criteria'!$C$14)+('Fund Ranking_Equity (2)'!Y7*'Fund Ranking Criteria'!$C$15) | AF7: 2 | AG7: 22 | AH7: =(AF7-MIN(AF$6:AF$10))/(MAX(AF$6:AF$10)-MIN(X$6:X$12)) | AI7: =(AG7-MIN(AG$6:AG$10))/(MAX(AG$6:AG$10)-MIN(Y$6:Y$12))
B8: ICICI Prudential Large Cap Fund | C8: =RANK(Z8,$Z$6:$Z$12,0) | D8: =B8 | E8: =VLOOKUP($B8, Sheet4!$A$2:$L$688, 'Fund Ranking_Equity (2)'!E$2,FALSE) | F8: =VLOOKUP($B8, Sheet4!$A$2:$L$688, 'Fund Ranking_Equity (2)'!F$2,FALSE) | G8: =VLOOKUP($B8, Sheet4!$A$2:$L$688, 'Fund Ranking_Equity (2)'!G$2,FALSE) | H8: =VLOOKUP($B8, Sheet4!$A$2:$L$688, 'Fund Ranking_Equity (2)'!H$2,FALSE) | I8: =VLOOKUP($B8, Sheet4!$A$2:$L$688, 'Fund Ranking_Equity (2)'!I$2,FALSE) | J8: =VLOOKUP($B8, Sheet4!$A$2:$L$688, 'Fund Ranking_Equity (2)'!J$2,FALSE) | K8: =VLOOKUP($B8, Sheet4!$A$2:$L$688, 'Fund Ranking_Equity (2)'!K$2,FALSE) | L8: =VLOOKUP($B8, Sheet4!$A$2:$L$688, 'Fund Ranking_Equity (2)'!L$2,FALSE) | ... O8: =VLOOKUP($B8, Sheet4!$A$2:$L$688, 'Fund Ranking_Equity (2)'!O$2,FALSE) | P8: =(F8-MIN(F$6:F$12))/(MAX(F$6:F$12)-MIN(F$6:F$12)) | Q8: =(G8-MIN(G$6:G$12))/(MAX(G$6:G$12)-MIN(G$6:G$12)) | R8: =(H8-MIN(H$6:H$12))/(MAX(H$6:H$12)-MIN(H$6:H$12)) | S8: =(I8-MIN(I$6:I$12))/(MAX(I$6:I$12)-MIN(I$6:I$12)) | T8: =(J8-MIN(J$6:J$12))/(MAX(J$6:J$12)-MIN(J$6:J$12)) | U8: =(K8-MIN(K$6:K$12))/(MAX(K$6:K$12)-MIN(K$6:K$12)) | V8: =(MAX(L$6:L$12)-L8)/(MAX(L$6:L$12)-MIN(L$6:L$12)) | W8: =(MAX(M$6:M$12)-M8)/(MAX(M$6:M$12)-MIN(M$6:M$12)) | X8: =(MAX(N$6:N$12)-N8)/(MAX(N$6:N$12)-MIN(N$6:N$12)) | Y8: =(MAX(O$6:O$12)-O8)/(MAX(O$6:O$12)-MIN(O$6:O$12)) | Z8: =(P8*'Fund Ranking Criteria'!$C$9)+('Fund Ranking_Equity (2)'!Q8*'Fund Ranking Criteria'!$C$10)+('Fund Ranking_Equity (2)'!R8*'Fund Ranking Criteria'!$C$11)+('Fund Ranking_Equity (2)'!S8*'Fund Ranking Criteria'!$C$16)+('Fund Ranking_Equity (2)'!T8*'Fund Ranking Criteria'!#REF!)+('Fund Ranking_Equity (2)'!U8*'Fund Ranking Criteria'!$C$12)+('Fund Ranking_Equity (2)'!V8*'Fund Ranking Criteria'!#REF!)+('Fund Ranking_Equity (2)'!W8*'Fund Ranking Criteria'!#REF!)+('Fund Ranking_Equity (2)'!X8*'Fund Ranking Criteria'!$C$14)+('Fund Ranking_Equity (2)'!Y8*'Fund Ranking Criteria'!$C$15) | AF8: 3 | AG8: 23 | AH8: =(AF8-MIN(AF$6:AF$10))/(MAX(AF$6:AF$10)-MIN(X$6:X$12)) | AI8: =(AG8-MIN(AG$6:AG$10))/(MAX(AG$6:AG$10)-MIN(Y$6:Y$12))
B9: Kotak Bluechip Fund - Regular Plan | C9: =RANK(Z9,$Z$6:$Z$12,0) | D9: =B9 | E9: =VLOOKUP($B9, Sheet4!$A$2:$L$688, 'Fund Ranking_Equity (2)'!E$2,FALSE) | F9: =VLOOKUP($B9, Sheet4!$A$2:$L$688, 'Fund Ranking_Equity (2)'!F$2,FALSE) | G9: =VLOOKUP($B9, Sheet4!$A$2:$L$688, 'Fund Ranking_Equity (2)'!G$2,FALSE) | H9: =VLOOKUP($B9, Sheet4!$A$2:$L$688, 'Fund Ranking_Equity (2)'!H$2,FALSE) | I9: =VLOOKUP($B9, Sheet4!$A$2:$L$688, 'Fund Ranking_Equity (2)'!I$2,FALSE) | J9: =VLOOKUP($B9, Sheet4!$A$2:$L$688, 'Fund Ranking_Equity (2)'!J$2,FALSE) | K9: =VLOOKUP($B9, Sheet4!$A$2:$L$688, 'Fund Ranking_Equity (2)'!K$2,FALSE) | L9: =VLOOKUP($B9, Sheet4!$A$2:$L$688, 'Fund Ranking_Equity (2)'!L$2,FALSE) | ... O9: =VLOOKUP($B9, Sheet4!$A$2:$L$688, 'Fund Ranking_Equity (2)'!O$2,FALSE) | P9: =(F9-MIN(F$6:F$12))/(MAX(F$6:F$12)-MIN(F$6:F$12)) | Q9: =(G9-MIN(G$6:G$12))/(MAX(G$6:G$12)-MIN(G$6:G$12)) | R9: =(H9-MIN(H$6:H$12))/(MAX(H$6:H$12)-MIN(H$6:H$12)) | S9: =(I9-MIN(I$6:I$12))/(MAX(I$6:I$12)-MIN(I$6:I$12)) | T9: =(J9-MIN(J$6:J$12))/(MAX(J$6:J$12)-MIN(J$6:J$12)) | U9: =(K9-MIN(K$6:K$12))/(MAX(K$6:K$12)-MIN(K$6:K$12)) | V9: =(MAX(L$6:L$12)-L9)/(MAX(L$6:L$12)-MIN(L$6:L$12)) | W9: =(MAX(M$6:M$12)-M9)/(MAX(M$6:M$12)-MIN(M$6:M$12)) | X9: =(MAX(N$6:N$12)-N9)/(MAX(N$6:N$12)-MIN(N$6:N$12)) | Y9: =(MAX(O$6:O$12)-O9)/(MAX(O$6:O$12)-MIN(O$6:O$12)) | Z9: =(P9*'Fund Ranking Criteria'!$C$9)+('Fund Ranking_Equity (2)'!Q9*'Fund Ranking Criteria'!$C$10)+('Fund Ranking_Equity (2)'!R9*'Fund Ranking Criteria'!$C$11)+('Fund Ranking_Equity (2)'!S9*'Fund Ranking Criteria'!$C$16)+('Fund Ranking_Equity (2)'!T9*'Fund Ranking Criteria'!#REF!)+('Fund Ranking_Equity (2)'!U9*'Fund Ranking Criteria'!$C$12)+('Fund Ranking_Equity (2)'!V9*'Fund Ranking Criteria'!#REF!)+('Fund Ranking_Equity (2)'!W9*'Fund Ranking Criteria'!#REF!)+('Fund Ranking_Equity (2)'!X9*'Fund Ranking Criteria'!$C$14)+('Fund Ranking_Equity (2)'!Y9*'Fund Ranking Criteria'!$C$15) | AF9: 4 | AG9: 24 | AH9: =(AF9-MIN(AF$6:AF$10))/(MAX(AF$6:AF$10)-MIN(X$6:X$12)) | AI9: =(AG9-MIN(AG$6:AG$10))/(MAX(AG$6:AG$10)-MIN(Y$6:Y$12))
B10: Nippon India Large Cap Fund | C10: =RANK(Z10,$Z$6:$Z$12,0) | D10: =B10 | E10: =VLOOKUP($B10, Sheet4!$A$2:$L$688, 'Fund Ranking_Equity (2)'!E$2,FALSE) | F10: =VLOOKUP($B10, Sheet4!$A$2:$L$688, 'Fund Ranking_Equity (2)'!F$2,FALSE) | G10: =VLOOKUP($B10, Sheet4!$A$2:$L$688, 'Fund Ranking_Equity (2)'!G$2,FALSE) | H10: =VLOOKUP($B10, Sheet4!$A$2:$L$688, 'Fund Ranking_Equity (2)'!H$2,FALSE) | I10: =VLOOKUP($B10, Sheet4!$A$2:$L$688, 'Fund Ranking_Equity (2)'!I$2,FALSE) | J10: =VLOOKUP($B10, Sheet4!$A$2:$L$688, 'Fund Ranking_Equity (2)'!J$2,FALSE) | K10: =VLOOKUP($B10, Sheet4!$A$2:$L$688, 'Fund Ranking_Equity (2)'!K$2,FALSE) | L10: =VLOOKUP($B10, Sheet4!$A$2:$L$688, 'Fund Ranking_Equity (2)'!L$2,FALSE) | ... O10: =VLOOKUP($B10, Sheet4!$A$2:$L$688, 'Fund Ranking_Equity (2)'!O$2,FALSE) | P10: =(F10-MIN(F$6:F$12))/(MAX(F$6:F$12)-MIN(F$6:F$12)) | Q10: =(G10-MIN(G$6:G$12))/(MAX(G$6:G$12)-MIN(G$6:G$12)) | R10: =(H10-MIN(H$6:H$12))/(MAX(H$6:H$12)-MIN(H$6:H$12)) | S10: =(I10-MIN(I$6:I$12))/(MAX(I$6:I$12)-MIN(I$6:I$12)) | T10: =(J10-MIN(J$6:J$12))/(MAX(J$6:J$12)-MIN(J$6:J$12)) | U10: =(K10-MIN(K$6:K$12))/(MAX(K$6:K$12)-MIN(K$6:K$12)) | V10: =(MAX(L$6:L$12)-L10)/(MAX(L$6:L$12)-MIN(L$6:L$12)) | W10: =(MAX(M$6:M$12)-M10)/(MAX(M$6:M$12)-MIN(M$6:M$12)) | X10: =(MAX(N$6:N$12)-N10)/(MAX(N$6:N$12)-MIN(N$6:N$12)) | Y10: =(MAX(O$6:O$12)-O10)/(MAX(O$6:O$12)-MIN(O$6:O$12)) | Z10: =(P10*'Fund Ranking Criteria'!$C$9)+('Fund Ranking_Equity (2)'!Q10*'Fund Ranking Criteria'!$C$10)+('Fund Ranking_Equity (2)'!R10*'Fund Ranking Criteria'!$C$11)+('Fund Ranking_Equity (2)'!S10*'Fund Ranking Criteria'!$C$16)+('Fund Ranking_Equity (2)'!T10*'Fund Ranking Criteria'!#REF!)+('Fund Ranking_Equity (2)'!U10*'Fund Ranking Criteria'!$C$12)+('Fund Ranking_Equity (2)'!V10*'Fund Ranking Criteria'!#REF!)+('Fund Ranking_Equity (2)'!W10*'Fund Ranking Criteria'!#REF!)+('Fund Ranking_Equity (2)'!X10*'Fund Ranking Criteria'!$C$14)+('Fund Ranking_Equity (2)'!Y10*'Fund Ranking Criteria'!$C$15) | AF10: 5 | AG10: 25 | AH10: =(AF10-MIN(AF$6:AF$10))/(MAX(AF$6:AF$10)-MIN(X$6:X$12)) | AI10: =(AG10-MIN(AG$6:AG$10))/(MAX(AG$6:AG$10)-MIN(Y$6:Y$12))
B11: SBI Bluechip Fund | C11: =RANK(Z11,$Z$6:$Z$12,0) | D11: =B11 | E11: =VLOOKUP($B11, Sheet4!$A$2:$L$688, 'Fund Ranking_Equity (2)'!E$2,FALSE) | F11: =VLOOKUP($B11, Sheet4!$A$2:$L$688, 'Fund Ranking_Equity (2)'!F$2,FALSE) | G11: =VLOOKUP($B11, Sheet4!$A$2:$L$688, 'Fund Ranking_Equity (2)'!G$2,FALSE) | H11: =VLOOKUP($B11, Sheet4!$A$2:$L$688, 'Fund Ranking_Equity (2)'!H$2,FALSE) | I11: =VLOOKUP($B11, Sheet4!$A$2:$L$688, 'Fund Ranking_Equity (2)'!I$2,FALSE) | J11: =VLOOKUP($B11, Sheet4!$A$2:$L$688, 'Fund Ranking_Equity (2)'!J$2,FALSE) | K11: =VLOOKUP($B11, Sheet4!$A$2:$L$688, 'Fund Ranking_Equity (2)'!K$2,FALSE) | L11: =VLOOKUP($B11, Sheet4!$A$2:$L$688, 'Fund Ranking_Equity (2)'!L$2,FALSE) | ... O11: =VLOOKUP($B11, Sheet4!$A$2:$L$688, 'Fund Ranking_Equity (2)'!O$2,FALSE) | P11: =(F11-MIN(F$6:F$12))/(MAX(F$6:F$12)-MIN(F$6:F$12)) | Q11: =(G11-MIN(G$6:G$12))/(MAX(G$6:G$12)-MIN(G$6:G$12)) | R11: =(H11-MIN(H$6:H$12))/(MAX(H$6:H$12)-MIN(H$6:H$12)) | S11: =(I11-MIN(I$6:I$12))/(MAX(I$6:I$12)-MIN(I$6:I$12)) | T11: =(J11-MIN(J$6:J$12))/(MAX(J$6:J$12)-MIN(J$6:J$12)) | U11: =(K11-MIN(K$6:K$12))/(MAX(K$6:K$12)-MIN(K$6:K$12)) | V11: =(MAX(L$6:L$12)-L11)/(MAX(L$6:L$12)-MIN(L$6:L$12)) | W11: =(MAX(M$6:M$12)-M11)/(MAX(M$6:M$12)-MIN(M$6:M$12)) | X11: =(MAX(N$6:N$12)-N11)/(MAX(N$6:N$12)-MIN(N$6:N$12)) | Y11: =(MAX(O$6:O$12)-O11)/(MAX(O$6:O$12)-MIN(O$6:O$12)) | Z11: =(P11*'Fund Ranking Criteria'!$C$9)+('Fund Ranking_Equity (2)'!Q11*'Fund Ranking Criteria'!$C$10)+('Fund Ranking_Equity (2)'!R11*'Fund Ranking Criteria'!$C$11)+('Fund Ranking_Equity (2)'!S11*'Fund Ranking Criteria'!$C$16)+('Fund Ranking_Equity (2)'!T11*'Fund Ranking Criteria'!#REF!)+('Fund Ranking_Equity (2)'!U11*'Fund Ranking Criteria'!$C$12)+('Fund Ranking_Equity (2)'!V11*'Fund Ranking Criteria'!#REF!)+('Fund Ranking_Equity (2)'!W11*'Fund Ranking Criteria'!#REF!)+('Fund Ranking_Equity (2)'!X11*'Fund Ranking Criteria'!$C$14)+('Fund Ranking_Equity (2)'!Y11*'Fund Ranking Criteria'!$C$15)
B12: UTI Large Cap Fund - Regular Plan | C12: =RANK(Z12,$Z$6:$Z$12,0) | D12: =B12 | E12: =VLOOKUP($B12, Sheet4!$A$2:$L$688, 'Fund Ranking_Equity (2)'!E$2,FALSE) | F12: =VLOOKUP($B12, Sheet4!$A$2:$L$688, 'Fund Ranking_Equity (2)'!F$2,FALSE) | G12: =VLOOKUP($B12, Sheet4!$A$2:$L$688, 'Fund Ranking_Equity (2)'!G$2,FALSE) | H12: =VLOOKUP($B12, Sheet4!$A$2:$L$688, 'Fund Ranking_Equity (2)'!H$2,FALSE) | I12: =VLOOKUP($B12, Sheet4!$A$2:$L$688, 'Fund Ranking_Equity (2)'!I$2,FALSE) | J12: =VLOOKUP($B12, Sheet4!$A$2:$L$688, 'Fund Ranking_Equity (2)'!J$2,FALSE) | K12: =VLOOKUP($B12, Sheet4!$A$2:$L$688, 'Fund Ranking_Equity (2)'!K$2,FALSE) | L12: =VLOOKUP($B12, Sheet4!$A$2:$L$688, 'Fund Ranking_Equity (2)'!L$2,FALSE) | ... O12: =VLOOKUP($B12, Sheet4!$A$2:$L$688, 'Fund Ranking_Equity (2)'!O$2,FALSE) | P12: =(F12-MIN(F$6:F$12))/(MAX(F$6:F$12)-MIN(F$6:F$12)) | Q12: =(G12-MIN(G$6:G$12))/(MAX(G$6:G$12)-MIN(G$6:G$12)) | R12: =(H12-MIN(H$6:H$12))/(MAX(H$6:H$12)-MIN(H$6:H$12)) | S12: =(I12-MIN(I$6:I$12))/(MAX(I$6:I$12)-MIN(I$6:I$12)) | T12: =(J12-MIN(J$6:J$12))/(MAX(J$6:J$12)-MIN(J$6:J$12)) | U12: =(K12-MIN(K$6:K$12))/(MAX(K$6:K$12)-MIN(K$6:K$12)) | V12: =(MAX(L$6:L$12)-L12)/(MAX(L$6:L$12)-MIN(L$6:L$12)) | W12: =(MAX(M$6:M$12)-M12)/(MAX(M$6:M$12)-MIN(M$6:M$12)) | X12: =(MAX(N$6:N$12)-N12)/(MAX(N$6:N$12)-MIN(N$6:N$12)) | Y12: =(MAX(O$6:O$12)-O12)/(MAX(O$6:O$12)-MIN(O$6:O$12)) | Z12: =(P12*'Fund Ranking Criteria'!$C$9)+('Fund Ranking_Equity (2)'!Q12*'Fund Ranking Criteria'!$C$10)+('Fund Ranking_Equity (2)'!R12*'Fund Ranking Criteria'!$C$11)+('Fund Ranking_Equity (2)'!S12*'Fund Ranking Criteria'!$C$16)+('Fund Ranking_Equity (2)'!T12*'Fund Ranking Criteria'!#REF!)+('Fund Ranking_Equity (2)'!U12*'Fund Ranking Criteria'!$C$12)+('Fund Ranking_Equity (2)'!V12*'Fund Ranking Criteria'!#REF!)+('Fund Ranking_Equity (2)'!W12*'Fund Ranking Criteria'!#REF!)+('Fund Ranking_Equity (2)'!X12*'Fund Ranking Criteria'!$C$14)+('Fund Ranking_Equity (2)'!Y12*'Fund Ranking Criteria'!$C$15)

Sheet Fund Ranking_Equity (3)
B1: (Match with morningstar)
B2: Model Portfolio | E2: 2 | F2: =E2+1 | G2: =F2+1 | H2: =G2+1 | I2: =H2+1 | J2: =I2+1 | K2: =J2+1 | L2: =K2+1 | M2: =L2+1 | ... O2: =N2+1
B4: Equity Large & Mid Cap
E5: Actuals | P5: Normalized | Z5: Score
B6: Funds | C6: Rank | E6: 1 Yr Ret (%) | F6: 3 Yr Ret (%) | G6: 5 Yr Ret (%) | H6: 10 Yr Ret (%) | I6: Sharpe | J6: Sortino | K6: Alpha | L6: Expense Ratio | M6: Turnover Ratio | N6: Beta | O6: SD | P6: =F6 | Q6: =G6 | R6: =H6 | S6: Sharpe | T6: Sortino | U6: Alpha | V6: Expense Ratio | W6: Turnover Ratio | X6: Beta | Y6: SD
B7: Aditya Birla Sun Life Large & Mid Cap Fund - Regular Plan | C7: =RANK(Z7,$Z$7:$Z$13,0) | D7: =B7 | E7: =VLOOKUP($B7, Sheet4!$A$2:$L$688, 'Fund Ranking_Equity (3)'!E$2,FALSE) | F7: =VLOOKUP($B7, Sheet4!$A$2:$L$688, 'Fund Ranking_Equity (3)'!F$2,FALSE) | G7: =VLOOKUP($B7, Sheet4!$A$2:$L$688, 'Fund Ranking_Equity (3)'!G$2,FALSE) | H7: =VLOOKUP($B7, Sheet4!$A$2:$L$688, 'Fund Ranking_Equity (3)'!H$2,FALSE) | I7: =VLOOKUP($B7, Sheet4!$A$2:$L$688, 'Fund Ranking_Equity (3)'!I$2,FALSE) | J7: =VLOOKUP($B7, Sheet4!$A$2:$L$688, 'Fund Ranking_Equity (3)'!J$2,FALSE) | K7: =VLOOKUP($B7, Sheet4!$A$2:$L$688, 'Fund Ranking_Equity (3)'!K$2,FALSE) | L7: =VLOOKUP($B7, Sheet4!$A$2:$L$688, 'Fund Ranking_Equity (3)'!L$2,FALSE) | ... O7: =VLOOKUP($B7, Sheet4!$A$2:$L$688, 'Fund Ranking_Equity (3)'!O$2,FALSE) | P7: =(F7-MIN(F$7:F$13))/(MAX(F$7:F$13)-MIN(F$7:F$13)) | Q7: =(G7-MIN(G$7:G$13))/(MAX(G$7:G$13)-MIN(G$7:G$13)) | R7: =(H7-MIN(H$7:H$13))/(MAX(H$7:H$13)-MIN(H$7:H$13)) | S7: =(I7-MIN(I$7:I$13))/(MAX(I$7:I$13)-MIN(I$7:I$13)) | T7: =(J7-MIN(J$7:J$13))/(MAX(J$7:J$13)-MIN(J$7:J$13)) | U7: =(K7-MIN(K$7:K$13))/(MAX(K$7:K$13)-MIN(K$7:K$13)) | V7: =(MAX(L$7:L$13)-L7)/(MAX(L$7:L$13)-MIN(L$7:L$13)) | W7: =(MAX(M$7:M$13)-M7)/(MAX(M$7:M$13)-MIN(M$7:M$13)) | X7: =(MAX(N$7:N$13)-N7)/(MAX(N$7:N$13)-MIN(N$7:N$13)) | Y7: =(MAX(O$7:O$13)-O7)/(MAX(O$7:O$13)-MIN(O$7:O$13)) | Z7: =(P7*'Fund Ranking Criteria'!$D$9)+('Fund Ranking_Equity (3)'!Q7*'Fund Ranking Criteria'!$D$10)+('Fund Ranking_Equity (3)'!R7*'Fund Ranking Criteria'!$D$11)+('Fund Ranking_Equity (3)'!S7*'Fund Ranking Criteria'!$D$16)+('Fund Ranking_Equity (3)'!T7*'Fund Ranking Criteria'!#REF!)+('Fund Ranking_Equity (3)'!U7*'Fund Ranking Criteria'!$D$12)+('Fund Ranking_Equity (3)'!V7*'Fund Ranking Criteria'!#REF!)+('Fund Ranking_Equity (3)'!W7*'Fund Ranking Criteria'!#REF!)+('Fund Ranking_Equity (3)'!X7*'Fund Ranking Criteria'!$D$14)+('Fund Ranking_Equity (3)'!Y7*'Fund Ranking Criteria'!$D$15)
B8: HDFC Large and Mid Cap Fund - Regular Plan | C8: =RANK(Z8,$Z$7:$Z$13,0) | D8: =B8 | E8: =VLOOKUP($B8, Sheet4!$A$2:$L$688, 'Fund Ranking_Equity (3)'!E$2,FALSE) | F8: =VLOOKUP($B8, Sheet4!$A$2:$L$688, 'Fund Ranking_Equity (3)'!F$2,FALSE) | G8: =VLOOKUP($B8, Sheet4!$A$2:$L$688, 'Fund Ranking_Equity (3)'!G$2,FALSE) | H8: =VLOOKUP($B8, Sheet4!$A$2:$L$688, 'Fund Ranking_Equity (3)'!H$2,FALSE) | I8: =VLOOKUP($B8, Sheet4!$A$2:$L$688, 'Fund Ranking_Equity (3)'!I$2,FALSE) | J8: =VLOOKUP($B8, Sheet4!$A$2:$L$688, 'Fund Ranking_Equity (3)'!J$2,FALSE) | K8: =VLOOKUP($B8, Sheet4!$A$2:$L$688, 'Fund Ranking_Equity (3)'!K$2,FALSE) | L8: =VLOOKUP($B8, Sheet4!$A$2:$L$688, 'Fund Ranking_Equity (3)'!L$2,FALSE) | ... O8: =VLOOKUP($B8, Sheet4!$A$2:$L$688, 'Fund Ranking_Equity (3)'!O$2,FALSE) | P8: =(F8-MIN(F$7:F$13))/(MAX(F$7:F$13)-MIN(F$7:F$13)) | Q8: =(G8-MIN(G$7:G$13))/(MAX(G$7:G$13)-MIN(G$7:G$13)) | R8: =(H8-MIN(H$7:H$13))/(MAX(H$7:H$13)-MIN(H$7:H$13)) | S8: =(I8-MIN(I$7:I$13))/(MAX(I$7:I$13)-MIN(I$7:I$13)) | T8: =(J8-MIN(J$7:J$13))/(MAX(J$7:J$13)-MIN(J$7:J$13)) | U8: =(K8-MIN(K$7:K$13))/(MAX(K$7:K$13)-MIN(K$7:K$13)) | V8: =(MAX(L$7:L$13)-L8)/(MAX(L$7:L$13)-MIN(L$7:L$13)) | W8: =(MAX(M$7:M$13)-M8)/(MAX(M$7:M$13)-MIN(M$7:M$13)) | X8: =(MAX(N$7:N$13)-N8)/(MAX(N$7:N$13)-MIN(N$7:N$13)) | Y8: =(MAX(O$7:O$13)-O8)/(MAX(O$7:O$13)-MIN(O$7:O$13)) | Z8: =(P8*'Fund Ranking Criteria'!$D$9)+('Fund Ranking_Equity (3)'!Q8*'Fund Ranking Criteria'!$D$10)+('Fund Ranking_Equity (3)'!R8*'Fund Ranking Criteria'!$D$11)+('Fund Ranking_Equity (3)'!S8*'Fund Ranking Criteria'!$D$16)+('Fund Ranking_Equity (3)'!T8*'Fund Ranking Criteria'!#REF!)+('Fund Ranking_Equity (3)'!U8*'Fund Ranking Criteria'!$D$12)+('Fund Ranking_Equity (3)'!V8*'Fund Ranking Criteria'!#REF!)+('Fund Ranking_Equity (3)'!W8*'Fund Ranking Criteria'!#REF!)+('Fund Ranking_Equity (3)'!X8*'Fund Ranking Criteria'!$D$14)+('Fund Ranking_Equity (3)'!Y8*'Fund Ranking Criteria'!$D$15)
B9: ICICI Prudential Large & Mid Cap Fund | C9: =RANK(Z9,$Z$7:$Z$13,0) | D9: =B9 | E9: =VLOOKUP($B9, Sheet4!$A$2:$L$688, 'Fund Ranking_Equity (3)'!E$2,FALSE) | F9: =VLOOKUP($B9, Sheet4!$A$2:$L$688, 'Fund Ranking_Equity (3)'!F$2,FALSE) | G9: =VLOOKUP($B9, Sheet4!$A$2:$L$688, 'Fund Ranking_Equity (3)'!G$2,FALSE) | H9: =VLOOKUP($B9, Sheet4!$A$2:$L$688, 'Fund Ranking_Equity (3)'!H$2,FALSE) | I9: =VLOOKUP($B9, Sheet4!$A$2:$L$688, 'Fund Ranking_Equity (3)'!I$2,FALSE) | J9: =VLOOKUP($B9, Sheet4!$A$2:$L$688, 'Fund Ranking_Equity (3)'!J$2,FALSE) | K9: =VLOOKUP($B9, Sheet4!$A$2:$L$688, 'Fund Ranking_Equity (3)'!K$2,FALSE) | L9: =VLOOKUP($B9, Sheet4!$A$2:$L$688, 'Fund Ranking_Equity (3)'!L$2,FALSE) | ... O9: =VLOOKUP($B9, Sheet4!$A$2:$L$688, 'Fund Ranking_Equity (3)'!O$2,FALSE) | P9: =(F9-MIN(F$7:F$13))/(MAX(F$7:F$13)-MIN(F$7:F$13)) | Q9: =(G9-MIN(G$7:G$13))/(MAX(G$7:G$13)-MIN(G$7:G$13)) | R9: =(H9-MIN(H$7:H$13))/(MAX(H$7:H$13)-MIN(H$7:H$13)) | S9: =(I9-MIN(I$7:I$13))/(MAX(I$7:I$13)-MIN(I$7:I$13)) | T9: =(J9-MIN(J$7:J$13))/(MAX(J$7:J$13)-MIN(J$7:J$13)) | U9: =(K9-MIN(K$7:K$13))/(MAX(K$7:K$13)-MIN(K$7:K$13)) | V9: =(MAX(L$7:L$13)-L9)/(MAX(L$7:L$13)-MIN(L$7:L$13)) | W9: =(MAX(M$7:M$13)-M9)/(MAX(M$7:M$13)-MIN(M$7:M$13)) | X9: =(MAX(N$7:N$13)-N9)/(MAX(N$7:N$13)-MIN(N$7:N$13)) | Y9: =(MAX(O$7:O$13)-O9)/(MAX(O$7:O$13)-MIN(O$7:O$13)) | Z9: =(P9*'Fund Ranking Criteria'!$D$9)+('Fund Ranking_Equity (3)'!Q9*'Fund Ranking Criteria'!$D$10)+('Fund Ranking_Equity (3)'!R9*'Fund Ranking Criteria'!$D$11)+('Fund Ranking_Equity (3)'!S9*'Fund Ranking Criteria'!$D$16)+('Fund Ranking_Equity (3)'!T9*'Fund Ranking Criteria'!#REF!)+('Fund Ranking_Equity (3)'!U9*'Fund Ranking Criteria'!$D$12)+('Fund Ranking_Equity (3)'!V9*'Fund Ranking Criteria'!#REF!)+('Fund Ranking_Equity (3)'!W9*'Fund Ranking Criteria'!#REF!)+('Fund Ranking_Equity (3)'!X9*'Fund Ranking Criteria'!$D$14)+('Fund Ranking_Equity (3)'!Y9*'Fund Ranking Criteria'!$D$15)
B10: Kotak Equity Opportunities Fund - Regular Plan | C10: =RANK(Z10,$Z$7:$Z$13,0) | D10: =B10 | E10: =VLOOKUP($B10, Sheet4!$A$2:$L$688, 'Fund Ranking_Equity (3)'!E$2,FALSE) | F10: =VLOOKUP($B10, Sheet4!$A$2:$L$688, 'Fund Ranking_Equity (3)'!F$2,FALSE) | G10: =VLOOKUP($B10, Sheet4!$A$2:$L$688, 'Fund Ranking_Equity (3)'!G$2,FALSE) | H10: =VLOOKUP($B10, Sheet4!$A$2:$L$688, 'Fund Ranking_Equity (3)'!H$2,FALSE) | I10: =VLOOKUP($B10, Sheet4!$A$2:$L$688, 'Fund Ranking_Equity (3)'!I$2,FALSE) | J10: =VLOOKUP($B10, Sheet4!$A$2:$L$688, 'Fund Ranking_Equity (3)'!J$2,FALSE) | K10: =VLOOKUP($B10, Sheet4!$A$2:$L$688, 'Fund Ranking_Equity (3)'!K$2,FALSE) | L10: =VLOOKUP($B10, Sheet4!$A$2:$L$688, 'Fund Ranking_Equity (3)'!L$2,FALSE) | ... O10: =VLOOKUP($B10, Sheet4!$A$2:$L$688, 'Fund Ranking_Equity (3)'!O$2,FALSE) | P10: =(F10-MIN(F$7:F$13))/(MAX(F$7:F$13)-MIN(F$7:F$13)) | Q10: =(G10-MIN(G$7:G$13))/(MAX(G$7:G$13)-MIN(G$7:G$13)) | R10: =(H10-MIN(H$7:H$13))/(MAX(H$7:H$13)-MIN(H$7:H$13)) | S10: =(I10-MIN(I$7:I$13))/(MAX(I$7:I$13)-MIN(I$7:I$13)) | T10: =(J10-MIN(J$7:J$13))/(MAX(J$7:J$13)-MIN(J$7:J$13)) | U10: =(K10-MIN(K$7:K$13))/(MAX(K$7:K$13)-MIN(K$7:K$13)) | V10: =(MAX(L$7:L$13)-L10)/(MAX(L$7:L$13)-MIN(L$7:L$13)) | W10: =(MAX(M$7:M$13)-M10)/(MAX(M$7:M$13)-MIN(M$7:M$13)) | X10: =(MAX(N$7:N$13)-N10)/(MAX(N$7:N$13)-MIN(N$7:N$13)) | Y10: =(MAX(O$7:O$13)-O10)/(MAX(O$7:O$13)-MIN(O$7:O$13)) | Z10: =(P10*'Fund Ranking Criteria'!$D$9)+('Fund Ranking_Equity (3)'!Q10*'Fund Ranking Criteria'!$D$10)+('Fund Ranking_Equity (3)'!R10*'Fund Ranking Criteria'!$D$11)+('Fund Ranking_Equity (3)'!S10*'Fund Ranking Criteria'!$D$16)+('Fund Ranking_Equity (3)'!T10*'Fund Ranking Criteria'!#REF!)+('Fund Ranking_Equity (3)'!U10*'Fund Ranking Criteria'!$D$12)+('Fund Ranking_Equity (3)'!V10*'Fund Ranking Criteria'!#REF!)+('Fund Ranking_Equity (3)'!W10*'Fund Ranking Criteria'!#REF!)+('Fund Ranking_Equity (3)'!X10*'Fund Ranking Criteria'!$D$14)+('Fund Ranking_Equity (3)'!Y10*'Fund Ranking Criteria'!$D$15)
B11: Nippon India Vision Fund | C11: =RANK(Z11,$Z$7:$Z$13,0) | D11: =B11 | E11: =VLOOKUP($B11, Sheet4!$A$2:$L$688, 'Fund Ranking_Equity (3)'!E$2,FALSE) | F11: =VLOOKUP($B11, Sheet4!$A$2:$L$688, 'Fund Ranking_Equity (3)'!F$2,FALSE) | G11: =VLOOKUP($B11, Sheet4!$A$2:$L$688, 'Fund Ranking_Equity (3)'!G$2,FALSE) | H11: =VLOOKUP($B11, Sheet4!$A$2:$L$688, 'Fund Ranking_Equity (3)'!H$2,FALSE) | I11: =VLOOKUP($B11, Sheet4!$A$2:$L$688, 'Fund Ranking_Equity (3)'!I$2,FALSE) | J11: =VLOOKUP($B11, Sheet4!$A$2:$L$688, 'Fund Ranking_Equity (3)'!J$2,FALSE) | K11: =VLOOKUP($B11, Sheet4!$A$2:$L$688, 'Fund Ranking_Equity (3)'!K$2,FALSE) | L11: =VLOOKUP($B11, Sheet4!$A$2:$L$688, 'Fund Ranking_Equity (3)'!L$2,FALSE) | ... O11: =VLOOKUP($B11, Sheet4!$A$2:$L$688, 'Fund Ranking_Equity (3)'!O$2,FALSE) | P11: =(F11-MIN(F$7:F$13))/(MAX(F$7:F$13)-MIN(F$7:F$13)) | Q11: =(G11-MIN(G$7:G$13))/(MAX(G$7:G$13)-MIN(G$7:G$13)) | R11: =(H11-MIN(H$7:H$13))/(MAX(H$7:H$13)-MIN(H$7:H$13)) | S11: =(I11-MIN(I$7:I$13))/(MAX(I$7:I$13)-MIN(I$7:I$13)) | T11: =(J11-MIN(J$7:J$13))/(MAX(J$7:J$13)-MIN(J$7:J$13)) | U11: =(K11-MIN(K$7:K$13))/(MAX(K$7:K$13)-MIN(K$7:K$13)) | V11: =(MAX(L$7:L$13)-L11)/(MAX(L$7:L$13)-MIN(L$7:L$13)) | W11: =(MAX(M$7:M$13)-M11)/(MAX(M$7:M$13)-MIN(M$7:M$13)) | X11: =(MAX(N$7:N$13)-N11)/(MAX(N$7:N$13)-MIN(N$7:N$13)) | Y11: =(MAX(O$7:O$13)-O11)/(MAX(O$7:O$13)-MIN(O$7:O$13)) | Z11: =(P11*'Fund Ranking Criteria'!$D$9)+('Fund Ranking_Equity (3)'!Q11*'Fund Ranking Criteria'!$D$10)+('Fund Ranking_Equity (3)'!R11*'Fund Ranking Criteria'!$D$11)+('Fund Ranking_Equity (3)'!S11*'Fund Ranking Criteria'!$D$16)+('Fund Ranking_Equity (3)'!T11*'Fund Ranking Criteria'!#REF!)+('Fund Ranking_Equity (3)'!U11*'Fund Ranking Criteria'!$D$12)+('Fund Ranking_Equity (3)'!V11*'Fund Ranking Criteria'!#REF!)+('Fund Ranking_Equity (3)'!W11*'Fund Ranking Criteria'!#REF!)+('Fund Ranking_Equity (3)'!X11*'Fund Ranking Criteria'!$D$14)+('Fund Ranking_Equity (3)'!Y11*'Fund Ranking Criteria'!$D$15)
B12: SBI Large & Midcap Fund | C12: =RANK(Z12,$Z$7:$Z$13,0) | D12: =B12 | E12: =VLOOKUP($B12, Sheet4!$A$2:$L$688, 'Fund Ranking_Equity (3)'!E$2,FALSE) | F12: =VLOOKUP($B12, Sheet4!$A$2:$L$688, 'Fund Ranking_Equity (3)'!F$2,FALSE) | G12: =VLOOKUP($B12, Sheet4!$A$2:$L$688, 'Fund Ranking_Equity (3)'!G$2,FALSE) | H12: =VLOOKUP($B12, Sheet4!$A$2:$L$688, 'Fund Ranking_Equity (3)'!H$2,FALSE) | I12: =VLOOKUP($B12, Sheet4!$A$2:$L$688, 'Fund Ranking_Equity (3)'!I$2,FALSE) | J12: =VLOOKUP($B12, Sheet4!$A$2:$L$688, 'Fund Ranking_Equity (3)'!J$2,FALSE) | K12: =VLOOKUP($B12, Sheet4!$A$2:$L$688, 'Fund Ranking_Equity (3)'!K$2,FALSE) | L12: =VLOOKUP($B12, Sheet4!$A$2:$L$688, 'Fund Ranking_Equity (3)'!L$2,FALSE) | ... O12: =VLOOKUP($B12, Sheet4!$A$2:$L$688, 'Fund Ranking_Equity (3)'!O$2,FALSE) | P12: =(F12-MIN(F$7:F$13))/(MAX(F$7:F$13)-MIN(F$7:F$13)) | Q12: =(G12-MIN(G$7:G$13))/(MAX(G$7:G$13)-MIN(G$7:G$13)) | R12: =(H12-MIN(H$7:H$13))/(MAX(H$7:H$13)-MIN(H$7:H$13)) | S12: =(I12-MIN(I$7:I$13))/(MAX(I$7:I$13)-MIN(I$7:I$13)) | T12: =(J12-MIN(J$7:J$13))/(MAX(J$7:J$13)-MIN(J$7:J$13)) | U12: =(K12-MIN(K$7:K$13))/(MAX(K$7:K$13)-MIN(K$7:K$13)) | V12: =(MAX(L$7:L$13)-L12)/(MAX(L$7:L$13)-MIN(L$7:L$13)) | W12: =(MAX(M$7:M$13)-M12)/(MAX(M$7:M$13)-MIN(M$7:M$13)) | X12: =(MAX(N$7:N$13)-N12)/(MAX(N$7:N$13)-MIN(N$7:N$13)) | Y12: =(MAX(O$7:O$13)-O12)/(MAX(O$7:O$13)-MIN(O$7:O$13)) | Z12: =(P12*'Fund Ranking Criteria'!$D$9)+('Fund Ranking_Equity (3)'!Q12*'Fund Ranking Criteria'!$D$10)+('Fund Ranking_Equity (3)'!R12*'Fund Ranking Criteria'!$D$11)+('Fund Ranking_Equity (3)'!S12*'Fund Ranking Criteria'!$D$16)+('Fund Ranking_Equity (3)'!T12*'Fund Ranking Criteria'!#REF!)+('Fund Ranking_Equity (3)'!U12*'Fund Ranking Criteria'!$D$12)+('Fund Ranking_Equity (3)'!V12*'Fund Ranking Criteria'!#REF!)+('Fund Ranking_Equity (3)'!W12*'Fund Ranking Criteria'!#REF!)+('Fund Ranking_Equity (3)'!X12*'Fund Ranking Criteria'!$D$14)+('Fund Ranking_Equity (3)'!Y12*'Fund Ranking Criteria'!$D$15)
B13: UTI Large & Mid Cap Fund - Regular Plan | C13: =RANK(Z13,$Z$7:$Z$13,0) | D13: =B13 | E13: =VLOOKUP($B13, Sheet4!$A$2:$L$688, 'Fund Ranking_Equity (3)'!E$2,FALSE) | F13: =VLOOKUP($B13, Sheet4!$A$2:$L$688, 'Fund Ranking_Equity (3)'!F$2,FALSE) | G13: =VLOOKUP($B13, Sheet4!$A$2:$L$688, 'Fund Ranking_Equity (3)'!G$2,FALSE) | H13: =VLOOKUP($B13, Sheet4!$A$2:$L$688, 'Fund Ranking_Equity (3)'!H$2,FALSE) | I13: =VLOOKUP($B13, Sheet4!$A$2:$L$688, 'Fund Ranking_Equity (3)'!I$2,FALSE) | J13: =VLOOKUP($B13, Sheet4!$A$2:$L$688, 'Fund Ranking_Equity (3)'!J$2,FALSE) | K13: =VLOOKUP($B13, Sheet4!$A$2:$L$688, 'Fund Ranking_Equity (3)'!K$2,FALSE) | L13: =VLOOKUP($B13, Sheet4!$A$2:$L$688, 'Fund Ranking_Equity (3)'!L$2,FALSE) | ... O13: =VLOOKUP($B13, Sheet4!$A$2:$L$688, 'Fund Ranking_Equity (3)'!O$2,FALSE) | P13: =(F13-MIN(F$7:F$13))/(MAX(F$7:F$13)-MIN(F$7:F$13)) | Q13: =(G13-MIN(G$7:G$13))/(MAX(G$7:G$13)-MIN(G$7:G$13)) | R13: =(H13-MIN(H$7:H$13))/(MAX(H$7:H$13)-MIN(H$7:H$13)) | S13: =(I13-MIN(I$7:I$13))/(MAX(I$7:I$13)-MIN(I$7:I$13)) | T13: =(J13-MIN(J$7:J$13))/(MAX(J$7:J$13)-MIN(J$7:J$13)) | U13: =(K13-MIN(K$7:K$13))/(MAX(K$7:K$13)-MIN(K$7:K$13)) | V13: =(MAX(L$7:L$13)-L13)/(MAX(L$7:L$13)-MIN(L$7:L$13)) | W13: =(MAX(M$7:M$13)-M13)/(MAX(M$7:M$13)-MIN(M$7:M$13)) | X13: =(MAX(N$7:N$13)-N13)/(MAX(N$7:N$13)-MIN(N$7:N$13)) | Y13: =(MAX(O$7:O$13)-O13)/(MAX(O$7:O$13)-MIN(O$7:O$13)) | Z13: =(P13*'Fund Ranking Criteria'!$D$9)+('Fund Ranking_Equity (3)'!Q13*'Fund Ranking Criteria'!$D$10)+('Fund Ranking_Equity (3)'!R13*'Fund Ranking Criteria'!$D$11)+('Fund Ranking_Equity (3)'!S13*'Fund Ranking Criteria'!$D$16)+('Fund Ranking_Equity (3)'!T13*'Fund Ranking Criteria'!#REF!)+('Fund Ranking_Equity (3)'!U13*'Fund Ranking Criteria'!$D$12)+('Fund Ranking_Equity (3)'!V13*'Fund Ranking Criteria'!#REF!)+('Fund Ranking_Equity (3)'!W13*'Fund Ranking Criteria'!#REF!)+('Fund Ranking_Equity (3)'!X13*'Fund Ranking Criteria'!$D$14)+('Fund Ranking_Equity (3)'!Y13*'Fund Ranking Criteria'!$D$15)

Sheet Sheet4
A1: Funds | B1: 1 Yr Ret (%) | C1: 3 Yr Ret (%) | D1: 5 Yr Ret (%) | E1: 10 Yr Ret (%) | F1: Sharpe Ratio | G1: Sortino Ratio | H1: Alpha | I1: Expense Ratio (%) | J1: Turnover | K1: Beta | L1: Standard Deviation
A2: 360 ONE Balanced Hybrid Fund - Regular Plan | B2: 5.81 | C2: 0 | D2: 0 | E2: 0 | F2: 0 | G2: 0 | H2: 0 | I2: 1.95 | J2: 60 | K2: 0 | L2: 0 | M2: HY-BH
A3: 360 ONE FlexiCap Fund - Regular Plan | B3: 2.96 | C3: 0 | D3: 0 | E3: 0 | F3: 0 | G3: 0 | H3: 0 | I3: 2.03 | J3: 27 | K3: 0 | L3: 0 | M3: EQ-FLX
A4: 360 ONE Focused Fund - Regular Plan | B4: 1.12 | C4: 22.27 | D4: 23.68 | E4: 15.85 | F4: 0.94 | G4: 1.58 | H4: 2.4 | I4: 1.8 | J4: 33 | K4: 0.88 | L4: 13.28 | M4: EQ-FLX
A5: 360 ONE Quant Fund - Regular Plan | B5: 6.72 | C5: 31.45 | D5: 0 | E5: 0 | F5: 1.07 | G5: 1.6 | H5: 5.59 | I5: 1.95 | J5: 112 | K5: 1.19 | L5: 18.03 | M5: EQ-THEMATIC
A6: Aditya Birla Sun Life Asset Allocator FoF - Regular Plan | B6: 9.4 | C6: 18.3 | D6: 17.87 | E6: 12.24 | F6: 1.12 | G6: 1.9 | H6: 1.95 | I6: 1.27 | J6: 0 | K6: 0.84 | L6: 8.45 | M6: HY-AR
A7: Aditya Birla Sun Life Balanced Advantage Fund - Regular Plan | B7: 9.74 | C7: 15.74 | D7: 15.19 | E7: 11.21 | F7: 0.91 | G7: 1.39 | H7: 1.17 | I7: 1.79 | J7: 302 | K7: 0.74 | L7: 7.75 | M7: HY-DAA
A8: Aditya Birla Sun Life Bal Bhavishya Yojna - Regular Plan | B8: 3.93 | C8: 18.44 | D8: 15 | E8: 0 | F8: 0.65 | G8: 0.98 | H8: -1.75 | I8: 2.16 | J8: 43 | K8: 0.94 | L8: 13.97 | M8: EQ-FLX
A9: Aditya Birla Sun Life Business Cycle Fund - Regular Plan | B9: 4.8 | C9: 19.22 | D9: 0 | E9: 0 | F9: 0.68 | G9: 1.09 | H9: -1.45 | I9: 2.14 | J9: 11 | K9: 0.96 | L9: 14.21 | M9: EQ-THEMATIC
A10: Aditya Birla Sun Life Conglomerate - Regular Plan | B10: 0 | C10: 0 | D10: 0 | E10: 0 | F10: 0 | G10: 0 | H10: 0 | I10: 2.07 | J10: 0 | K10: 0 | L10: 0 | M10: EQ-THEMATIC
A11: Aditya Birla Sun Life Dividend Yield Fund - Regular Plan | B11: 1.73 | C11: 26.52 | D11: 25.08 | E11: 12.47 | F11: 1 | G11: 1.56 | H11: 4.06 | I11: 2.22 | J11: 33 | K11: 0.97 | L11: 15.2 | M11: EQ-L&MC
A12: Aditya Birla Sun Life Equity Hybrid '95 Fund - Regular Plan | B12: 6.35 | C12: 16.61 | D12: 18.41 | E12: 10.7 | F12: 0.72 | G12: 1.04 | H12: -0.69 | I12: 1.84 | J12: 56 | K12: 0.85 | L12: 10.28 | M12: HY-AH
A13: Aditya Birla Sun Life ESG Integration Strategy Fund - Regular Plan | B13: 8.59 | C13: 18.83 | D13: 0 | E13: 0 | F13: 0.62 | G13: 0.98 | H13: -1 | I13: 2.44 | J13: 10 | K13: 0.98 | L13: 14.57 | M13: EQ-FLX
... A630: Union Aggressive Hybrid Fund - Regular Plan | B630: 5.6 | C630: 16.71 | D630: 0 | E630: 0 | F630: 0.74 | G630: 1.14 | H630: -0.46 | I630: 2.37 | J630: 65 | K630: 0.88 | L630: 10.76 | M630: HY-AH
A631: Union Arbitrage Fund - Regular Plan | B631: 6.69 | C631: 6.71 | D631: 5.31 | E631: 0 | F631: 0.23 | G631: 0.27 | H631: 1.1 | I631: 1.07 | J631: 1,315.00 | K631: 0.51 | L631: 0.56 | M631: HY-AR
A632: Union Balanced Advantage Fund - Regular Plan | B632: 3.87 | C632: 12.11 | D632: 12.34 | E632: 0 | F632: 0.61 | G632: 0.91 | H632: -0.97 | I632: 2.15 | J632: 451 | K632: 0.67 | L632: 7.08 | M632: HY-DAA
A633: Union Business Cycle Fund - Regular Plan | B633: -2.33 | C633: 0 | D633: 0 | E633: 0 | F633: 0 | G633: 0 | H633: 0 | I633: 2.36 | J633: 194 | K633: 0 | L633: 0 | M633: EQ-THEMATIC
A634: Union Children's Fund - Regular Plan | B634: 6.05 | C634: 0 | D634: 0 | E634: 0 | F634: 0 | G634: 0 | H634: 0 | I634: 2.42 | J634: 82 | K634: 0 | L634: 0 | M634: EQ-FLX
A635: Union Flexi Cap Fund | B635: 3.24 | C635: 20.29 | D635: 22.09 | E635: 12.21 | F635: 0.78 | G635: 1.07 | H635: 0.25 | I635: 2.02 | J635: 106 | K635: 0.9 | L635: 13.52 | M635: EQ-FLX
A636: Union Focused Fund - Regular Plan | B636: 0.49 | C636: 16.85 | D636: 19.43 | E636: 0 | F636: 0.6 | G636: 0.85 | H636: -1.86 | I636: 2.49 | J636: 126 | K636: 0.84 | L636: 12.93 | M636: EQ-FLX
A637: Union Innovation & Opportunities Fund - Regular Plan | B637: 5.27 | C637: 0 | D637: 0 | E637: 0 | F637: 0 | G637: 0 | H637: 0 | I637: 2.21 | J637: 55 | K637: 0 | L637: 0 | M637: EQ-THEMATIC
A638: Union Largecap Fund - Regular Plan | B638: 0.09 | C638: 17.44 | D638: 18.78 | E638: 0 | F638: 0.62 | G638: 1.08 | H638: -1.41 | I638: 2.49 | J638: 130 | K638: 0.92 | L638: 12.93 | M638: EQ-LC
A639: Union Large & Midcap Fund - Regular Plan | B639: 1.3 | C639: 20.34 | D639: 22.06 | E639: 0 | F639: 0.73 | G639: 0.92 | H639: 0.42 | I639: 2.27 | J639: 164 | K639: 0.92 | L639: 14.43 | M639: EQ-L&MC
A640: Union Midcap Fund - Regular Plan | B640: 2.51 | C640: 24.33 | D640: 28.94 | E640: 0 | F640: 0.85 | G640: 1.13 | H640: -2.84 | I640: 2.1 | J640: 168 | K640: 0.94 | L640: 16.73 | M640: EQ-MC
A641: Union Multi Asset Allocation Fund - Regular Plan | B641: 0 | C641: 0 | D641: 0 | E641: 0 | F641: 0 | G641: 0 | H641: 0 | I641: 2.2 | J641: 0 | K641: 0 | L641: 0 | M641: HY-MAA
A642: Union Multicap Fund - Regular Plan | B642: 2.2 | C642: 0 | D642: 0 | E642: 0 | F642: 0 | G642: 0 | H642: 0 | I642: 2.19 | J642: 125 | K642: 0 | L642: 0 | M642: EQ-MLC
A643: Union Retirement Fund - Regular Plan | B643: 3.73 | C643: 0 | D643: 0 | E643: 0 | F643: 0 | G643: 0 | H643: 0 | I643: 2.37 | J643: 49 | K643: 0 | L643: 0 | M643: EQ-FLX
... A645: UTI Aggressive Hybrid Fund - Regular Plan | B645: 6.92 | C645: 20.58 | D645: 21.76 | E645: 12.32 | F645: 1.11 | G645: 1.7 | H645: 3.21 | I645: 1.88 | J645: 31 | K645: 0.83 | L645: 10.1 | M645: HY-AH
A646: UTI Arbitrage Fund - Regular Plan | B646: 7.12 | C646: 6.89 | D646: 5.57 | E646: 5.83 | F646: 0.5 | G646: 0.54 | H646: 1.54 | I646: 0.76 | J646: 1,164.00 | K646: 0.66 | L646: 0.56 | M646: HY-AR
A647: UTI Balanced Advantage Fund - Regular Plan | B647: 8.23 | C647: 0 | D647: 0 | E647: 0 | F647: 0 | G647: 0 | H647: 0 | I647: 1.92 | J647: 223 | K647: 0 | L647: 0 | M647: HY-DAA
A648: UTI BSE Housing Index Fund - Regular Plan | B648: -8.18 | C648: 0 | D648: 0 | E648: 0 | F648: 0 | G648: 0 | H648: 0 | I648: 0.98 | J648: 0 | K648: 0 | L648: 0 | M648: EQ-THEMATIC
A649: UTI BSE Low Volatility Index Fund - Regular Plan | B649: 0.36 | C649: 19.57 | D649: 0 | E649: 0 | F649: 0.74 | G649: 1.15 | H649: 0.16 | I649: 0.91 | J649: 0 | K649: 0.9 | L649: 13.58 | M649: EQ-L&MC
A650: UTI BSE Sensex Index Fund - Regular Plan | B650: 5.98 | C650: 17.46 | D650: 0 | E650: 0 | F650: 0.64 | G650: 1.06 | H650: -1.27 | I650: 0.3 | J650: 15 | K650: 0.91 | L650: 12.71 | M650: EQ-LC
A651: UTI Children's Equity Fund - Regular Plan | B651: 1.38 | C651: 18.31 | D651: 19.9 | E651: 12.25 | F651: 0.61 | G651: 0.99 | H651: -2.16 | I651: 2.25 | J651: 28 | K651: 0.93 | L651: 14.08 | M651: EQ-FLX
A652: UTI Children's Hybrid Fund - Regular Plan | B652: 6.21 | C652: 12.14 | D652: 12.49 | E652: 8.77 | F652: 0.7 | G652: 1.09 | H652: -0.61 | I652: 1.73 | J652: 35 | K652: 0.62 | L652: 6.22 | M652: HY-BH
A653: UTI Conservative Hybrid Fund - Regular Plan | B653: 8.26 | C653: 11.58 | D653: 11.74 | E653: 8.37 | F653: 1 | G653: 1.65 | H653: 0.44 | I653: 1.82 | J653: 31 | K653: 1.01 | L653: 4.12 | M653: HY-CH
A654: UTI Flexi Cap Fund - Regular Plan | B654: 7.63 | C654: 15.63 | D654: 18.85 | E654: 12.29 | F654: 0.44 | G654: 0.71 | H654: -3.97 | I654: 1.66 | J654: 10 | K654: 0.88 | L654: 13.97 | M654: EQ-FLX
A655: UTI Focused Fund - Regular Plan | B655: 1.4 | C655: 20.55 | D655: 0 | E655: 0 | F655: 0.73 | G655: 1.17 | H655: -0.29 | I655: 1.96 | J655: 23 | K655: 0.93 | L655: 14.3 | M655: EQ-FLX
A656: UTI Innovation Fund - Regular Plan | B656: 1.11 | C656: 0 | D656: 0 | E656: 0 | F656: 0 | G656: 0 | H656: 0 | I656: 2.29 | J656: 12 | K656: 0 | L656: 0 | M656: EQ-THEMATIC
A657: UTI Large Cap Fund - Regular Plan | B657: 4.4 | C657: 17.43 | D657: 19.29 | E657: 11.81 | F657: 0.6 | G657: 0.97 | H657: -1.71 | I657: 1.75 | J657: 36 | K657: 0.91 | L657: 12.76 | M657: EQ-LC
A658: UTI Large & Mid Cap Fund - Regular Plan | B658: 6.5 | C658: 26.81 | D658: 27.74 | E658: 13.81 | F658: 1.15 | G658: 1.75 | H658: 5.69 | I658: 1.93 | J658: 33 | K658: 0.95 | L658: 14.07 | M658: EQ-L&MC
... A688: WhiteOak Capital Special Opportunities Fund - Regular Plan | B688: 14.93 | C688: 0 | D688: 0 | E688: 0 | F688: 0 | G688: 0 | H688: 0 | I688: 2.19 | J688: 0 | K688: 0 | L688: 0 | M688: EQ-THEMATIC

Sheet Fund Ranking_Debt
B4: Ultra Short Duration Fund
AN5: Score
B6: Funds | C6: Rank | F6: YTM | G6: Modified Duration | H6: Macaulay Duration | I6: 3 Months | J6: 6 Months | K6: 9 Months | L6: 1 Year | M6: 2 Years | N6: 3 Years | O6: 5 Years | P6: 10 Years | Q6: Sovereign | R6: AAA/A1+ | S6: AA+ | T6: AA/AA- | U6: Below AA- | V6: Cash and Fixed Deposits | W6: =F6 | X6: =G6 | Y6: =H6 | Z6: =I6 | AA6: =J6 | AB6: =K6 | AC6: =L6 | AD6: =M6 | ... AM6: =V6 | AQ6: 1 | AR6: 2 | AS6: 3
B7: Aditya Birla Sun Life Savings Fund - Reg - Growth | C7: =RANK(AN7,$AN$7:$AN$13,0) | E7: =B7 | F7: 7.45 | G7: 0.49 | H7: 0.52 | I7: 6.73 | J7: 5.85 | K7: 5.97 | L7: 6.48 | M7: 7.22 | N7: 7.3 | O7: 6.33 | P7: 6.92 | Q7: 9.06 | R7: 57.33 | S7: 22.55 | T7: 8.68 | U7: 0.2 | V7: 2.39 | W7: =(F7-MIN(F$7:F$13))/(MAX(F$7:F$13)-MIN(F$7:F$13)) | X7: =(MAX(G$7:G$13)-G7)/(MAX(G$7:G$13)-MIN(G$7:G$13)) | Y7: =(MAX(H$7:H$13)-H7)/(MAX(H$7:H$13)-MIN(H$7:H$13)) | Z7: =(I7-MIN(I$7:I$13))/(MAX(I$7:I$13)-MIN(I$7:I$13)) | AA7: =(J7-MIN(J$7:J$13))/(MAX(J$7:J$13)-MIN(J$7:J$13)) | AB7: =(K7-MIN(K$7:K$13))/(MAX(K$7:K$13)-MIN(K$7:K$13)) | AC7: =(L7-MIN(L$7:L$13))/(MAX(L$7:L$13)-MIN(L$7:L$13)) | AD7: =(M7-MIN(M$7:M$13))/(MAX(M$7:M$13)-MIN(M$7:M$13)) | AE7: =(N7-MIN(N$7:N$13))/(MAX(N$7:N$13)-MIN(N$7:N$13)) | AF7: =(O7-MIN(O$7:O$13))/(MAX(O$7:O$13)-MIN(O$7:O$13)) | AG7: =(P7-MIN(P$7:P$13))/(MAX(P$7:P$13)-MIN(P$7:P$13)) | ... AJ7: =(S7-MIN(S$7:S$13))/(MAX(S$7:S$13)-MIN(S$7:S$13)) | AK7: =(MAX(T$7:T$13)-T7)/(MAX(T$7:T$13)-MIN(T$7:T$13)) | AL7: =(MAX(U$7:U$13)-U7)/(MAX(U$7:U$13)-MIN(U$7:U$13)) | AM7: =(V7-MIN(V$7:V$13))/(MAX(V$7:V$13)-MIN(V$7:V$13)) | AN7: {=SUMPRODUCT(W7:Y7, TRANSPOSE('Fund Ranking Criteria'!$C$39:$C$41))+SUMPRODUCT('Fund Ranking_Debt'!Z7:AG7, TRANSPOSE('Fund Ranking Criteria'!$C$30:$C$37))+SUMPRODUCT('Fund Ranking_Debt'!AH7:AM7, TRANSPOSE('Fund Ranking Criteria'!$C$43:$C$48))} | AQ7: 2 | AR7: 3 | AS7: 5
B8: HDFC Ultra Short Term Fund - Reg - Growth | C8: =RANK(AN8,$AN$7:$AN$13,0) | E8: =B8 | F8: 7.8 | G8: 0.46 | H8: 0.51 | I8: 6.63 | J8: 5.65 | K8: 5.74 | L8: 6.13 | M8: 6.83 | N8: 6.94 | O8: 5.99 | P8: 0 | Q8: 9.56 | R8: 81.95 | S8: 3.31 | T8: 4.28 | U8: 0 | V8: 0.9 | W8: =(F8-MIN(F$7:F$13))/(MAX(F$7:F$13)-MIN(F$7:F$13)) | X8: =(MAX(G$7:G$13)-G8)/(MAX(G$7:G$13)-MIN(G$7:G$13)) | Y8: =(MAX(H$7:H$13)-H8)/(MAX(H$7:H$13)-MIN(H$7:H$13)) | Z8: =(I8-MIN(I$7:I$13))/(MAX(I$7:I$13)-MIN(I$7:I$13)) | AA8: =(J8-MIN(J$7:J$13))/(MAX(J$7:J$13)-MIN(J$7:J$13)) | AB8: =(K8-MIN(K$7:K$13))/(MAX(K$7:K$13)-MIN(K$7:K$13)) | AC8: =(L8-MIN(L$7:L$13))/(MAX(L$7:L$13)-MIN(L$7:L$13)) | AD8: =(M8-MIN(M$7:M$13))/(MAX(M$7:M$13)-MIN(M$7:M$13)) | AE8: =(N8-MIN(N$7:N$13))/(MAX(N$7:N$13)-MIN(N$7:N$13)) | AF8: =(O8-MIN(O$7:O$13))/(MAX(O$7:O$13)-MIN(O$7:O$13)) | AG8: =(P8-MIN(P$7:P$13))/(MAX(P$7:P$13)-MIN(P$7:P$13)) | ... AJ8: =(S8-MIN(S$7:S$13))/(MAX(S$7:S$13)-MIN(S$7:S$13)) | AK8: =(MAX(T$7:T$13)-T8)/(MAX(T$7:T$13)-MIN(T$7:T$13)) | AL8: =(MAX(U$7:U$13)-U8)/(MAX(U$7:U$13)-MIN(U$7:U$13)) | AM8: =(V8-MIN(V$7:V$13))/(MAX(V$7:V$13)-MIN(V$7:V$13)) | AN8: {=SUMPRODUCT(W8:Y8, TRANSPOSE('Fund Ranking Criteria'!$C$39:$C$41))+SUMPRODUCT('Fund Ranking_Debt'!Z8:AG8, TRANSPOSE('Fund Ranking Criteria'!$C$30:$C$37))+SUMPRODUCT('Fund Ranking_Debt'!AH8:AM8, TRANSPOSE('Fund Ranking Criteria'!$C$43:$C$48))}
B9: SBI Magnum Ultra Short Duration Fund - Growth | C9: =RANK(AN9,$AN$7:$AN$13,0) | E9: =B9 | F9: 6.26 | G9: 0.42 | H9: 0.45 | I9: 7.17 | J9: 7.88 | K9: 7.54 | L9: 7.56 | M9: 7.37 | N9: 7.06 | O9: 5.65 | P9: 6.6 | Q9: 16.31 | R9: 77.66 | S9: 3.09 | T9: 0 | U9: -13.56 | V9: 16.29 | W9: =(F9-MIN(F$7:F$13))/(MAX(F$7:F$13)-MIN(F$7:F$13)) | X9: =(MAX(G$7:G$13)-G9)/(MAX(G$7:G$13)-MIN(G$7:G$13)) | Y9: =(MAX(H$7:H$13)-H9)/(MAX(H$7:H$13)-MIN(H$7:H$13)) | Z9: =(I9-MIN(I$7:I$13))/(MAX(I$7:I$13)-MIN(I$7:I$13)) | AA9: =(J9-MIN(J$7:J$13))/(MAX(J$7:J$13)-MIN(J$7:J$13)) | AB9: =(K9-MIN(K$7:K$13))/(MAX(K$7:K$13)-MIN(K$7:K$13)) | AC9: =(L9-MIN(L$7:L$13))/(MAX(L$7:L$13)-MIN(L$7:L$13)) | AD9: =(M9-MIN(M$7:M$13))/(MAX(M$7:M$13)-MIN(M$7:M$13)) | AE9: =(N9-MIN(N$7:N$13))/(MAX(N$7:N$13)-MIN(N$7:N$13)) | AF9: =(O9-MIN(O$7:O$13))/(MAX(O$7:O$13)-MIN(O$7:O$13)) | AG9: =(P9-MIN(P$7:P$13))/(MAX(P$7:P$13)-MIN(P$7:P$13)) | ... AJ9: =(S9-MIN(S$7:S$13))/(MAX(S$7:S$13)-MIN(S$7:S$13)) | AK9: =(MAX(T$7:T$13)-T9)/(MAX(T$7:T$13)-MIN(T$7:T$13)) | AL9: =(MAX(U$7:U$13)-U9)/(MAX(U$7:U$13)-MIN(U$7:U$13)) | AM9: =(V9-MIN(V$7:V$13))/(MAX(V$7:V$13)-MIN(V$7:V$13)) | AN9: {=SUMPRODUCT(W9:Y9, TRANSPOSE('Fund Ranking Criteria'!$C$39:$C$41))+SUMPRODUCT('Fund Ranking_Debt'!Z9:AG9, TRANSPOSE('Fund Ranking Criteria'!$C$30:$C$37))+SUMPRODUCT('Fund Ranking_Debt'!AH9:AM9, TRANSPOSE('Fund Ranking Criteria'!$C$43:$C$48))} | AQ9: =SUMPRODUCT(AQ6:AS6,AQ7:AS7)
B10: ICICI Prudential Ultra Short Term Fund - Growth | C10: =RANK(AN10,$AN$7:$AN$13,0) | E10: =B10 | F10: 7.73 | G10: 0.46 | H10: 0.5 | I10: 6.76 | J10: 5.87 | K10: 5.94 | L10: 6.37 | M10: 6.93 | N10: 7.02 | O10: 6.11 | P10: 6.78 | Q10: 4.13 | R10: 70.07 | S10: 9.65 | T10: 11.7 | U10: -34.69 | V10: 4.45 | W10: =(F10-MIN(F$7:F$13))/(MAX(F$7:F$13)-MIN(F$7:F$13)) | X10: =(MAX(G$7:G$13)-G10)/(MAX(G$7:G$13)-MIN(G$7:G$13)) | Y10: =(MAX(H$7:H$13)-H10)/(MAX(H$7:H$13)-MIN(H$7:H$13)) | Z10: =(I10-MIN(I$7:I$13))/(MAX(I$7:I$13)-MIN(I$7:I$13)) | AA10: =(J10-MIN(J$7:J$13))/(MAX(J$7:J$13)-MIN(J$7:J$13)) | AB10: =(K10-MIN(K$7:K$13))/(MAX(K$7:K$13)-MIN(K$7:K$13)) | AC10: =(L10-MIN(L$7:L$13))/(MAX(L$7:L$13)-MIN(L$7:L$13)) | AD10: =(M10-MIN(M$7:M$13))/(MAX(M$7:M$13)-MIN(M$7:M$13)) | AE10: =(N10-MIN(N$7:N$13))/(MAX(N$7:N$13)-MIN(N$7:N$13)) | AF10: =(O10-MIN(O$7:O$13))/(MAX(O$7:O$13)-MIN(O$7:O$13)) | AG10: =(P10-MIN(P$7:P$13))/(MAX(P$7:P$13)-MIN(P$7:P$13)) | ... AJ10: =(S10-MIN(S$7:S$13))/(MAX(S$7:S$13)-MIN(S$7:S$13)) | AK10: =(MAX(T$7:T$13)-T10)/(MAX(T$7:T$13)-MIN(T$7:T$13)) | AL10: =(MAX(U$7:U$13)-U10)/(MAX(U$7:U$13)-MIN(U$7:U$13)) | AM10: =(V10-MIN(V$7:V$13))/(MAX(V$7:V$13)-MIN(V$7:V$13)) | AN10: {=SUMPRODUCT(W10:Y10, TRANSPOSE('Fund Ranking Criteria'!$C$39:$C$41))+SUMPRODUCT('Fund Ranking_Debt'!Z10:AG10, TRANSPOSE('Fund Ranking Criteria'!$C$30:$C$37))+SUMPRODUCT('Fund Ranking_Debt'!AH10:AM10, TRANSPOSE('Fund Ranking Criteria'!$C$43:$C$48))}
B11: Kotak Savings Fund - Reg - Growth | C11: =RANK(AN11,$AN$7:$AN$13,0) | E11: =B11 | F11: 7.53 | G11: 0.48 | H11: 0.49 | I11: 6.57 | J11: 5.74 | K11: 5.72 | L11: 6.1 | M11: 6.73 | N11: 6.81 | O11: 5.87 | P11: 6.35 | Q11: 15.04 | R11: 70.34 | S11: 6.67 | T11: 7.59 | U11: 0 | V11: 0.35 | W11: =(F11-MIN(F$7:F$13))/(MAX(F$7:F$13)-MIN(F$7:F$13)) | X11: =(MAX(G$7:G$13)-G11)/(MAX(G$7:G$13)-MIN(G$7:G$13)) | Y11: =(MAX(H$7:H$13)-H11)/(MAX(H$7:H$13)-MIN(H$7:H$13)) | Z11: =(I11-MIN(I$7:I$13))/(MAX(I$7:I$13)-MIN(I$7:I$13)) | AA11: =(J11-MIN(J$7:J$13))/(MAX(J$7:J$13)-MIN(J$7:J$13)) | AB11: =(K11-MIN(K$7:K$13))/(MAX(K$7:K$13)-MIN(K$7:K$13)) | AC11: =(L11-MIN(L$7:L$13))/(MAX(L$7:L$13)-MIN(L$7:L$13)) | AD11: =(M11-MIN(M$7:M$13))/(MAX(M$7:M$13)-MIN(M$7:M$13)) | AE11: =(N11-MIN(N$7:N$13))/(MAX(N$7:N$13)-MIN(N$7:N$13)) | AF11: =(O11-MIN(O$7:O$13))/(MAX(O$7:O$13)-MIN(O$7:O$13)) | AG11: =(P11-MIN(P$7:P$13))/(MAX(P$7:P$13)-MIN(P$7:P$13)) | ... AJ11: =(S11-MIN(S$7:S$13))/(MAX(S$7:S$13)-MIN(S$7:S$13)) | AK11: =(MAX(T$7:T$13)-T11)/(MAX(T$7:T$13)-MIN(T$7:T$13)) | AL11: =(MAX(U$7:U$13)-U11)/(MAX(U$7:U$13)-MIN(U$7:U$13)) | AM11: =(V11-MIN(V$7:V$13))/(MAX(V$7:V$13)-MIN(V$7:V$13)) | AN11: {=SUMPRODUCT(W11:Y11, TRANSPOSE('Fund Ranking Criteria'!$C$39:$C$41))+SUMPRODUCT('Fund Ranking_Debt'!Z11:AG11, TRANSPOSE('Fund Ranking Criteria'!$C$30:$C$37))+SUMPRODUCT('Fund Ranking_Debt'!AH11:AM11, TRANSPOSE('Fund Ranking Criteria'!$C$43:$C$48))}
B12: Nippon India Ultra Short Duration Fund - Reg - Growth | C12: =RANK(AN12,$AN$7:$AN$13,0) | E12: =B12 | F12: 7.97 | G12: 0.49 | H12: 0.53 | I12: 6.83 | J12: 5.89 | K12: 5.86 | L12: 6.18 | M12: 6.76 | N12: 6.81 | O12: 6.71 | P12: 5.81 | Q12: 8.29 | R12: 59.74 | S12: 9.07 | T12: 24.37 | U12: 0.07 | V12: -1.53 | W12: =(F12-MIN(F$7:F$13))/(MAX(F$7:F$13)-MIN(F$7:F$13)) | X12: =(MAX(G$7:G$13)-G12)/(MAX(G$7:G$13)-MIN(G$7:G$13)) | Y12: =(MAX(H$7:H$13)-H12)/(MAX(H$7:H$13)-MIN(H$7:H$13)) | Z12: =(I12-MIN(I$7:I$13))/(MAX(I$7:I$13)-MIN(I$7:I$13)) | AA12: =(J12-MIN(J$7:J$13))/(MAX(J$7:J$13)-MIN(J$7:J$13)) | AB12: =(K12-MIN(K$7:K$13))/(MAX(K$7:K$13)-MIN(K$7:K$13)) | AC12: =(L12-MIN(L$7:L$13))/(MAX(L$7:L$13)-MIN(L$7:L$13)) | AD12: =(M12-MIN(M$7:M$13))/(MAX(M$7:M$13)-MIN(M$7:M$13)) | AE12: =(N12-MIN(N$7:N$13))/(MAX(N$7:N$13)-MIN(N$7:N$13)) | AF12: =(O12-MIN(O$7:O$13))/(MAX(O$7:O$13)-MIN(O$7:O$13)) | AG12: =(P12-MIN(P$7:P$13))/(MAX(P$7:P$13)-MIN(P$7:P$13)) | ... AJ12: =(S12-MIN(S$7:S$13))/(MAX(S$7:S$13)-MIN(S$7:S$13)) | AK12: =(MAX(T$7:T$13)-T12)/(MAX(T$7:T$13)-MIN(T$7:T$13)) | AL12: =(MAX(U$7:U$13)-U12)/(MAX(U$7:U$13)-MIN(U$7:U$13)) | AM12: =(V12-MIN(V$7:V$13))/(MAX(V$7:V$13)-MIN(V$7:V$13)) | AN12: {=SUMPRODUCT(W12:Y12, TRANSPOSE('Fund Ranking Criteria'!$C$39:$C$41))+SUMPRODUCT('Fund Ranking_Debt'!Z12:AG12, TRANSPOSE('Fund Ranking Criteria'!$C$30:$C$37))+SUMPRODUCT('Fund Ranking_Debt'!AH12:AM12, TRANSPOSE('Fund Ranking Criteria'!$C$43:$C$48))}
B13: UTI Ultra Short Duration Fund - Growth | C13: =RANK(AN13,$AN$7:$AN$13,0) | E13: =B13 | F13: 7.8 | G13: 0.55 | H13: 0.56 | I13: 6.34 | J13: 5.55 | K13: 5.56 | L13: 5.92 | M13: 6.61 | N13: 6.72 | O13: 6.32 | P13: 6.06 | Q13: 15.88 | R13: 58.84 | S13: 16.29 | T13: 8.56 | U13: 0 | V13: 0.44 | W13: =(F13-MIN(F$7:F$13))/(MAX(F$7:F$13)-MIN(F$7:F$13)) | X13: =(MAX(G$7:G$13)-G13)/(MAX(G$7:G$13)-MIN(G$7:G$13)) | Y13: =(MAX(H$7:H$13)-H13)/(MAX(H$7:H$13)-MIN(H$7:H$13)) | Z13: =(I13-MIN(I$7:I$13))/(MAX(I$7:I$13)-MIN(I$7:I$13)) | AA13: =(J13-MIN(J$7:J$13))/(MAX(J$7:J$13)-MIN(J$7:J$13)) | AB13: =(K13-MIN(K$7:K$13))/(MAX(K$7:K$13)-MIN(K$7:K$13)) | AC13: =(L13-MIN(L$7:L$13))/(MAX(L$7:L$13)-MIN(L$7:L$13)) | AD13: =(M13-MIN(M$7:M$13))/(MAX(M$7:M$13)-MIN(M$7:M$13)) | AE13: =(N13-MIN(N$7:N$13))/(MAX(N$7:N$13)-MIN(N$7:N$13)) | AF13: =(O13-MIN(O$7:O$13))/(MAX(O$7:O$13)-MIN(O$7:O$13)) | AG13: =(P13-MIN(P$7:P$13))/(MAX(P$7:P$13)-MIN(P$7:P$13)) | ... AJ13: =(S13-MIN(S$7:S$13))/(MAX(S$7:S$13)-MIN(S$7:S$13)) | AK13: =(MAX(T$7:T$13)-T13)/(MAX(T$7:T$13)-MIN(T$7:T$13)) | AL13: =(MAX(U$7:U$13)-U13)/(MAX(U$7:U$13)-MIN(U$7:U$13)) | AM13: =(V13-MIN(V$7:V$13))/(MAX(V$7:V$13)-MIN(V$7:V$13)) | AN13: {=SUMPRODUCT(W13:Y13, TRANSPOSE('Fund Ranking Criteria'!$C$39:$C$41))+SUMPRODUCT('Fund Ranking_Debt'!Z13:AG13, TRANSPOSE('Fund Ranking Criteria'!$C$30:$C$37))+SUMPRODUCT('Fund Ranking_Debt'!AH13:AM13, TRANSPOSE('Fund Ranking Criteria'!$C$43:$C$48))}
B16: Low Duration Fund
AN17: Score
B18: Funds | C18: Rank | F18: YTM | G18: Modified Duration | H18: Macaulay Duration | I18: 3 Months | J18: 6 Months | K18: 9 Months | L18: 1 Year | M18: 2 Years | N18: 3 Years | O18: 5 Years | P18: 10 Years | Q18: Sovereign | R18: AAA/A1+ | S18: AA+ | T18: AA/AA- | U18: Below AA- | V18: Cash and Fixed Deposits | W18: =F18 | X18: =G18 | Y18: =H18 | Z18: =I18 | AA18: =J18 | AB18: =K18 | AC18: =L18 | AD18: =M18 | ... AM18: =V18
B19: ICICI Prudential Savings Fund - Reg - Growth | C19: =RANK(AN19,$AN$19:$AN$25,0) | E19: =B19 | F19: 7.57 | G19: 0.91 | H19: 0.97 | I19: 6.38 | J19: 5.79 | K19: 5.9 | L19: 6.51 | M19: 7.35 | N19: 7.5 | O19: 6.5 | P19: 7.1 | Q19: 10.54 | R19: 71.7 | S19: 7.24 | T19: 6.87 | U19: -26.53 | V19: 3.66 | W19: =(F19-MIN(F$19:F$25))/(MAX(F$19:F$25)-MIN(F$19:F$25)) | X19: =(MAX(G$19:G$25)-G19)/(MAX(G$19:G$25)-MIN(G$19:G$25)) | Y19: =(MAX(H$19:H$25)-H19)/(MAX(H$19:H$25)-MIN(H$19:H$25)) | Z19: =(I19-MIN(I$19:I$25))/(MAX(I$19:I$25)-MIN(I$19:I$25)) | AA19: =(J19-MIN(J$19:J$25))/(MAX(J$19:J$25)-MIN(J$19:J$25)) | AB19: =(K19-MIN(K$19:K$25))/(MAX(K$19:K$25)-MIN(K$19:K$25)) | AC19: =(L19-MIN(L$19:L$25))/(MAX(L$19:L$25)-MIN(L$19:L$25)) | AD19: =(M19-MIN(M$19:M$25))/(MAX(M$19:M$25)-MIN(M$19:M$25)) | AE19: =(N19-MIN(N$19:N$25))/(MAX(N$19:N$25)-MIN(N$19:N$25)) | AF19: =(O19-MIN(O$19:O$25))/(MAX(O$19:O$25)-MIN(O$19:O$25)) | AG19: =(P19-MIN(P$19:P$25))/(MAX(P$19:P$25)-MIN(P$19:P$25)) | ... AJ19: =(S19-MIN(S$19:S$25))/(MAX(S$19:S$25)-MIN(S$19:S$25)) | AK19: =(MAX(T$7:T$13)-T19)/(MAX(T$7:T$13)-MIN(T$7:T$13)) | AL19: =(MAX(U$7:U$13)-U19)/(MAX(U$7:U$13)-MIN(U$7:U$13)) | AM19: =(V19-MIN(V$19:V$25))/(MAX(V$19:V$25)-MIN(V$19:V$25)) | AN19: {=SUMPRODUCT(W19:Y19, TRANSPOSE('Fund Ranking Criteria'!$D$39:$D$41))+SUMPRODUCT('Fund Ranking_Debt'!Z19:AG19, TRANSPOSE('Fund Ranking Criteria'!$D$30:$D$37))+SUMPRODUCT('Fund Ranking_Debt'!AH19:AM19, TRANSPOSE('Fund Ranking Criteria'!$D$43:$D$48))}
B20: HDFC Low Duration Fund - Growth | C20: =RANK(AN20,$AN$19:$AN$25,0) | E20: =B20 | F20: 7.77 | G20: 0.95 | H20: 1.02 | I20: 6.23 | J20: 5.18 | K20: 5.33 | L20: 5.96 | M20: 6.86 | N20: 6.96 | O20: 6.01 | P20: 6.58 | Q20: 13.48 | R20: 73.49 | S20: 1.8 | T20: 12.55 | U20: 0 | V20: -1.31 | W20: =(F20-MIN(F$19:F$25))/(MAX(F$19:F$25)-MIN(F$19:F$25)) | X20: =(MAX(G$19:G$25)-G20)/(MAX(G$19:G$25)-MIN(G$19:G$25)) | Y20: =(MAX(H$19:H$25)-H20)/(MAX(H$19:H$25)-MIN(H$19:H$25)) | Z20: =(I20-MIN(I$19:I$25))/(MAX(I$19:I$25)-MIN(I$19:I$25)) | AA20: =(J20-MIN(J$19:J$25))/(MAX(J$19:J$25)-MIN(J$19:J$25)) | AB20: =(K20-MIN(K$19:K$25))/(MAX(K$19:K$25)-MIN(K$19:K$25)) | AC20: =(L20-MIN(L$19:L$25))/(MAX(L$19:L$25)-MIN(L$19:L$25)) | AD20: =(M20-MIN(M$19:M$25))/(MAX(M$19:M$25)-MIN(M$19:M$25)) | AE20: =(N20-MIN(N$19:N$25))/(MAX(N$19:N$25)-MIN(N$19:N$25)) | AF20: =(O20-MIN(O$19:O$25))/(MAX(O$19:O$25)-MIN(O$19:O$25)) | AG20: =(P20-MIN(P$19:P$25))/(MAX(P$19:P$25)-MIN(P$19:P$25)) | ... AJ20: =(S20-MIN(S$19:S$25))/(MAX(S$19:S$25)-MIN(S$19:S$25)) | AK20: =(MAX(T$7:T$13)-T20)/(MAX(T$7:T$13)-MIN(T$7:T$13)) | AL20: =(MAX(U$7:U$13)-U20)/(MAX(U$7:U$13)-MIN(U$7:U$13)) | AM20: =(V20-MIN(V$19:V$25))/(MAX(V$19:V$25)-MIN(V$19:V$25)) | AN20: {=SUMPRODUCT(W20:Y20, TRANSPOSE('Fund Ranking Criteria'!$D$39:$D$41))+SUMPRODUCT('Fund Ranking_Debt'!Z20:AG20, TRANSPOSE('Fund Ranking Criteria'!$D$30:$D$37))+SUMPRODUCT('Fund Ranking_Debt'!AH20:AM20, TRANSPOSE('Fund Ranking Criteria'!$D$43:$D$48))}
B21: SBI Magnum Low Duration Fund - Growth | C21: =RANK(AN21,$AN$19:$AN$25,0) | E21: =B21 | F21: 6.53 | G21: 0.86 | H21: 0.9 | I21: 7.56 | J21: 8.51 | K21: 7.81 | L21: 7.79 | M21: 7.37 | N21: 7 | O21: 5.54 | P21: 6.68 | Q21: 13.35 | R21: 77.58 | S21: 7.01 | T21: 0 | U21: 0 | V21: 1.84 | W21: =(F21-MIN(F$19:F$25))/(MAX(F$19:F$25)-MIN(F$19:F$25)) | X21: =(MAX(G$19:G$25)-G21)/(MAX(G$19:G$25)-MIN(G$19:G$25)) | Y21: =(MAX(H$19:H$25)-H21)/(MAX(H$19:H$25)-MIN(H$19:H$25)) | Z21: =(I21-MIN(I$19:I$25))/(MAX(I$19:I$25)-MIN(I$19:I$25)) | AA21: =(J21-MIN(J$19:J$25))/(MAX(J$19:J$25)-MIN(J$19:J$25)) | AB21: =(K21-MIN(K$19:K$25))/(MAX(K$19:K$25)-MIN(K$19:K$25)) | AC21: =(L21-MIN(L$19:L$25))/(MAX(L$19:L$25)-MIN(L$19:L$25)) | AD21: =(M21-MIN(M$19:M$25))/(MAX(M$19:M$25)-MIN(M$19:M$25)) | AE21: =(N21-MIN(N$19:N$25))/(MAX(N$19:N$25)-MIN(N$19:N$25)) | AF21: =(O21-MIN(O$19:O$25))/(MAX(O$19:O$25)-MIN(O$19:O$25)) | AG21: =(P21-MIN(P$19:P$25))/(MAX(P$19:P$25)-MIN(P$19:P$25)) | ... AJ21: =(S21-MIN(S$19:S$25))/(MAX(S$19:S$25)-MIN(S$19:S$25)) | AK21: =(MAX(T$7:T$13)-T21)/(MAX(T$7:T$13)-MIN(T$7:T$13)) | AL21: =(MAX(U$7:U$13)-U21)/(MAX(U$7:U$13)-MIN(U$7:U$13)) | AM21: =(V21-MIN(V$19:V$25))/(MAX(V$19:V$25)-MIN(V$19:V$25)) | AN21: {=SUMPRODUCT(W21:Y21, TRANSPOSE('Fund Ranking Criteria'!$D$39:$D$41))+SUMPRODUCT('Fund Ranking_Debt'!Z21:AG21, TRANSPOSE('Fund Ranking Criteria'!$D$30:$D$37))+SUMPRODUCT('Fund Ranking_Debt'!AH21:AM21, TRANSPOSE('Fund Ranking Criteria'!$D$43:$D$48))}
B22: Aditya Birla Sun Life Low Duration Fund - Reg - Growth | C22: =RANK(AN22,$AN$19:$AN$25,0) | E22: =B22 | F22: 7.52 | G22: 1.07 | H22: 1.15 | I22: 5.66 | J22: 4.77 | K22: 4.99 | L22: 5.68 | M22: 6.59 | N22: 6.65 | O22: 5.78 | P22: 6.5 | Q22: 13.03 | R22: 81.58 | S22: 6.76 | T22: 12.11 | U22: 0.24 | V22: -13.47 | W22: =(F22-MIN(F$19:F$25))/(MAX(F$19:F$25)-MIN(F$19:F$25)) | X22: =(MAX(G$19:G$25)-G22)/(MAX(G$19:G$25)-MIN(G$19:G$25)) | Y22: =(MAX(H$19:H$25)-H22)/(MAX(H$19:H$25)-MIN(H$19:H$25)) | Z22: =(I22-MIN(I$19:I$25))/(MAX(I$19:I$25)-MIN(I$19:I$25)) | AA22: =(J22-MIN(J$19:J$25))/(MAX(J$19:J$25)-MIN(J$19:J$25)) | AB22: =(K22-MIN(K$19:K$25))/(MAX(K$19:K$25)-MIN(K$19:K$25)) | AC22: =(L22-MIN(L$19:L$25))/(MAX(L$19:L$25)-MIN(L$19:L$25)) | AD22: =(M22-MIN(M$19:M$25))/(MAX(M$19:M$25)-MIN(M$19:M$25)) | AE22: =(N22-MIN(N$19:N$25))/(MAX(N$19:N$25)-MIN(N$19:N$25)) | AF22: =(O22-MIN(O$19:O$25))/(MAX(O$19:O$25)-MIN(O$19:O$25)) | AG22: =(P22-MIN(P$19:P$25))/(MAX(P$19:P$25)-MIN(P$19:P$25)) | ... AJ22: =(S22-MIN(S$19:S$25))/(MAX(S$19:S$25)-MIN(S$19:S$25)) | AK22: =(MAX(T$7:T$13)-T22)/(MAX(T$7:T$13)-MIN(T$7:T$13)) | AL22: =(MAX(U$7:U$13)-U22)/(MAX(U$7:U$13)-MIN(U$7:U$13)) | AM22: =(V22-MIN(V$19:V$25))/(MAX(V$19:V$25)-MIN(V$19:V$25)) | AN22: {=SUMPRODUCT(W22:Y22, TRANSPOSE('Fund Ranking Criteria'!$D$39:$D$41))+SUMPRODUCT('Fund Ranking_Debt'!Z22:AG22, TRANSPOSE('Fund Ranking Criteria'!$D$30:$D$37))+SUMPRODUCT('Fund Ranking_Debt'!AH22:AM22, TRANSPOSE('Fund Ranking Criteria'!$D$43:$D$48))}
B23: Kotak Low Duration Fund - Std - Growth | C23: =RANK(AN23,$AN$19:$AN$25,0) | E23: =B23 | F23: 7.73 | G23: 0.9 | H23: 0.96 | I23: 6.1 | J23: 4.93 | K23: 5.15 | L23: 5.79 | M23: 6.75 | N23: 6.77 | O23: 5.8 | P23: 6.67 | Q23: 12.21 | R23: 73.05 | S23: 2.79 | T23: 12.08 | U23: 0 | V23: -0.14 | W23: =(F23-MIN(F$19:F$25))/(MAX(F$19:F$25)-MIN(F$19:F$25)) | X23: =(MAX(G$19:G$25)-G23)/(MAX(G$19:G$25)-MIN(G$19:G$25)) | Y23: =(MAX(H$19:H$25)-H23)/(MAX(H$19:H$25)-MIN(H$19:H$25)) | Z23: =(I23-MIN(I$19:I$25))/(MAX(I$19:I$25)-MIN(I$19:I$25)) | AA23: =(J23-MIN(J$19:J$25))/(MAX(J$19:J$25)-MIN(J$19:J$25)) | AB23: =(K23-MIN(K$19:K$25))/(MAX(K$19:K$25)-MIN(K$19:K$25)) | AC23: =(L23-MIN(L$19:L$25))/(MAX(L$19:L$25)-MIN(L$19:L$25)) | AD23: =(M23-MIN(M$19:M$25))/(MAX(M$19:M$25)-MIN(M$19:M$25)) | AE23: =(N23-MIN(N$19:N$25))/(MAX(N$19:N$25)-MIN(N$19:N$25)) | AF23: =(O23-MIN(O$19:O$25))/(MAX(O$19:O$25)-MIN(O$19:O$25)) | AG23: =(P23-MIN(P$19:P$25))/(MAX(P$19:P$25)-MIN(P$19:P$25)) | ... AJ23: =(S23-MIN(S$19:S$25))/(MAX(S$19:S$25)-MIN(S$19:S$25)) | AK23: =(MAX(T$7:T$13)-T23)/(MAX(T$7:T$13)-MIN(T$7:T$13)) | AL23: =(MAX(U$7:U$13)-U23)/(MAX(U$7:U$13)-MIN(U$7:U$13)) | AM23: =(V23-MIN(V$19:V$25))/(MAX(V$19:V$25)-MIN(V$19:V$25)) | AN23: {=SUMPRODUCT(W23:Y23, TRANSPOSE('Fund Ranking Criteria'!$D$39:$D$41))+SUMPRODUCT('Fund Ranking_Debt'!Z23:AG23, TRANSPOSE('Fund Ranking Criteria'!$D$30:$D$37))+SUMPRODUCT('Fund Ranking_Debt'!AH23:AM23, TRANSPOSE('Fund Ranking Criteria'!$D$43:$D$48))}
B24: Nippon India Low Duration Fund - Reg - Growth | C24: =RANK(AN24,$AN$19:$AN$25,0) | E24: =B24 | F24: 7.63 | G24: 1 | H24: 1.06 | I24: 5.91 | J24: 5.1 | K24: 5.36 | L24: 5.97 | M24: 6.89 | N24: 6.88 | O24: 5.96 | P24: 6.5 | Q24: 11.3 | R24: 68.26 | S24: 6.49 | T24: 8.84 | U24: 0.09 | V24: 5.02 | W24: =(F24-MIN(F$19:F$25))/(MAX(F$19:F$25)-MIN(F$19:F$25)) | X24: =(MAX(G$19:G$25)-G24)/(MAX(G$19:G$25)-MIN(G$19:G$25)) | Y24: =(MAX(H$19:H$25)-H24)/(MAX(H$19:H$25)-MIN(H$19:H$25)) | Z24: =(I24-MIN(I$19:I$25))/(MAX(I$19:I$25)-MIN(I$19:I$25)) | AA24: =(J24-MIN(J$19:J$25))/(MAX(J$19:J$25)-MIN(J$19:J$25)) | AB24: =(K24-MIN(K$19:K$25))/(MAX(K$19:K$25)-MIN(K$19:K$25)) | AC24: =(L24-MIN(L$19:L$25))/(MAX(L$19:L$25)-MIN(L$19:L$25)) | AD24: =(M24-MIN(M$19:M$25))/(MAX(M$19:M$25)-MIN(M$19:M$25)) | AE24: =(N24-MIN(N$19:N$25))/(MAX(N$19:N$25)-MIN(N$19:N$25)) | AF24: =(O24-MIN(O$19:O$25))/(MAX(O$19:O$25)-MIN(O$19:O$25)) | AG24: =(P24-MIN(P$19:P$25))/(MAX(P$19:P$25)-MIN(P$19:P$25)) | ... AJ24: =(S24-MIN(S$19:S$25))/(MAX(S$19:S$25)-MIN(S$19:S$25)) | AK24: =(MAX(T$7:T$13)-T24)/(MAX(T$7:T$13)-MIN(T$7:T$13)) | AL24: =(MAX(U$7:U$13)-U24)/(MAX(U$7:U$13)-MIN(U$7:U$13)) | AM24: =(V24-MIN(V$19:V$25))/(MAX(V$19:V$25)-MIN(V$19:V$25)) | AN24: {=SUMPRODUCT(W24:Y24, TRANSPOSE('Fund Ranking Criteria'!$D$39:$D$41))+SUMPRODUCT('Fund Ranking_Debt'!Z24:AG24, TRANSPOSE('Fund Ranking Criteria'!$D$30:$D$37))+SUMPRODUCT('Fund Ranking_Debt'!AH24:AM24, TRANSPOSE('Fund Ranking Criteria'!$D$43:$D$48))}
B25: UTI Low Duration Fund - Reg - Growth | C25: =RANK(AN25,$AN$19:$AN$25,0) | E25: =B25 | F25: 7.89 | G25: 0.87 | H25: 0.91 | I25: 6.41 | J25: 5.51 | K25: 5.73 | L25: 6.31 | M25: 7.23 | N25: 7.2 | O25: 7.26 | P25: 6.02 | Q25: 3.32 | R25: 74.2 | S25: 4.45 | T25: 7.56 | U25: 0 | V25: 10.46 | W25: =(F25-MIN(F$19:F$25))/(MAX(F$19:F$25)-MIN(F$19:F$25)) | X25: =(MAX(G$19:G$25)-G25)/(MAX(G$19:G$25)-MIN(G$19:G$25)) | Y25: =(MAX(H$19:H$25)-H25)/(MAX(H$19:H$25)-MIN(H$19:H$25)) | Z25: =(I25-MIN(I$19:I$25))/(MAX(I$19:I$25)-MIN(I$19:I$25)) | AA25: =(J25-MIN(J$19:J$25))/(MAX(J$19:J$25)-MIN(J$19:J$25)) | AB25: =(K25-MIN(K$19:K$25))/(MAX(K$19:K$25)-MIN(K$19:K$25)) | AC25: =(L25-MIN(L$19:L$25))/(MAX(L$19:L$25)-MIN(L$19:L$25)) | AD25: =(M25-MIN(M$19:M$25))/(MAX(M$19:M$25)-MIN(M$19:M$25)) | AE25: =(N25-MIN(N$19:N$25))/(MAX(N$19:N$25)-MIN(N$19:N$25)) | AF25: =(O25-MIN(O$19:O$25))/(MAX(O$19:O$25)-MIN(O$19:O$25)) | AG25: =(P25-MIN(P$19:P$25))/(MAX(P$19:P$25)-MIN(P$19:P$25)) | ... AJ25: =(S25-MIN(S$19:S$25))/(MAX(S$19:S$25)-MIN(S$19:S$25)) | AK25: =(MAX(T$7:T$13)-T25)/(MAX(T$7:T$13)-MIN(T$7:T$13)) | AL25: =(MAX(U$7:U$13)-U25)/(MAX(U$7:U$13)-MIN(U$7:U$13)) | AM25: =(V25-MIN(V$19:V$25))/(MAX(V$19:V$25)-MIN(V$19:V$25)) | AN25: {=SUMPRODUCT(W25:Y25, TRANSPOSE('Fund Ranking Criteria'!$D$39:$D$41))+SUMPRODUCT('Fund Ranking_Debt'!Z25:AG25, TRANSPOSE('Fund Ranking Criteria'!$D$30:$D$37))+SUMPRODUCT('Fund Ranking_Debt'!AH25:AM25, TRANSPOSE('Fund Ranking Criteria'!$D$43:$D$48))}
B28: Short Duration Fund
AN29: Score
B30: Funds | C30: Rank | F30: YTM | G30: Modified Duration | H30: Macaulay Duration | I30: 3 Months | J30: 6 Months | K30: 9 Months | L30: 1 Year | M30: 2 Years | N30: 3 Years | O30: 5 Years | P30: 10 Years | Q30: Sovereign | R30: AAA/A1+ | S30: AA+ | T30: AA/AA- | U30: Below AA- | V30: Cash and Fixed Deposits | W30: =F30 | X30: =G30 | Y30: =H30 | Z30: =I30 | AA30: =J30 | AB30: =K30 | AC30: =L30 | AD30: =M30 | ... AM30: =V30
B31: ICICI Prudential Short Term Fund - Growth | C31: =RANK(AN31,$AN$31:$AN$37,0) | E31: =B31 | F31: 7.89 | G31: 2.4 | H31: 2.52 | I31: 5.1 | J31: 4.53 | K31: 4.84 | L31: 5.7 | M31: 7.35 | N31: 7.29 | O31: 6.41 | P31: 7.25 | Q31: 15.73 | R31: 62.82 | S31: 9.71 | T31: 10.5 | U31: -5.32 | V31: 1.23 | W31: =(F31-MIN(F$31:F$37))/(MAX(F$31:F$37)-MIN(F$31:F$37)) | X31: =(MAX(G$31:G$37)-G31)/(MAX(G$31:G$37)-MIN(G$31:G$37)) | Y31: =(MAX(H$31:H$37)-H31)/(MAX(H$31:H$37)-MIN(H$31:H$37)) | Z31: =(I31-MIN(I$31:I$37))/(MAX(I$31:I$37)-MIN(I$31:I$37)) | AA31: =(J31-MIN(J$31:J$37))/(MAX(J$31:J$37)-MIN(J$31:J$37)) | AB31: =(K31-MIN(K$31:K$37))/(MAX(K$31:K$37)-MIN(K$31:K$37)) | AC31: =(L31-MIN(L$31:L$37))/(MAX(L$31:L$37)-MIN(L$31:L$37)) | AD31: =(M31-MIN(M$31:M$37))/(MAX(M$31:M$37)-MIN(M$31:M$37)) | AE31: =(N31-MIN(N$31:N$37))/(MAX(N$31:N$37)-MIN(N$31:N$37)) | AF31: =(O31-MIN(O$31:O$37))/(MAX(O$31:O$37)-MIN(O$31:O$37)) | AG31: =(P31-MIN(P$31:P$37))/(MAX(P$31:P$37)-MIN(P$31:P$37)) | ... AJ31: =(S31-MIN(S$31:S$37))/(MAX(S$31:S$37)-MIN(S$31:S$37)) | AK31: =(MAX(T$31:T$37)-T31)/(MAX(T$31:T$37)-MIN(T$31:T$37)) | AL31: =(MAX(U$31:U$37)-U31)/(MAX(U$31:U$37)-MIN(U$31:U$37)) | AM31: =(V31-MIN(V$31:V$37))/(MAX(V$31:V$37)-MIN(V$31:V$37)) | AN31: {=SUMPRODUCT(W31:Y31, TRANSPOSE('Fund Ranking Criteria'!$E$39:$E$41))+SUMPRODUCT('Fund Ranking_Debt'!Z31:AG31, TRANSPOSE('Fund Ranking Criteria'!$E$30:$E$37))+SUMPRODUCT('Fund Ranking_Debt'!AH31:AM31, TRANSPOSE('Fund Ranking Criteria'!$E$43:$E$48))}
B32: Kotak Bond Short Term Fund - Reg - Growth | C32: =RANK(AN32,$AN$31:$AN$37,0) | E32: =B32 | F32: 7.77 | G32: 2.26 | H32: 2.4 | I32: 4.52 | J32: 3.43 | K32: 3.82 | L32: 4.66 | M32: 6.88 | N32: 6.7 | O32: 5.66 | P32: 6.65 | Q32: 15.24 | R32: 88.5 | S32: 0 | T32: 0 | U32: 0 | V32: -3.74 | W32: =(F32-MIN(F$31:F$37))/(MAX(F$31:F$37)-MIN(F$31:F$37)) | X32: =(MAX(G$31:G$37)-G32)/(MAX(G$31:G$37)-MIN(G$31:G$37)) | Y32: =(MAX(H$31:H$37)-H32)/(MAX(H$31:H$37)-MIN(H$31:H$37)) | Z32: =(I32-MIN(I$31:I$37))/(MAX(I$31:I$37)-MIN(I$31:I$37)) | AA32: =(J32-MIN(J$31:J$37))/(MAX(J$31:J$37)-MIN(J$31:J$37)) | AB32: =(K32-MIN(K$31:K$37))/(MAX(K$31:K$37)-MIN(K$31:K$37)) | AC32: =(L32-MIN(L$31:L$37))/(MAX(L$31:L$37)-MIN(L$31:L$37)) | AD32: =(M32-MIN(M$31:M$37))/(MAX(M$31:M$37)-MIN(M$31:M$37)) | AE32: =(N32-MIN(N$31:N$37))/(MAX(N$31:N$37)-MIN(N$31:N$37)) | AF32: =(O32-MIN(O$31:O$37))/(MAX(O$31:O$37)-MIN(O$31:O$37)) | AG32: =(P32-MIN(P$31:P$37))/(MAX(P$31:P$37)-MIN(P$31:P$37)) | ... AJ32: =(S32-MIN(S$31:S$37))/(MAX(S$31:S$37)-MIN(S$31:S$37)) | AK32: =(MAX(T$31:T$37)-T32)/(MAX(T$31:T$37)-MIN(T$31:T$37)) | AL32: =(MAX(U$31:U$37)-U32)/(MAX(U$31:U$37)-MIN(U$31:U$37)) | AM32: =(V32-MIN(V$31:V$37))/(MAX(V$31:V$37)-MIN(V$31:V$37)) | AN32: {=SUMPRODUCT(W32:Y32, TRANSPOSE('Fund Ranking Criteria'!$D$39:$D$41))+SUMPRODUCT('Fund Ranking_Debt'!Z32:AG32, TRANSPOSE('Fund Ranking Criteria'!$D$30:$D$37))+SUMPRODUCT('Fund Ranking_Debt'!AH32:AM32, TRANSPOSE('Fund Ranking Criteria'!$D$43:$D$48))}
B33: HDFC Short Term Debt Fund - Growth | C33: =RANK(AN33,$AN$31:$AN$37,0) | E33: =B33 | F33: 7.85 | G33: 2.38 | H33: 2.53 | I33: 5.13 | J33: 3.99 | K33: 4.5 | L33: 5.39 | M33: 7.37 | N33: 7.27 | O33: 6.19 | P33: 7.21 | Q33: 13.34 | R33: 71.63 | S33: 5.84 | T33: 9.59 | U33: 0 | V33: -0.41 | W33: =(F33-MIN(F$31:F$37))/(MAX(F$31:F$37)-MIN(F$31:F$37)) | X33: =(MAX(G$31:G$37)-G33)/(MAX(G$31:G$37)-MIN(G$31:G$37)) | Y33: =(MAX(H$31:H$37)-H33)/(MAX(H$31:H$37)-MIN(H$31:H$37)) | Z33: =(I33-MIN(I$31:I$37))/(MAX(I$31:I$37)-MIN(I$31:I$37)) | AA33: =(J33-MIN(J$31:J$37))/(MAX(J$31:J$37)-MIN(J$31:J$37)) | AB33: =(K33-MIN(K$31:K$37))/(MAX(K$31:K$37)-MIN(K$31:K$37)) | AC33: =(L33-MIN(L$31:L$37))/(MAX(L$31:L$37)-MIN(L$31:L$37)) | AD33: =(M33-MIN(M$31:M$37))/(MAX(M$31:M$37)-MIN(M$31:M$37)) | AE33: =(N33-MIN(N$31:N$37))/(MAX(N$31:N$37)-MIN(N$31:N$37)) | AF33: =(O33-MIN(O$31:O$37))/(MAX(O$31:O$37)-MIN(O$31:O$37)) | AG33: =(P33-MIN(P$31:P$37))/(MAX(P$31:P$37)-MIN(P$31:P$37)) | ... AJ33: =(S33-MIN(S$31:S$37))/(MAX(S$31:S$37)-MIN(S$31:S$37)) | AK33: =(MAX(T$31:T$37)-T33)/(MAX(T$31:T$37)-MIN(T$31:T$37)) | AL33: =(MAX(U$31:U$37)-U33)/(MAX(U$31:U$37)-MIN(U$31:U$37)) | AM33: =(V33-MIN(V$31:V$37))/(MAX(V$31:V$37)-MIN(V$31:V$37)) | AN33: {=SUMPRODUCT(W33:Y33, TRANSPOSE('Fund Ranking Criteria'!$D$39:$D$41))+SUMPRODUCT('Fund Ranking_Debt'!Z33:AG33, TRANSPOSE('Fund Ranking Criteria'!$D$30:$D$37))+SUMPRODUCT('Fund Ranking_Debt'!AH33:AM33, TRANSPOSE('Fund Ranking Criteria'!$D$43:$D$48))}
B34: SBI Short Term Debt Fund - Growth | C34: =RANK(AN34,$AN$31:$AN$37,0) | E34: =B34 | F34: 7.79 | G34: 2.28 | H34: 2.4 | I34: 4.46 | J34: 3.47 | K34: 4.13 | L34: 5.1 | M34: 7.13 | N34: 6.88 | O34: 5.84 | P34: 6.71 | Q34: 16.25 | R34: 66.15 | S34: 8.38 | T34: 6.58 | U34: 0 | V34: 2.64 | W34: =(F34-MIN(F$31:F$37))/(MAX(F$31:F$37)-MIN(F$31:F$37)) | X34: =(MAX(G$31:G$37)-G34)/(MAX(G$31:G$37)-MIN(G$31:G$37)) | Y34: =(MAX(H$31:H$37)-H34)/(MAX(H$31:H$37)-MIN(H$31:H$37)) | Z34: =(I34-MIN(I$31:I$37))/(MAX(I$31:I$37)-MIN(I$31:I$37)) | AA34: =(J34-MIN(J$31:J$37))/(MAX(J$31:J$37)-MIN(J$31:J$37)) | AB34: =(K34-MIN(K$31:K$37))/(MAX(K$31:K$37)-MIN(K$31:K$37)) | AC34: =(L34-MIN(L$31:L$37))/(MAX(L$31:L$37)-MIN(L$31:L$37)) | AD34: =(M34-MIN(M$31:M$37))/(MAX(M$31:M$37)-MIN(M$31:M$37)) | AE34: =(N34-MIN(N$31:N$37))/(MAX(N$31:N$37)-MIN(N$31:N$37)) | AF34: =(O34-MIN(O$31:O$37))/(MAX(O$31:O$37)-MIN(O$31:O$37)) | AG34: =(P34-MIN(P$31:P$37))/(MAX(P$31:P$37)-MIN(P$31:P$37)) | ... AJ34: =(S34-MIN(S$31:S$37))/(MAX(S$31:S$37)-MIN(S$31:S$37)) | AK34: =(MAX(T$31:T$37)-T34)/(MAX(T$31:T$37)-MIN(T$31:T$37)) | AL34: =(MAX(U$31:U$37)-U34)/(MAX(U$31:U$37)-MIN(U$31:U$37)) | AM34: =(V34-MIN(V$31:V$37))/(MAX(V$31:V$37)-MIN(V$31:V$37)) | AN34: {=SUMPRODUCT(W34:Y34, TRANSPOSE('Fund Ranking Criteria'!$D$39:$D$41))+SUMPRODUCT('Fund Ranking_Debt'!Z34:AG34, TRANSPOSE('Fund Ranking Criteria'!$D$30:$D$37))+SUMPRODUCT('Fund Ranking_Debt'!AH34:AM34, TRANSPOSE('Fund Ranking Criteria'!$D$43:$D$48))}
B35: Aditya Birla Sun Life Short Term Fund - Reg - Growth | C35: =RANK(AN35,$AN$31:$AN$37,0) | E35: =B35 | F35: 7.84 | G35: 2.78 | H35: 2.97 | I35: 5.04 | J35: 3.84 | K35: 4.38 | L35: 5.17 | M35: 7.23 | N35: 7 | O35: 6.15 | P35: 7.08 | Q35: 14.07 | R35: 73.37 | S35: 6.16 | T35: 14.38 | U35: 0.43 | V35: -7.97 | W35: =(F35-MIN(F$31:F$37))/(MAX(F$31:F$37)-MIN(F$31:F$37)) | X35: =(MAX(G$31:G$37)-G35)/(MAX(G$31:G$37)-MIN(G$31:G$37)) | Y35: =(MAX(H$31:H$37)-H35)/(MAX(H$31:H$37)-MIN(H$31:H$37)) | Z35: =(I35-MIN(I$31:I$37))/(MAX(I$31:I$37)-MIN(I$31:I$37)) | AA35: =(J35-MIN(J$31:J$37))/(MAX(J$31:J$37)-MIN(J$31:J$37)) | AB35: =(K35-MIN(K$31:K$37))/(MAX(K$31:K$37)-MIN(K$31:K$37)) | AC35: =(L35-MIN(L$31:L$37))/(MAX(L$31:L$37)-MIN(L$31:L$37)) | AD35: =(M35-MIN(M$31:M$37))/(MAX(M$31:M$37)-MIN(M$31:M$37)) | AE35: =(N35-MIN(N$31:N$37))/(MAX(N$31:N$37)-MIN(N$31:N$37)) | AF35: =(O35-MIN(O$31:O$37))/(MAX(O$31:O$37)-MIN(O$31:O$37)) | AG35: =(P35-MIN(P$31:P$37))/(MAX(P$31:P$37)-MIN(P$31:P$37)) | ... AJ35: =(S35-MIN(S$31:S$37))/(MAX(S$31:S$37)-MIN(S$31:S$37)) | AK35: =(MAX(T$31:T$37)-T35)/(MAX(T$31:T$37)-MIN(T$31:T$37)) | AL35: =(MAX(U$31:U$37)-U35)/(MAX(U$31:U$37)-MIN(U$31:U$37)) | AM35: =(V35-MIN(V$31:V$37))/(MAX(V$31:V$37)-MIN(V$31:V$37)) | AN35: {=SUMPRODUCT(W35:Y35, TRANSPOSE('Fund Ranking Criteria'!$D$39:$D$41))+SUMPRODUCT('Fund Ranking_Debt'!Z35:AG35, TRANSPOSE('Fund Ranking Criteria'!$D$30:$D$37))+SUMPRODUCT('Fund Ranking_Debt'!AH35:AM35, TRANSPOSE('Fund Ranking Criteria'!$D$43:$D$48))}
B36: Nippon India Short Duration Fund - Reg - Growth | C36: =RANK(AN36,$AN$31:$AN$37,0) | E36: =B36 | F36: 7.78 | G36: 2.4 | H36: 2.52 | I36: 4.87 | J36: 3.59 | K36: 4.21 | L36: 5.25 | M36: 7.31 | N36: 7.07 | O36: 6.02 | P36: 6.79 | Q36: 21.03 | R36: 60.87 | S36: 6.83 | T36: 8.51 | U36: 0 | V36: 2.76 | W36: =(F36-MIN(F$31:F$37))/(MAX(F$31:F$37)-MIN(F$31:F$37)) | X36: =(MAX(G$31:G$37)-G36)/(MAX(G$31:G$37)-MIN(G$31:G$37)) | Y36: =(MAX(H$31:H$37)-H36)/(MAX(H$31:H$37)-MIN(H$31:H$37)) | Z36: =(I36-MIN(I$31:I$37))/(MAX(I$31:I$37)-MIN(I$31:I$37)) | AA36: =(J36-MIN(J$31:J$37))/(MAX(J$31:J$37)-MIN(J$31:J$37)) | AB36: =(K36-MIN(K$31:K$37))/(MAX(K$31:K$37)-MIN(K$31:K$37)) | AC36: =(L36-MIN(L$31:L$37))/(MAX(L$31:L$37)-MIN(L$31:L$37)) | AD36: =(M36-MIN(M$31:M$37))/(MAX(M$31:M$37)-MIN(M$31:M$37)) | AE36: =(N36-MIN(N$31:N$37))/(MAX(N$31:N$37)-MIN(N$31:N$37)) | AF36: =(O36-MIN(O$31:O$37))/(MAX(O$31:O$37)-MIN(O$31:O$37)) | AG36: =(P36-MIN(P$31:P$37))/(MAX(P$31:P$37)-MIN(P$31:P$37)) | ... AJ36: =(S36-MIN(S$31:S$37))/(MAX(S$31:S$37)-MIN(S$31:S$37)) | AK36: =(MAX(T$31:T$37)-T36)/(MAX(T$31:T$37)-MIN(T$31:T$37)) | AL36: =(MAX(U$31:U$37)-U36)/(MAX(U$31:U$37)-MIN(U$31:U$37)) | AM36: =(V36-MIN(V$31:V$37))/(MAX(V$31:V$37)-MIN(V$31:V$37)) | AN36: {=SUMPRODUCT(W36:Y36, TRANSPOSE('Fund Ranking Criteria'!$D$39:$D$41))+SUMPRODUCT('Fund Ranking_Debt'!Z36:AG36, TRANSPOSE('Fund Ranking Criteria'!$D$30:$D$37))+SUMPRODUCT('Fund Ranking_Debt'!AH36:AM36, TRANSPOSE('Fund Ranking Criteria'!$D$43:$D$48))}
B37: UTI Short Duration Fund - Reg - Growth | C37: =RANK(AN37,$AN$31:$AN$37,0) | E37: =B37 | F37: 7.86 | G37: 2.38 | H37: 2.51 | I37: 4.78 | J37: 3.51 | K37: 4.05 | L37: 4.95 | M37: 6.9 | N37: 6.91 | O37: 6.91 | P37: 6.07 | Q37: 15.86 | R37: 67.45 | S37: 5.37 | T37: 9.41 | U37: 0 | V37: 1.91 | W37: =(F37-MIN(F$31:F$37))/(MAX(F$31:F$37)-MIN(F$31:F$37)) | X37: =(MAX(G$31:G$37)-G37)/(MAX(G$31:G$37)-MIN(G$31:G$37)) | Y37: =(MAX(H$31:H$37)-H37)/(MAX(H$31:H$37)-MIN(H$31:H$37)) | Z37: =(I37-MIN(I$31:I$37))/(MAX(I$31:I$37)-MIN(I$31:I$37)) | AA37: =(J37-MIN(J$31:J$37))/(MAX(J$31:J$37)-MIN(J$31:J$37)) | AB37: =(K37-MIN(K$31:K$37))/(MAX(K$31:K$37)-MIN(K$31:K$37)) | AC37: =(L37-MIN(L$31:L$37))/(MAX(L$31:L$37)-MIN(L$31:L$37)) | AD37: =(M37-MIN(M$31:M$37))/(MAX(M$31:M$37)-MIN(M$31:M$37)) | AE37: =(N37-MIN(N$31:N$37))/(MAX(N$31:N$37)-MIN(N$31:N$37)) | AF37: =(O37-MIN(O$31:O$37))/(MAX(O$31:O$37)-MIN(O$31:O$37)) | AG37: =(P37-MIN(P$31:P$37))/(MAX(P$31:P$37)-MIN(P$31:P$37)) | ... AJ37: =(S37-MIN(S$31:S$37))/(MAX(S$31:S$37)-MIN(S$31:S$37)) | AK37: =(MAX(T$31:T$37)-T37)/(MAX(T$31:T$37)-MIN(T$31:T$37)) | AL37: =(MAX(U$31:U$37)-U37)/(MAX(U$31:U$37)-MIN(U$31:U$37)) | AM37: =(V37-MIN(V$31:V$37))/(MAX(V$31:V$37)-MIN(V$31:V$37)) | AN37: {=SUMPRODUCT(W37:Y37, TRANSPOSE('Fund Ranking Criteria'!$D$39:$D$41))+SUMPRODUCT('Fund Ranking_Debt'!Z37:AG37, TRANSPOSE('Fund Ranking Criteria'!$D$30:$D$37))+SUMPRODUCT('Fund Ranking_Debt'!AH37:AM37, TRANSPOSE('Fund Ranking Criteria'!$D$43:$D$48))}
B39: Medium Duration Fund
AN40: Score
B41: Funds | C41: Rank | F41: YTM | G41: Modified Duration | H41: Macaulay Duration | I41: 3 Months | J41: 6 Months | K41: 9 Months | L41: 1 Year | M41: 2 Years | N41: 3 Years | O41: 5 Years | P41: 10 Years | Q41: Sovereign | R41: AAA/A1+ | S41: AA+ | T41: AA/AA- | U41: Below AA- | V41: Cash and Fixed Deposits | W41: =F41 | X41: =G41 | Y41: =H41 | Z41: =I41 | AA41: =J41 | AB41: =K41 | AC41: =L41 | AD41: =M41 | ... AM41: =V41
B42: SBI Magnum Medium Duration Fund - Growth | C42: =RANK(AN42,$AN$42:$AN$48,0) | E42: =B42 | F42: 7.23 | G42: 3.78 | H42: 3.94 | I42: 6.62 | J42: 9.86 | K42: 8.69 | L42: 8.96 | M42: 8.01 | N42: 7.84 | O42: 6.39 | P42: 7.92 | Q42: 40.45 | R42: 7.66 | S42: 16.45 | T42: 23.5 | U42: 6.89 | V42: 4.73 | W42: =(F42-MIN(F$42:F$48))/(MAX(F$42:F$48)-MIN(F$42:F$48)) | X42: =(MAX(G$42:G$48)-G42)/(MAX(G$42:G$48)-MIN(G$42:G$48)) | Y42: =(MAX(H$42:H$48)-H42)/(MAX(H$42:H$48)-MIN(H$42:H$48)) | Z42: =(I42-MIN(I$42:I$48))/(MAX(I$42:I$48)-MIN(I$42:I$48)) | AA42: =(J42-MIN(J$42:J$48))/(MAX(J$42:J$48)-MIN(J$42:J$48)) | AB42: =(K42-MIN(K$42:K$48))/(MAX(K$42:K$48)-MIN(K$42:K$48)) | AC42: =(L42-MIN(L$42:L$48))/(MAX(L$42:L$48)-MIN(L$42:L$48)) | AD42: =(M42-MIN(M$42:M$48))/(MAX(M$42:M$48)-MIN(M$42:M$48)) | AE42: =(N42-MIN(N$42:N$48))/(MAX(N$42:N$48)-MIN(N$42:N$48)) | AF42: =(O42-MIN(O$42:O$48))/(MAX(O$42:O$48)-MIN(O$42:O$48)) | AG42: =(P42-MIN(P$42:P$48))/(MAX(P$42:P$48)-MIN(P$42:P$48)) | ... AJ42: =(S42-MIN(S$42:S$48))/(MAX(S$42:S$48)-MIN(S$42:S$48)) | AK42: =(MAX(T$42:T$48)-T42)/(MAX(T$42:T$48)-MIN(T$42:T$48)) | AL42: =(MAX(U$42:U$48)-U42)/(MAX(U$42:U$48)-MIN(U$42:U$48)) | AM42: =(V42-MIN(V$42:V$48))/(MAX(V$42:V$48)-MIN(V$42:V$48)) | AN42: {=SUMPRODUCT(W42:Y42, TRANSPOSE('Fund Ranking Criteria'!$F$39:$F$41))+SUMPRODUCT('Fund Ranking_Debt'!Z42:AG42, TRANSPOSE('Fund Ranking Criteria'!$F$30:$F$37))+SUMPRODUCT('Fund Ranking_Debt'!AH42:AM42, TRANSPOSE('Fund Ranking Criteria'!$F$43:$F$48))}
B43: ICICI Prudential Medium Term Bond Fund - Growth | C43: =RANK(AN43,$AN$42:$AN$48,0) | E43: =B43 | F43: 8.44 | G43: 2.89 | H43: 3.04 | I43: 5.33 | J43: 4.91 | K43: 5.69 | L43: 6.45 | M43: 8.02 | N43: 7.53 | O43: 6.63 | P43: 7.31 | Q43: 13.88 | R43: 18.46 | S43: 18.78 | T43: 36.08 | U43: 0 | V43: 12.8 | W43: =(F43-MIN(F$42:F$48))/(MAX(F$42:F$48)-MIN(F$42:F$48)) | X43: =(MAX(G$42:G$48)-G43)/(MAX(G$42:G$48)-MIN(G$42:G$48)) | Y43: =(MAX(H$42:H$48)-H43)/(MAX(H$42:H$48)-MIN(H$42:H$48)) | Z43: =(I43-MIN(I$42:I$48))/(MAX(I$42:I$48)-MIN(I$42:I$48)) | AA43: =(J43-MIN(J$42:J$48))/(MAX(J$42:J$48)-MIN(J$42:J$48)) | AB43: =(K43-MIN(K$42:K$48))/(MAX(K$42:K$48)-MIN(K$42:K$48)) | AC43: =(L43-MIN(L$42:L$48))/(MAX(L$42:L$48)-MIN(L$42:L$48)) | AD43: =(M43-MIN(M$42:M$48))/(MAX(M$42:M$48)-MIN(M$42:M$48)) | AE43: =(N43-MIN(N$42:N$48))/(MAX(N$42:N$48)-MIN(N$42:N$48)) | AF43: =(O43-MIN(O$42:O$48))/(MAX(O$42:O$48)-MIN(O$42:O$48)) | AG43: =(P43-MIN(P$42:P$48))/(MAX(P$42:P$48)-MIN(P$42:P$48)) | ... AJ43: =(S43-MIN(S$42:S$48))/(MAX(S$42:S$48)-MIN(S$42:S$48)) | AK43: =(MAX(T$42:T$48)-T43)/(MAX(T$42:T$48)-MIN(T$42:T$48)) | AL43: =(MAX(U$42:U$48)-U43)/(MAX(U$42:U$48)-MIN(U$42:U$48)) | AM43: =(V43-MIN(V$42:V$48))/(MAX(V$42:V$48)-MIN(V$42:V$48)) | AN43: {=SUMPRODUCT(W43:Y43, TRANSPOSE('Fund Ranking Criteria'!$F$39:$F$41))+SUMPRODUCT('Fund Ranking_Debt'!Z43:AG43, TRANSPOSE('Fund Ranking Criteria'!$F$30:$F$37))+SUMPRODUCT('Fund Ranking_Debt'!AH43:AM43, TRANSPOSE('Fund Ranking Criteria'!$F$43:$F$48))}
B44: HDFC Medium Term Debt Fund - Growth | C44: =RANK(AN44,$AN$42:$AN$48,0) | E44: =B44 | F44: 8.39 | G44: 3.07 | H44: 3.23 | I44: 5.59 | J44: 4.34 | K44: 4.62 | L44: 5.13 | M44: 7.33 | N44: 7.04 | O44: 6.11 | P44: 6.98 | Q44: 17.73 | R44: 23.96 | S44: 17.45 | T44: 27.34 | U44: 6.42 | V44: 7.1 | W44: =(F44-MIN(F$42:F$48))/(MAX(F$42:F$48)-MIN(F$42:F$48)) | X44: =(MAX(G$42:G$48)-G44)/(MAX(G$42:G$48)-MIN(G$42:G$48)) | Y44: =(MAX(H$42:H$48)-H44)/(MAX(H$42:H$48)-MIN(H$42:H$48)) | Z44: =(I44-MIN(I$42:I$48))/(MAX(I$42:I$48)-MIN(I$42:I$48)) | AA44: =(J44-MIN(J$42:J$48))/(MAX(J$42:J$48)-MIN(J$42:J$48)) | AB44: =(K44-MIN(K$42:K$48))/(MAX(K$42:K$48)-MIN(K$42:K$48)) | AC44: =(L44-MIN(L$42:L$48))/(MAX(L$42:L$48)-MIN(L$42:L$48)) | AD44: =(M44-MIN(M$42:M$48))/(MAX(M$42:M$48)-MIN(M$42:M$48)) | AE44: =(N44-MIN(N$42:N$48))/(MAX(N$42:N$48)-MIN(N$42:N$48)) | AF44: =(O44-MIN(O$42:O$48))/(MAX(O$42:O$48)-MIN(O$42:O$48)) | AG44: =(P44-MIN(P$42:P$48))/(MAX(P$42:P$48)-MIN(P$42:P$48)) | ... AJ44: =(S44-MIN(S$42:S$48))/(MAX(S$42:S$48)-MIN(S$42:S$48)) | AK44: =(MAX(T$42:T$48)-T44)/(MAX(T$42:T$48)-MIN(T$42:T$48)) | AL44: =(MAX(U$42:U$48)-U44)/(MAX(U$42:U$48)-MIN(U$42:U$48)) | AM44: =(V44-MIN(V$42:V$48))/(MAX(V$42:V$48)-MIN(V$42:V$48)) | AN44: {=SUMPRODUCT(W44:Y44, TRANSPOSE('Fund Ranking Criteria'!$F$39:$F$41))+SUMPRODUCT('Fund Ranking_Debt'!Z44:AG44, TRANSPOSE('Fund Ranking Criteria'!$F$30:$F$37))+SUMPRODUCT('Fund Ranking_Debt'!AH44:AM44, TRANSPOSE('Fund Ranking Criteria'!$F$43:$F$48))}
B45: Aditya Birla Sun Life Medium Term Plan - Reg - Growth | C45: =RANK(AN45,$AN$42:$AN$48,0) | E45: =B45 | F45: 8.4 | G45: 2.86 | H45: 3.03 | I45: 6.3 | J45: 8.26 | K45: 7.77 | L45: 8.27 | M45: 11.3 | N45: 9.61 | O45: 11.83 | P45: 8.5 | Q45: 19.53 | R45: 23.67 | S45: 6.95 | T45: 29.24 | U45: 13.23 | V45: 7.38 | W45: =(F45-MIN(F$42:F$48))/(MAX(F$42:F$48)-MIN(F$42:F$48)) | X45: =(MAX(G$42:G$48)-G45)/(MAX(G$42:G$48)-MIN(G$42:G$48)) | Y45: =(MAX(H$42:H$48)-H45)/(MAX(H$42:H$48)-MIN(H$42:H$48)) | Z45: =(I45-MIN(I$42:I$48))/(MAX(I$42:I$48)-MIN(I$42:I$48)) | AA45: =(J45-MIN(J$42:J$48))/(MAX(J$42:J$48)-MIN(J$42:J$48)) | AB45: =(K45-MIN(K$42:K$48))/(MAX(K$42:K$48)-MIN(K$42:K$48)) | AC45: =(L45-MIN(L$42:L$48))/(MAX(L$42:L$48)-MIN(L$42:L$48)) | AD45: =(M45-MIN(M$42:M$48))/(MAX(M$42:M$48)-MIN(M$42:M$48)) | AE45: =(N45-MIN(N$42:N$48))/(MAX(N$42:N$48)-MIN(N$42:N$48)) | AF45: =(O45-MIN(O$42:O$48))/(MAX(O$42:O$48)-MIN(O$42:O$48)) | AG45: =(P45-MIN(P$42:P$48))/(MAX(P$42:P$48)-MIN(P$42:P$48)) | ... AJ45: =(S45-MIN(S$42:S$48))/(MAX(S$42:S$48)-MIN(S$42:S$48)) | AK45: =(MAX(T$42:T$48)-T45)/(MAX(T$42:T$48)-MIN(T$42:T$48)) | AL45: =(MAX(U$42:U$48)-U45)/(MAX(U$42:U$48)-MIN(U$42:U$48)) | AM45: =(V45-MIN(V$42:V$48))/(MAX(V$42:V$48)-MIN(V$42:V$48)) | AN45: {=SUMPRODUCT(W45:Y45, TRANSPOSE('Fund Ranking Criteria'!$F$39:$F$41))+SUMPRODUCT('Fund Ranking_Debt'!Z45:AG45, TRANSPOSE('Fund Ranking Criteria'!$F$30:$F$37))+SUMPRODUCT('Fund Ranking_Debt'!AH45:AM45, TRANSPOSE('Fund Ranking Criteria'!$F$43:$F$48))}
B46: Kotak Medium Term Fund - Reg - Growth | C46: =RANK(AN46,$AN$42:$AN$48,0) | E46: =B46 | F46: 8.66 | G46: 3.09 | H46: 3.27 | I46: 4.27 | J46: 3.88 | K46: 5.3 | L46: 6.17 | M46: 7.9 | N46: 7.54 | O46: 6.43 | P46: 6.79 | Q46: 11.13 | R46: 24.25 | S46: 14.52 | T46: 37.22 | U46: 7.6 | V46: 5.29 | W46: =(F46-MIN(F$42:F$48))/(MAX(F$42:F$48)-MIN(F$42:F$48)) | X46: =(MAX(G$42:G$48)-G46)/(MAX(G$42:G$48)-MIN(G$42:G$48)) | Y46: =(MAX(H$42:H$48)-H46)/(MAX(H$42:H$48)-MIN(H$42:H$48)) | Z46: =(I46-MIN(I$42:I$48))/(MAX(I$42:I$48)-MIN(I$42:I$48)) | AA46: =(J46-MIN(J$42:J$48))/(MAX(J$42:J$48)-MIN(J$42:J$48)) | AB46: =(K46-MIN(K$42:K$48))/(MAX(K$42:K$48)-MIN(K$42:K$48)) | AC46: =(L46-MIN(L$42:L$48))/(MAX(L$42:L$48)-MIN(L$42:L$48)) | AD46: =(M46-MIN(M$42:M$48))/(MAX(M$42:M$48)-MIN(M$42:M$48)) | AE46: =(N46-MIN(N$42:N$48))/(MAX(N$42:N$48)-MIN(N$42:N$48)) | AF46: =(O46-MIN(O$42:O$48))/(MAX(O$42:O$48)-MIN(O$42:O$48)) | AG46: =(P46-MIN(P$42:P$48))/(MAX(P$42:P$48)-MIN(P$42:P$48)) | ... AJ46: =(S46-MIN(S$42:S$48))/(MAX(S$42:S$48)-MIN(S$42:S$48)) | AK46: =(MAX(T$42:T$48)-T46)/(MAX(T$42:T$48)-MIN(T$42:T$48)) | AL46: =(MAX(U$42:U$48)-U46)/(MAX(U$42:U$48)-MIN(U$42:U$48)) | AM46: =(V46-MIN(V$42:V$48))/(MAX(V$42:V$48)-MIN(V$42:V$48)) | AN46: {=SUMPRODUCT(W46:Y46, TRANSPOSE('Fund Ranking Criteria'!$F$39:$F$41))+SUMPRODUCT('Fund Ranking_Debt'!Z46:AG46, TRANSPOSE('Fund Ranking Criteria'!$F$30:$F$37))+SUMPRODUCT('Fund Ranking_Debt'!AH46:AM46, TRANSPOSE('Fund Ranking Criteria'!$F$43:$F$48))}
B47: Nippon India Medium Duration Fund - Reg - Growth | C47: =RANK(AN47,$AN$42:$AN$48,0) | E47: =B47 | F47: 8.07 | G47: 3.29 | H47: 3.45 | I47: 5.43 | J47: 4.3 | K47: 4.52 | L47: 7.08 | M47: 8.44 | N47: 7.64 | O47: 8.87 | P47: 3.23 | Q47: 27.23 | R47: 16.01 | S47: 5.61 | T47: 36.9 | U47: 0 | V47: 14.25 | W47: =(F47-MIN(F$42:F$48))/(MAX(F$42:F$48)-MIN(F$42:F$48)) | X47: =(MAX(G$42:G$48)-G47)/(MAX(G$42:G$48)-MIN(G$42:G$48)) | Y47: =(MAX(H$42:H$48)-H47)/(MAX(H$42:H$48)-MIN(H$42:H$48)) | Z47: =(I47-MIN(I$42:I$48))/(MAX(I$42:I$48)-MIN(I$42:I$48)) | AA47: =(J47-MIN(J$42:J$48))/(MAX(J$42:J$48)-MIN(J$42:J$48)) | AB47: =(K47-MIN(K$42:K$48))/(MAX(K$42:K$48)-MIN(K$42:K$48)) | AC47: =(L47-MIN(L$42:L$48))/(MAX(L$42:L$48)-MIN(L$42:L$48)) | AD47: =(M47-MIN(M$42:M$48))/(MAX(M$42:M$48)-MIN(M$42:M$48)) | AE47: =(N47-MIN(N$42:N$48))/(MAX(N$42:N$48)-MIN(N$42:N$48)) | AF47: =(O47-MIN(O$42:O$48))/(MAX(O$42:O$48)-MIN(O$42:O$48)) | AG47: =(P47-MIN(P$42:P$48))/(MAX(P$42:P$48)-MIN(P$42:P$48)) | ... AJ47: =(S47-MIN(S$42:S$48))/(MAX(S$42:S$48)-MIN(S$42:S$48)) | AK47: =(MAX(T$42:T$48)-T47)/(MAX(T$42:T$48)-MIN(T$42:T$48)) | AL47: =(MAX(U$42:U$48)-U47)/(MAX(U$42:U$48)-MIN(U$42:U$48)) | AM47: =(V47-MIN(V$42:V$48))/(MAX(V$42:V$48)-MIN(V$42:V$48)) | AN47: {=SUMPRODUCT(W47:Y47, TRANSPOSE('Fund Ranking Criteria'!$F$39:$F$41))+SUMPRODUCT('Fund Ranking_Debt'!Z47:AG47, TRANSPOSE('Fund Ranking Criteria'!$F$30:$F$37))+SUMPRODUCT('Fund Ranking_Debt'!AH47:AM47, TRANSPOSE('Fund Ranking Criteria'!$F$43:$F$48))}
B48: UTI Medium Duration Fund - Reg - Growth | C48: =RANK(AN48,$AN$42:$AN$48,0) | E48: =B48 | F48: 7.53 | G48: 3.24 | H48: 3.37 | I48: 3.31 | J48: 2.89 | K48: 3.06 | L48: 3.71 | M48: 6.42 | N48: 6.27 | O48: 5.95 | P48: 5.59 | Q48: 44.29 | R48: 16.19 | S48: 2.48 | T48: 24.65 | U48: 0 | V48: 12.39 | W48: =(F48-MIN(F$42:F$48))/(MAX(F$42:F$48)-MIN(F$42:F$48)) | X48: =(MAX(G$42:G$48)-G48)/(MAX(G$42:G$48)-MIN(G$42:G$48)) | Y48: =(MAX(H$42:H$48)-H48)/(MAX(H$42:H$48)-MIN(H$42:H$48)) | Z48: =(I48-MIN(I$42:I$48))/(MAX(I$42:I$48)-MIN(I$42:I$48)) | AA48: =(J48-MIN(J$42:J$48))/(MAX(J$42:J$48)-MIN(J$42:J$48)) | AB48: =(K48-MIN(K$42:K$48))/(MAX(K$42:K$48)-MIN(K$42:K$48)) | AC48: =(L48-MIN(L$42:L$48))/(MAX(L$42:L$48)-MIN(L$42:L$48)) | AD48: =(M48-MIN(M$42:M$48))/(MAX(M$42:M$48)-MIN(M$42:M$48)) | AE48: =(N48-MIN(N$42:N$48))/(MAX(N$42:N$48)-MIN(N$42:N$48)) | AF48: =(O48-MIN(O$42:O$48))/(MAX(O$42:O$48)-MIN(O$42:O$48)) | AG48: =(P48-MIN(P$42:P$48))/(MAX(P$42:P$48)-MIN(P$42:P$48)) | ... AJ48: =(S48-MIN(S$42:S$48))/(MAX(S$42:S$48)-MIN(S$42:S$48)) | AK48: =(MAX(T$42:T$48)-T48)/(MAX(T$42:T$48)-MIN(T$42:T$48)) | AL48: =(MAX(U$42:U$48)-U48)/(MAX(U$42:U$48)-MIN(U$42:U$48)) | AM48: =(V48-MIN(V$42:V$48))/(MAX(V$42:V$48)-MIN(V$42:V$48)) | AN48: {=SUMPRODUCT(W48:Y48, TRANSPOSE('Fund Ranking Criteria'!$F$39:$F$41))+SUMPRODUCT('Fund Ranking_Debt'!Z48:AG48, TRANSPOSE('Fund Ranking Criteria'!$F$30:$F$37))+SUMPRODUCT('Fund Ranking_Debt'!AH48:AM48, TRANSPOSE('Fund Ranking Criteria'!$F$43:$F$48))}
B50: ='Fund Ranking Criteria'!G24
AN51: Score
B52: Funds | C52: Rank | F52: YTM | G52: Modified Duration | H52: Macaulay Duration | I52: 3 Months | J52: 6 Months | K52: 9 Months | L52: 1 Year | M52: 2 Years | N52: 3 Years | O52: 5 Years | P52: 10 Years | Q52: Sovereign | R52: AAA/A1+ | S52: AA+ | T52: AA/AA- | U52: Below AA- | V52: Cash and Fixed Deposits | W52: =F52 | X52: =G52 | Y52: =H52 | Z52: =I52 | AA52: =J52 | AB52: =K52 | AC52: =L52 | AD52: =M52 | ... AM52: =V52
B53: ICICI Prudential Bond Fund - Growth | C53: =RANK(AN53,$AN$53:$AN$59,0) | E53: =B53 | F53: 7.73 | G53: 5.82 | H53: 6.06 | I53: 1.55 | J53: 1.86 | K53: 1.71 | L53: 2.64 | M53: 6.76 | N53: 6.76 | O53: 5.76 | P53: 6.9 | Q53: 54.9 | R53: 40.1 | S53: 0 | T53: 0 | U53: -14.82 | V53: 5 | W53: =(F53-MIN(F$53:F$59))/(MAX(F$53:F$59)-MIN(F$53:F$59)) | X53: =(MAX(G$53:G$59)-G53)/(MAX(G$53:G$59)-MIN(G$53:G$59)) | Y53: =(MAX(H$53:H$59)-H53)/(MAX(H$53:H$59)-MIN(H$53:H$59)) | Z53: =(I53-MIN(I$53:I$59))/(MAX(I$53:I$59)-MIN(I$53:I$59)) | AA53: =(J53-MIN(J$53:J$59))/(MAX(J$53:J$59)-MIN(J$53:J$59)) | AB53: =(K53-MIN(K$53:K$59))/(MAX(K$53:K$59)-MIN(K$53:K$59)) | AC53: =(L53-MIN(L$53:L$59))/(MAX(L$53:L$59)-MIN(L$53:L$59)) | AD53: =(M53-MIN(M$53:M$59))/(MAX(M$53:M$59)-MIN(M$53:M$59)) | AE53: =(N53-MIN(N$53:N$59))/(MAX(N$53:N$59)-MIN(N$53:N$59)) | AF53: =(O53-MIN(O$53:O$59))/(MAX(O$53:O$59)-MIN(O$53:O$59)) | AG53: =(P53-MIN(P$53:P$59))/(MAX(P$53:P$59)-MIN(P$53:P$59)) | ... AJ53: =(S53-MIN(S$53:S$59))/(MAX(S$53:S$59)-MIN(S$53:S$59)) | AK53: =(MAX(T$53:T$59)-T53)/(MAX(T$53:T$59)-MIN(T$53:T$59)) | AL53: =(MAX(U$53:U$59)-U53)/(MAX(U$53:U$59)-MIN(U$53:U$59)) | AM53: =(V53-MIN(V$53:V$59))/(MAX(V$53:V$59)-MIN(V$53:V$59)) | AN53: {=SUMPRODUCT(W53:Y53, TRANSPOSE('Fund Ranking Criteria'!$G$39:$G$41))+SUMPRODUCT('Fund Ranking_Debt'!Z53:AG53, TRANSPOSE('Fund Ranking Criteria'!$G$30:$G$37))+SUMPRODUCT('Fund Ranking_Debt'!AH53:AM53, TRANSPOSE('Fund Ranking Criteria'!$G$43:$G$48))}
B54: Aditya Birla Sun Life Income Fund - Reg - Growth | C54: =RANK(AN54,$AN$53:$AN$59,0) | E54: =B54 | F54: 7.71 | G54: 6.66 | H54: 6.95 | I54: 1.41 | J54: 0.22 | K54: 0.49 | L54: 0.98 | M54: 5.73 | N54: 5.66 | O54: 5.2 | P54: 6.62 | Q54: 61.31 | R54: 33.73 | S54: 0 | T54: 0 | U54: 0.03 | V54: 4.96 | W54: =(F54-MIN(F$53:F$59))/(MAX(F$53:F$59)-MIN(F$53:F$59)) | X54: =(MAX(G$53:G$59)-G54)/(MAX(G$53:G$59)-MIN(G$53:G$59)) | Y54: =(MAX(H$53:H$59)-H54)/(MAX(H$53:H$59)-MIN(H$53:H$59)) | Z54: =(I54-MIN(I$53:I$59))/(MAX(I$53:I$59)-MIN(I$53:I$59)) | AA54: =(J54-MIN(J$53:J$59))/(MAX(J$53:J$59)-MIN(J$53:J$59)) | AB54: =(K54-MIN(K$53:K$59))/(MAX(K$53:K$59)-MIN(K$53:K$59)) | AC54: =(L54-MIN(L$53:L$59))/(MAX(L$53:L$59)-MIN(L$53:L$59)) | AD54: =(M54-MIN(M$53:M$59))/(MAX(M$53:M$59)-MIN(M$53:M$59)) | AE54: =(N54-MIN(N$53:N$59))/(MAX(N$53:N$59)-MIN(N$53:N$59)) | AF54: =(O54-MIN(O$53:O$59))/(MAX(O$53:O$59)-MIN(O$53:O$59)) | AG54: =(P54-MIN(P$53:P$59))/(MAX(P$53:P$59)-MIN(P$53:P$59)) | ... AJ54: =(S54-MIN(S$53:S$59))/(MAX(S$53:S$59)-MIN(S$53:S$59)) | AK54: =(MAX(T$53:T$59)-T54)/(MAX(T$53:T$59)-MIN(T$53:T$59)) | AL54: =(MAX(U$53:U$59)-U54)/(MAX(U$53:U$59)-MIN(U$53:U$59)) | AM54: =(V54-MIN(V$53:V$59))/(MAX(V$53:V$59)-MIN(V$53:V$59)) | AN54: {=SUMPRODUCT(W54:Y54, TRANSPOSE('Fund Ranking Criteria'!$G$39:$G$41))+SUMPRODUCT('Fund Ranking_Debt'!Z54:AG54, TRANSPOSE('Fund Ranking Criteria'!$G$30:$G$37))+SUMPRODUCT('Fund Ranking_Debt'!AH54:AM54, TRANSPOSE('Fund Ranking Criteria'!$G$43:$G$48))}
B55: Kotak Bond Fund - Reg - Growth | C55: =RANK(AN55,$AN$53:$AN$59,0) | E55: =B55 | F55: 7.69 | G55: 5.91 | H55: 6.14 | I55: 1.86 | J55: 0.9 | K55: 1.09 | L55: 1.62 | M55: 5.79 | N55: 5.87 | O55: 5.13 | P55: 6.21 | Q55: 59.32 | R55: 34.17 | S55: 0 | T55: 0 | U55: 0 | V55: 6.52 | W55: =(F55-MIN(F$53:F$59))/(MAX(F$53:F$59)-MIN(F$53:F$59)) | X55: =(MAX(G$53:G$59)-G55)/(MAX(G$53:G$59)-MIN(G$53:G$59)) | Y55: =(MAX(H$53:H$59)-H55)/(MAX(H$53:H$59)-MIN(H$53:H$59)) | Z55: =(I55-MIN(I$53:I$59))/(MAX(I$53:I$59)-MIN(I$53:I$59)) | AA55: =(J55-MIN(J$53:J$59))/(MAX(J$53:J$59)-MIN(J$53:J$59)) | AB55: =(K55-MIN(K$53:K$59))/(MAX(K$53:K$59)-MIN(K$53:K$59)) | AC55: =(L55-MIN(L$53:L$59))/(MAX(L$53:L$59)-MIN(L$53:L$59)) | AD55: =(M55-MIN(M$53:M$59))/(MAX(M$53:M$59)-MIN(M$53:M$59)) | AE55: =(N55-MIN(N$53:N$59))/(MAX(N$53:N$59)-MIN(N$53:N$59)) | AF55: =(O55-MIN(O$53:O$59))/(MAX(O$53:O$59)-MIN(O$53:O$59)) | AG55: =(P55-MIN(P$53:P$59))/(MAX(P$53:P$59)-MIN(P$53:P$59)) | ... AJ55: =(S55-MIN(S$53:S$59))/(MAX(S$53:S$59)-MIN(S$53:S$59)) | AK55: =(MAX(T$53:T$59)-T55)/(MAX(T$53:T$59)-MIN(T$53:T$59)) | AL55: =(MAX(U$53:U$59)-U55)/(MAX(U$53:U$59)-MIN(U$53:U$59)) | AM55: =(V55-MIN(V$53:V$59))/(MAX(V$53:V$59)-MIN(V$53:V$59)) | AN55: {=SUMPRODUCT(W55:Y55, TRANSPOSE('Fund Ranking Criteria'!$G$39:$G$41))+SUMPRODUCT('Fund Ranking_Debt'!Z55:AG55, TRANSPOSE('Fund Ranking Criteria'!$G$30:$G$37))+SUMPRODUCT('Fund Ranking_Debt'!AH55:AM55, TRANSPOSE('Fund Ranking Criteria'!$G$43:$G$48))}
